Workbook
Name ARTICLE: _xlfn.ANCHORARRAY(ARTICLE!$A$2)
Name COMPO: 'MATRICE COMPO'!$A$2:$A$199
Name COMPOSITION: _xlfn.ANCHORARRAY(COMPOSITION!$A$2)
Name COMPOSITIONS: COMPOSITION!$B$1:$I$91
Name ETAPE: _xlfn.ANCHORARRAY('MAIN D OEUVRE'!$G$4)
Name MATERIAUX: _xlfn.ANCHORARRAY(MATERIAUX!$A$3)
Name MATRICE_ARTICLE: ARTICLE!$B:$O
Name MATRICE_COMPOSITION: COMPOSITION!$B:$N
Name MATRICE_MATERIAUX: MATERIAUX!$C:$AM
Name MATRICE_SERVICE: SERVICE!$B:$N
Name PAVAWALL_40_mm___OSB_8___STRUCT_150_mm___IZOLATIE_LEMN_150_mm___FOLIE___OSB_15: 'MATRICE COMPO'!$A$3:$A$199
Name PRESTATION: GESTION!$E$2:$E$9
Name SERVICE: _xlfn.ANCHORARRAY(SERVICE!$A$2)

Sheet GESTION
A1: PARAMETRE DE CHIFFRAGE | B1: VALEUR | C1: Unité | E1: PRESTATION | F1: MATRICE
A2: Déboursé horaire | B2: 22 | C2: €/hr | E2: SERVICE | F2: MATRICE_SERVICE
A3: Frais généraux | B3: 0.1 | C3: pourcent | E3: COMPOSITION | F3: MATRICE_COMPOSITION
A4: Bénéfice Article/compo | B4: 0.3 | C4: pourcent | E4: ARTICLE | F4: MATRICE_ARTICLE
A5: Bénéfice vente matériaux | B5: 0.2 | C5: pourcent | E5: MATERIAUX | F5: MATRICE_MATERIAUX
A6: Bénéfice Service | B6: 0 | C6: pourcent
A7: Conversion Lei --> Euro | B7: 4.85 | C7: Lei/€
A8: Conversion Euro --> Lei | B8: =1/B7 -> 0.20618557 | C8: €/Lei
A9: Quincaillerie | B9: 0.07 | C9: % de CA €

Sheet SERVICE
A1: Liste déroulante: | B1: COMPOSITION | C1: ID | D1: Unité | E1: Prix net | F1: Prix brut | G1: =GESTION!B6 -> 0 | H1: =GESTION!B3 -> 0.1
A2: {=_xlfn.UNIQUE(_xlfn._xlws.FILTER(B2:B1000,NOT(ISBLANK(B2:B1000))))} -> Etude Loftwood Construction | B2: Etude Loftwood Construction | D2: ens | E2: =IFERROR(F2+G2+H2,"") -> 660 | F2: 600 | G2: =IF(B2="","",F2*$G$1) -> 0 | H2: =IFERROR((F2+G2)*$H$1,"") -> 60
A3: Transport Camion standard | B3: Transport Camion standard | D3: ft | E3: =IFERROR(F3+G3+H3,"") -> 3850 | F3: 3500 | G3: =IF(B3="","",F3*$G$1) -> 0 | H3: =IFERROR((F3+G3)*$H$1,"") -> 350
A4: Transport Camion Mega | B4: Transport Camion Mega | D4: ft | E4: =IFERROR(F4+G4+H4,"") -> 4235 | F4: =F3*1.1 -> 3850 | G4: =IF(B4="","",F4*$G$1) -> 0 | H4: =IFERROR((F4+G4)*$H$1,"") -> 385
A5: Charpente industrielle | B5: Charpente industrielle | D5: m2 | E5: =IFERROR(F5+G5+H5,"") -> 38.5 | F5: 35 | G5: =IF(B5="","",F5*$G$1) -> 0 | H5: =IFERROR((F5+G5)*$H$1,"") -> 3.5
A6: Forfait quincaillerie | B6: Forfait quincaillerie | D6: ft | E6: =IFERROR(F6+G6+H6,"") -> 1100 | F6: 1000 | G6: =IF(B6="","",F6*$G$1) -> 0 | H6: =IFERROR((F6+G6)*$H$1,"") -> 100
A7: PSE CHANTIER | B7: PSE CHANTIER | D7: m2 | E7: =IFERROR(F7+G7+H7,"") -> 27.753 | F7: 25.23 | G7: =IF(B7="","",F7*$G$1) -> 0 | H7: =IFERROR((F7+G7)*$H$1,"") -> 2.523
A8: Transport camion tandem VAR (83) | B8: Transport camion tandem VAR (83) | D8: ft | E8: =IFERROR(F8+G8+H8,"") -> 2530 | F8: 2300 | G8: =IF(B8="","",F8*$G$1) -> 0 | H8: =IFERROR((F8+G8)*$H$1,"") -> 230 | I8: Reste a etre validee a la demande, en principe est 1,3 Euro / Km
A9: Transport camion standard BOUCHE-DU-RHONE (13) | B9: Transport camion standard BOUCHE-DU-RHONE (13) | D9: ft | E9: =IFERROR(F9+G9+H9,"") -> 2200 | F9: 2000 | G9: =IF(B9="","",F9*$G$1) -> 0 | H9: =IFERROR((F9+G9)*$H$1,"") -> 200
A10: Transport camion standard ISERE (38) | B10: Transport camion standard ISERE (38) | D10: ft | E10: =IFERROR(F10+G10+H10,"") -> 2530 | F10: 2300 | G10: =IF(B10="","",F10*$G$1) -> 0 | H10: =IFERROR((F10+G10)*$H$1,"") -> 230
A11: Déplacement | B11: Déplacement | D11: ft | E11: =IFERROR(F11+G11+H11,"") -> 1430 | F11: 1300 | G11: =IF(B11="","",F11*$G$1) -> 0 | H11: =IFERROR((F11+G11)*$H$1,"") -> 130
A12: Logement | B12: Logement | D12: j | E12: =IFERROR(F12+G12+H12,"") -> 165 | F12: =50*3 -> 150 | G12: =IF(B12="","",F12*$G$1) -> 0 | H12: =IFERROR((F12+G12)*$H$1,"") -> 15
A13: Montage chantier | B13: Montage chantier | D13: j | E13: =IFERROR(F13+G13+H13,"") -> 997.92 | F13: =37.8*3*8 -> 907.2 | G13: =IF(B13="","",F13*$G$1) -> 0 | H13: =IFERROR((F13+G13)*$H$1,"") -> 90.72
A14: Engin de levage | B14: Engin de levage | D14: ens | E14: =IFERROR(F14+G14+H14,"") -> 5720 | F14: =130*8*5 -> 5200 | G14: =IF(B14="","",F14*$G$1) -> 0 | H14: =IFERROR((F14+G14)*$H$1,"") -> 520
A15: Transport standard (75) | B15: Transport standard (75) | D15: ft | E15: =IFERROR(F15+G15+H15,"") -> 3146 | F15: =1.3*2200 -> 2860 | G15: =IF(B15="","",F15*$G$1) -> 0 | H15: =IFERROR((F15+G15)*$H$1,"") -> 286
A16: Déplacement (75) | B16: Déplacement (75) | D16: ft | E16: =IFERROR(F16+G16+H16,"") -> 2347.84 | F16: =2*(160+37.8*3*8) -> 2134.4 | G16: =IF(B16="","",F16*$G$1) -> 0 | H16: =IFERROR((F16+G16)*$H$1,"") -> 213.44
D17: =IFERROR(VLOOKUP(A17,'MATRICE COMPO'!$A:$H,3,FALSE),"") | E17: =IFERROR(F17+G17+H17,"") | G17: =IF(B17="","",F17*$G$1) | H17: =IFERROR((F17+G17)*$H$1,"")
D18: =IFERROR(VLOOKUP(A18,'MATRICE COMPO'!$A:$H,3,FALSE),"") | E18: =IFERROR(F18+G18+H18,"") | G18: =IF(B18="","",F18*$G$1) | H18: =IFERROR((F18+G18)*$H$1,"")
D19: =IFERROR(VLOOKUP(A19,'MATRICE COMPO'!$A:$H,3,FALSE),"") | E19: =IFERROR(F19+G19+H19,"") | G19: =IF(B19="","",F19*$G$1) | H19: =IFERROR((F19+G19)*$H$1,"")
D20: =IFERROR(VLOOKUP(A20,'MATRICE COMPO'!$A:$H,3,FALSE),"") | E20: =IFERROR(F20+G20+H20,"") | G20: =IF(B20="","",F20*$G$1) | H20: =IFERROR((F20+G20)*$H$1,"")
D21: =IFERROR(VLOOKUP(A21,'MATRICE COMPO'!$A:$H,3,FALSE),"") | E21: =IFERROR(F21+G21+H21,"") | G21: =IF(B21="","",F21*$G$1) | H21: =IFERROR((F21+G21)*$H$1,"")
D22: =IFERROR(VLOOKUP(A22,'MATRICE COMPO'!$A:$H,3,FALSE),"") | E22: =IFERROR(F22+G22+H22,"") | G22: =IF(B22="","",F22*$G$1) | H22: =IFERROR((F22+G22)*$H$1,"")
D23: =IFERROR(VLOOKUP(A23,'MATRICE COMPO'!$A:$H,3,FALSE),"") | E23: =IFERROR(F23+G23+H23,"") | G23: =IF(B23="","",F23*$G$1) | H23: =IFERROR((F23+G23)*$H$1,"")
D24: =IFERROR(VLOOKUP(A24,'MATRICE COMPO'!$A:$H,3,FALSE),"") | E24: =IFERROR(F24+G24+H24,"") | G24: =IF(B24="","",F24*$G$1) | H24: =IFERROR((F24+G24)*$H$1,"")
D25: =IFERROR(VLOOKUP(A25,'MATRICE COMPO'!$A:$H,3,FALSE),"") | E25: =IFERROR(F25+G25+H25,"") | G25: =IF(B25="","",F25*$G$1) | H25: =IFERROR((F25+G25)*$H$1,"")
D26: =IFERROR(VLOOKUP(A26,'MATRICE COMPO'!$A:$H,3,FALSE),"") | E26: =IFERROR(F26+G26+H26,"") | G26: =IF(B26="","",F26*$G$1) | H26: =IFERROR((F26+G26)*$H$1,"")
D27: =IFERROR(VLOOKUP(A27,'MATRICE COMPO'!$A:$H,3,FALSE),"") | E27: =IFERROR(F27+G27+H27,"") | G27: =IF(B27="","",F27*$G$1) | H27: =IFERROR((F27+G27)*$H$1,"")
D28: =IFERROR(VLOOKUP(A28,'MATRICE COMPO'!$A:$H,3,FALSE),"") | E28: =IFERROR(F28+G28+H28,"") | G28: =IF(B28="","",F28*$G$1) | H28: =IFERROR((F28+G28)*$H$1,"")
... D91: =IFERROR(VLOOKUP(A91,'MATRICE COMPO'!$A:$H,3,FALSE),"") | E91: =IFERROR(F91+G91+H91,"") | G91: =IF(B91="","",F91*$G$1) | H91: =IFERROR((F91+G91)*$H$1,"")

Sheet COMPOSITION
A1: Liste déroulante: | B1: COMPOSITION | C1: ID | D1: Unité | E1: PRIX / U | F1: MAT | G1: MO | H1: =GESTION!B4 -> 0.3 | I1: =GESTION!B3 -> 0.1
A2: {=_xlfn.UNIQUE(_xlfn._xlws.FILTER('MATRICE COMPO'!A2:A199,NOT(ISBLANK('MATRICE COMPO'!A2:A199))))} -> Pare-vapeur SD 90 / Structure 145 mm / Laine minérale 150 mm / OSB 12 / Bache de protection provisoire | B2: =IF(A2=0,"",A2) -> Pare-vapeur SD 90 / Structure 145 mm / Laine minérale 150 mm / OSB 12 / Bache de protection provisoire | C2: =IF($B2="","",VLOOKUP($B2,'MATRICE COMPO'!$A:$I,9,FALSE)) -> PE-15 | D2: =IFERROR(VLOOKUP(A2,'MATRICE COMPO'!$A:$H,3,FALSE),"") -> m2 | E2: =IF(B2="","",VLOOKUP(B2,'MATRICE COMPO'!$A:$H,4,FALSE)) -> 83.133938 | F2: =IF(B2="","",VLOOKUP($B2,'MATRICE COMPO'!$A:$H,5,FALSE)) -> 50.215621 | G2: =IF($B2="","",VLOOKUP($B2,'MATRICE COMPO'!$A:$H,6,FALSE)) -> 7.92 | H2: =IF($B2="","",VLOOKUP($B2,'MATRICE COMPO'!$A:$H,7,FALSE)) -> 17.440686 | I2: =IF($B2="","",VLOOKUP($B2,'MATRICE COMPO'!$A:$H,8,FALSE)) -> 7.5576307
A3: Structure 100 mm / OSB 12 / Bache de protection provisoire / Pignon | B3: =IF(A3=0,"",A3) -> Structure 100 mm / OSB 12 / Bache de protection provisoire / Pignon | C3: =IF($B3="","",VLOOKUP($B3,'MATRICE COMPO'!$A:$I,9,FALSE)) -> PEST-10 | D3: =IFERROR(VLOOKUP(A3,'MATRICE COMPO'!$A:$H,3,FALSE),"") -> m2 | E3: =IF(B3="","",VLOOKUP(B3,'MATRICE COMPO'!$A:$H,4,FALSE)) -> 63.852748 | F3: =IF(B3="","",VLOOKUP($B3,'MATRICE COMPO'!$A:$H,5,FALSE)) -> 27.002271 | G3: =IF($B3="","",VLOOKUP($B3,'MATRICE COMPO'!$A:$H,6,FALSE)) -> 17.65 | H3: =IF($B3="","",VLOOKUP($B3,'MATRICE COMPO'!$A:$H,7,FALSE)) -> 13.395681 | I3: =IF($B3="","",VLOOKUP($B3,'MATRICE COMPO'!$A:$H,8,FALSE)) -> 5.8047952
A4: Structure 100 mm / Bardage horizontal cl4 | B4: =IF(A4=0,"",A4) -> Structure 100 mm / Bardage horizontal cl4 | C4: =IF($B4="","",VLOOKUP($B4,'MATRICE COMPO'!$A:$I,9,FALSE)) -> PEST-10-BARDAGE | D4: =IFERROR(VLOOKUP(A4,'MATRICE COMPO'!$A:$H,3,FALSE),"") -> m2 | E4: =IF(B4="","",VLOOKUP(B4,'MATRICE COMPO'!$A:$H,4,FALSE)) -> 61.764948 | F4: =IF(B4="","",VLOOKUP($B4,'MATRICE COMPO'!$A:$H,5,FALSE)) -> 36.342271 | G4: =IF($B4="","",VLOOKUP($B4,'MATRICE COMPO'!$A:$H,6,FALSE)) -> 6.85 | H4: =IF($B4="","",VLOOKUP($B4,'MATRICE COMPO'!$A:$H,7,FALSE)) -> 12.957681 | I4: =IF($B4="","",VLOOKUP($B4,'MATRICE COMPO'!$A:$H,8,FALSE)) -> 5.6149952
A5: Structure 100 mm / Bardage horizontal cl4 / Pignon | B5: =IF(A5=0,"",A5) -> Structure 100 mm / Bardage horizontal cl4 / Pignon | C5: =IF($B5="","",VLOOKUP($B5,'MATRICE COMPO'!$A:$I,9,FALSE)) -> PEST-10-BARDAGE PIGNON | D5: =IFERROR(VLOOKUP(A5,'MATRICE COMPO'!$A:$H,3,FALSE),"") -> m2 | E5: =IF(B5="","",VLOOKUP(B5,'MATRICE COMPO'!$A:$H,4,FALSE)) -> 79.468348 | F5: =IF(B5="","",VLOOKUP($B5,'MATRICE COMPO'!$A:$H,5,FALSE)) -> 36.342271 | G5: =IF($B5="","",VLOOKUP($B5,'MATRICE COMPO'!$A:$H,6,FALSE)) -> 19.23 | H5: =IF($B5="","",VLOOKUP($B5,'MATRICE COMPO'!$A:$H,7,FALSE)) -> 16.671681 | I5: =IF($B5="","",VLOOKUP($B5,'MATRICE COMPO'!$A:$H,8,FALSE)) -> 7.2243952
A6: OSB 22 / Structure PP 260-625 | B6: =IF(A6=0,"",A6) -> OSB 22 / Structure PP 260-625 | C6: =IF($B6="","",VLOOKUP($B6,'MATRICE COMPO'!$A:$I,9,FALSE)) -> PP-625 | D6: =IFERROR(VLOOKUP(A6,'MATRICE COMPO'!$A:$H,3,FALSE),"") -> m2 | E6: =IF(B6="","",VLOOKUP(B6,'MATRICE COMPO'!$A:$H,4,FALSE)) -> 62.557923 | F6: =IF(B6="","",VLOOKUP($B6,'MATRICE COMPO'!$A:$H,5,FALSE)) -> 36.636799 | G6: =IF($B6="","",VLOOKUP($B6,'MATRICE COMPO'!$A:$H,6,FALSE)) -> 7.11 | H6: =IF($B6="","",VLOOKUP($B6,'MATRICE COMPO'!$A:$H,7,FALSE)) -> 13.12404 | I6: =IF($B6="","",VLOOKUP($B6,'MATRICE COMPO'!$A:$H,8,FALSE)) -> 5.6870839
A7: OSB 22 / Structure PP 260-313 | B7: =IF(A7=0,"",A7) -> OSB 22 / Structure PP 260-313 | C7: =IF($B7="","",VLOOKUP($B7,'MATRICE COMPO'!$A:$I,9,FALSE)) -> PP-313 | D7: =IFERROR(VLOOKUP(A7,'MATRICE COMPO'!$A:$H,3,FALSE),"") -> m2 | E7: =IF(B7="","",VLOOKUP(B7,'MATRICE COMPO'!$A:$H,4,FALSE)) -> 81.405737 | F7: =IF(B7="","",VLOOKUP($B7,'MATRICE COMPO'!$A:$H,5,FALSE)) -> 46.887089 | G7: =IF($B7="","",VLOOKUP($B7,'MATRICE COMPO'!$A:$H,6,FALSE)) -> 10.04 | H7: =IF($B7="","",VLOOKUP($B7,'MATRICE COMPO'!$A:$H,7,FALSE)) -> 17.078127 | I7: =IF($B7="","",VLOOKUP($B7,'MATRICE COMPO'!$A:$H,8,FALSE)) -> 7.4005216
B8: =IF(A8=0,"",A8) | C8: =IF($B8="","",VLOOKUP($B8,'MATRICE COMPO'!$A:$I,9,FALSE)) | D8: =IFERROR(VLOOKUP(A8,'MATRICE COMPO'!$A:$H,3,FALSE),"") | E8: =IF(B8="","",VLOOKUP(B8,'MATRICE COMPO'!$A:$H,4,FALSE)) | F8: =IF(B8="","",VLOOKUP($B8,'MATRICE COMPO'!$A:$H,5,FALSE)) | G8: =IF($B8="","",VLOOKUP($B8,'MATRICE COMPO'!$A:$H,6,FALSE)) | H8: =IF($B8="","",VLOOKUP($B8,'MATRICE COMPO'!$A:$H,7,FALSE)) | I8: =IF($B8="","",VLOOKUP($B8,'MATRICE COMPO'!$A:$H,8,FALSE))
B9: =IF(A9=0,"",A9) | C9: =IF($B9="","",VLOOKUP($B9,'MATRICE COMPO'!$A:$I,9,FALSE)) | D9: =IFERROR(VLOOKUP(A9,'MATRICE COMPO'!$A:$H,3,FALSE),"") | E9: =IF(B9="","",VLOOKUP(B9,'MATRICE COMPO'!$A:$H,4,FALSE)) | F9: =IF(B9="","",VLOOKUP($B9,'MATRICE COMPO'!$A:$H,5,FALSE)) | G9: =IF($B9="","",VLOOKUP($B9,'MATRICE COMPO'!$A:$H,6,FALSE)) | H9: =IF($B9="","",VLOOKUP($B9,'MATRICE COMPO'!$A:$H,7,FALSE)) | I9: =IF($B9="","",VLOOKUP($B9,'MATRICE COMPO'!$A:$H,8,FALSE))
B10: =IF(A10=0,"",A10) | C10: =IF($B10="","",VLOOKUP($B10,'MATRICE COMPO'!$A:$I,9,FALSE)) | D10: =IFERROR(VLOOKUP(A10,'MATRICE COMPO'!$A:$H,3,FALSE),"") | E10: =IF(B10="","",VLOOKUP(B10,'MATRICE COMPO'!$A:$H,4,FALSE)) | F10: =IF(B10="","",VLOOKUP($B10,'MATRICE COMPO'!$A:$H,5,FALSE)) | G10: =IF($B10="","",VLOOKUP($B10,'MATRICE COMPO'!$A:$H,6,FALSE)) | H10: =IF($B10="","",VLOOKUP($B10,'MATRICE COMPO'!$A:$H,7,FALSE)) | I10: =IF($B10="","",VLOOKUP($B10,'MATRICE COMPO'!$A:$H,8,FALSE))
B11: =IF(A11=0,"",A11) | C11: =IF($B11="","",VLOOKUP($B11,'MATRICE COMPO'!$A:$I,9,FALSE)) | D11: =IFERROR(VLOOKUP(A11,'MATRICE COMPO'!$A:$H,3,FALSE),"") | E11: =IF(B11="","",VLOOKUP(B11,'MATRICE COMPO'!$A:$H,4,FALSE)) | F11: =IF(B11="","",VLOOKUP($B11,'MATRICE COMPO'!$A:$H,5,FALSE)) | G11: =IF($B11="","",VLOOKUP($B11,'MATRICE COMPO'!$A:$H,6,FALSE)) | H11: =IF($B11="","",VLOOKUP($B11,'MATRICE COMPO'!$A:$H,7,FALSE)) | I11: =IF($B11="","",VLOOKUP($B11,'MATRICE COMPO'!$A:$H,8,FALSE))
B12: =IF(A12=0,"",A12) | C12: =IF($B12="","",VLOOKUP($B12,'MATRICE COMPO'!$A:$I,9,FALSE)) | D12: =IFERROR(VLOOKUP(A12,'MATRICE COMPO'!$A:$H,3,FALSE),"") | E12: =IF(B12="","",VLOOKUP(B12,'MATRICE COMPO'!$A:$H,4,FALSE)) | F12: =IF(B12="","",VLOOKUP($B12,'MATRICE COMPO'!$A:$H,5,FALSE)) | G12: =IF($B12="","",VLOOKUP($B12,'MATRICE COMPO'!$A:$H,6,FALSE)) | H12: =IF($B12="","",VLOOKUP($B12,'MATRICE COMPO'!$A:$H,7,FALSE)) | I12: =IF($B12="","",VLOOKUP($B12,'MATRICE COMPO'!$A:$H,8,FALSE))
B13: =IF(A13=0,"",A13) | C13: =IF($B13="","",VLOOKUP($B13,'MATRICE COMPO'!$A:$I,9,FALSE)) | D13: =IFERROR(VLOOKUP(A13,'MATRICE COMPO'!$A:$H,3,FALSE),"") | E13: =IF(B13="","",VLOOKUP(B13,'MATRICE COMPO'!$A:$H,4,FALSE)) | F13: =IF(B13="","",VLOOKUP($B13,'MATRICE COMPO'!$A:$H,5,FALSE)) | G13: =IF($B13="","",VLOOKUP($B13,'MATRICE COMPO'!$A:$H,6,FALSE)) | H13: =IF($B13="","",VLOOKUP($B13,'MATRICE COMPO'!$A:$H,7,FALSE)) | I13: =IF($B13="","",VLOOKUP($B13,'MATRICE COMPO'!$A:$H,8,FALSE))
B14: =IF(A14=0,"",A14) | C14: =IF($B14="","",VLOOKUP($B14,'MATRICE COMPO'!$A:$I,9,FALSE)) | D14: =IFERROR(VLOOKUP(A14,'MATRICE COMPO'!$A:$H,3,FALSE),"") | E14: =IF(B14="","",VLOOKUP(B14,'MATRICE COMPO'!$A:$H,4,FALSE)) | F14: =IF(B14="","",VLOOKUP($B14,'MATRICE COMPO'!$A:$H,5,FALSE)) | G14: =IF($B14="","",VLOOKUP($B14,'MATRICE COMPO'!$A:$H,6,FALSE)) | H14: =IF($B14="","",VLOOKUP($B14,'MATRICE COMPO'!$A:$H,7,FALSE)) | I14: =IF($B14="","",VLOOKUP($B14,'MATRICE COMPO'!$A:$H,8,FALSE))
B15: =IF(A15=0,"",A15) | C15: =IF($B15="","",VLOOKUP($B15,'MATRICE COMPO'!$A:$I,9,FALSE)) | D15: =IFERROR(VLOOKUP(A15,'MATRICE COMPO'!$A:$H,3,FALSE),"") | E15: =IF(B15="","",VLOOKUP(B15,'MATRICE COMPO'!$A:$H,4,FALSE)) | F15: =IF(B15="","",VLOOKUP($B15,'MATRICE COMPO'!$A:$H,5,FALSE)) | G15: =IF($B15="","",VLOOKUP($B15,'MATRICE COMPO'!$A:$H,6,FALSE)) | H15: =IF($B15="","",VLOOKUP($B15,'MATRICE COMPO'!$A:$H,7,FALSE)) | I15: =IF($B15="","",VLOOKUP($B15,'MATRICE COMPO'!$A:$H,8,FALSE))
B16: =IF(A16=0,"",A16) | C16: =IF($B16="","",VLOOKUP($B16,'MATRICE COMPO'!$A:$I,9,FALSE)) | D16: =IFERROR(VLOOKUP(A16,'MATRICE COMPO'!$A:$H,3,FALSE),"") | E16: =IF(B16="","",VLOOKUP(B16,'MATRICE COMPO'!$A:$H,4,FALSE)) | F16: =IF(B16="","",VLOOKUP($B16,'MATRICE COMPO'!$A:$H,5,FALSE)) | G16: =IF($B16="","",VLOOKUP($B16,'MATRICE COMPO'!$A:$H,6,FALSE)) | H16: =IF($B16="","",VLOOKUP($B16,'MATRICE COMPO'!$A:$H,7,FALSE)) | I16: =IF($B16="","",VLOOKUP($B16,'MATRICE COMPO'!$A:$H,8,FALSE))
B17: =IF(A17=0,"",A17) | C17: =IF($B17="","",VLOOKUP($B17,'MATRICE COMPO'!$A:$I,9,FALSE)) | D17: =IFERROR(VLOOKUP(A17,'MATRICE COMPO'!$A:$H,3,FALSE),"") | E17: =IF(B17="","",VLOOKUP(B17,'MATRICE COMPO'!$A:$H,4,FALSE)) | F17: =IF(B17="","",VLOOKUP($B17,'MATRICE COMPO'!$A:$H,5,FALSE)) | G17: =IF($B17="","",VLOOKUP($B17,'MATRICE COMPO'!$A:$H,6,FALSE)) | H17: =IF($B17="","",VLOOKUP($B17,'MATRICE COMPO'!$A:$H,7,FALSE)) | I17: =IF($B17="","",VLOOKUP($B17,'MATRICE COMPO'!$A:$H,8,FALSE))
B18: =IF(A18=0,"",A18) | C18: =IF($B18="","",VLOOKUP($B18,'MATRICE COMPO'!$A:$I,9,FALSE)) | D18: =IFERROR(VLOOKUP(A18,'MATRICE COMPO'!$A:$H,3,FALSE),"") | E18: =IF(B18="","",VLOOKUP(B18,'MATRICE COMPO'!$A:$H,4,FALSE)) | F18: =IF(B18="","",VLOOKUP($B18,'MATRICE COMPO'!$A:$H,5,FALSE)) | G18: =IF($B18="","",VLOOKUP($B18,'MATRICE COMPO'!$A:$H,6,FALSE)) | H18: =IF($B18="","",VLOOKUP($B18,'MATRICE COMPO'!$A:$H,7,FALSE)) | I18: =IF($B18="","",VLOOKUP($B18,'MATRICE COMPO'!$A:$H,8,FALSE))
B19: =IF(A19=0,"",A19) | C19: =IF($B19="","",VLOOKUP($B19,'MATRICE COMPO'!$A:$I,9,FALSE)) | D19: =IFERROR(VLOOKUP(A19,'MATRICE COMPO'!$A:$H,3,FALSE),"") | E19: =IF(B19="","",VLOOKUP(B19,'MATRICE COMPO'!$A:$H,4,FALSE)) | F19: =IF(B19="","",VLOOKUP($B19,'MATRICE COMPO'!$A:$H,5,FALSE)) | G19: =IF($B19="","",VLOOKUP($B19,'MATRICE COMPO'!$A:$H,6,FALSE)) | H19: =IF($B19="","",VLOOKUP($B19,'MATRICE COMPO'!$A:$H,7,FALSE)) | I19: =IF($B19="","",VLOOKUP($B19,'MATRICE COMPO'!$A:$H,8,FALSE))
... B91: =IF(A91=0,"",A91) | C91: =IF($B91="","",VLOOKUP($B91,'MATRICE COMPO'!$A:$I,9,FALSE)) | D91: =IFERROR(VLOOKUP(A91,'MATRICE COMPO'!$A:$H,3,FALSE),"") | E91: =IF(B91="","",VLOOKUP(B91,'MATRICE COMPO'!$A:$H,4,FALSE)) | F91: =IF(B91="","",VLOOKUP($B91,'MATRICE COMPO'!$A:$H,5,FALSE)) | G91: =IF($B91="","",VLOOKUP($B91,'MATRICE COMPO'!$A:$H,6,FALSE)) | H91: =IF($B91="","",VLOOKUP($B91,'MATRICE COMPO'!$A:$H,7,FALSE)) | I91: =IF($B91="","",VLOOKUP($B91,'MATRICE COMPO'!$A:$H,8,FALSE))

Sheet MATRICE COMPO
A1: COMPOSITION | C1: Unité | D1: PRIX | E1: MAT | F1: MO | G1: =GESTION!$B$4 -> 0.3 | H1: =GESTION!$B$3 -> 0.1 | I1: ID | K1: Valeur | L1: MAT | N1: MO | P1: Marge | R1: FG
A2: =B2 -> Pare-vapeur SD 90 / Structure 145 mm / Laine minérale 150 mm / OSB 12 / Bache de protection provisoire | B2: =CONCATENATE(B3,IF(B4="",""," / "),B4,IF(B5="",""," / "),B5,IF(B6="",""," / "),B6,IF(B7="",""," / "),B7,IF(B8="",""," / "),B8,IF(B9="",""," / "),B9,B9,IF(B10="",""," / "),B10,IF(B11="",""," / "),B11,IF(B12="",""," / "),B12) -> Pare-vapeur SD 90 / Structure 145 mm / Laine minérale 150 mm / OSB 12 / Bache de protection provisoire | C2: =C3 -> m2 | D2: =IF(SUM(E2:H2)=0,0,SUM(E2:H2)) -> 83.133938 | E2: =SUM(E3:E12) -> 50.215621 | F2: =SUM(F3:F12) -> 7.92 | G2: =SUM(G3:G12) -> 17.440686 | H2: =SUM(H3:H12) -> 7.5576307 | I2: PE-15 | J2: =716+757 -> 1473 | K2: =ROUNDUP(D2,0)*J2 -> 123732 | L2: =ROUNDUP(J2*E2,0) -> 73968 | M2: =L2/K2 -> 0.59780817 | N2: =ROUNDUP(J2*F2,0) -> 11667 | O2: =N2/K2 -> 0.094292503 | P2: =ROUNDUP(J2*G2,0) -> 25691 | Q2: =P2/K2 -> 0.20763424 | R2: =ROUNDUP(J2*H2,0) -> 11133 | S2: =R2/K2 -> 0.089976724
B3: Pare-vapeur SD 90 | C3: =IFERROR(IF(ISBLANK(VLOOKUP($B3,ARTICLE!$B$2:$J$200,3,FALSE)),"",VLOOKUP($B3,ARTICLE!$B$2:$J$200,3,FALSE)),"") -> m2 | D3: =IFERROR(IF(ISBLANK(VLOOKUP($B3,ARTICLE!$B$2:$J$200,4,FALSE)),"",VLOOKUP($B3,ARTICLE!$B$2:$J$200,4,FALSE)),"") -> 3.8181 | E3: =IFERROR(IF(ISBLANK(VLOOKUP($B3,ARTICLE!$B$2:$J$200,5,FALSE)),"",VLOOKUP($B3,ARTICLE!$B$2:$J$200,5,FALSE)),"") -> 2.06 | F3: =IFERROR(IF(ISBLANK(VLOOKUP($B3,ARTICLE!$B$2:$J$200,6,FALSE)),"",VLOOKUP($B3,ARTICLE!$B$2:$J$200,6,FALSE)),"") -> 0.61 | G3: =IFERROR(IF(ISBLANK(VLOOKUP($B3,ARTICLE!$B$2:$J$200,7,FALSE)),"",VLOOKUP($B3,ARTICLE!$B$2:$J$200,7,FALSE)),"") -> 0.801 | H3: =IFERROR(IF(ISBLANK(VLOOKUP($B3,ARTICLE!$B$2:$J$200,8,FALSE)),"",VLOOKUP($B3,ARTICLE!$B$2:$J$200,8,FALSE)),"") -> 0.3471
B4: Structure 145 mm | C4: =IFERROR(IF(ISBLANK(VLOOKUP($B4,ARTICLE!$B$2:$J$200,3,FALSE)),"",VLOOKUP($B4,ARTICLE!$B$2:$J$200,3,FALSE)),"") -> m2 | D4: =IFERROR(IF(ISBLANK(VLOOKUP($B4,ARTICLE!$B$2:$J$200,4,FALSE)),"",VLOOKUP($B4,ARTICLE!$B$2:$J$200,4,FALSE)),"") -> 48.442138 | E4: =IFERROR(IF(ISBLANK(VLOOKUP($B4,ARTICLE!$B$2:$J$200,5,FALSE)),"",VLOOKUP($B4,ARTICLE!$B$2:$J$200,5,FALSE)),"") -> 29.445621 | F4: =IFERROR(IF(ISBLANK(VLOOKUP($B4,ARTICLE!$B$2:$J$200,6,FALSE)),"",VLOOKUP($B4,ARTICLE!$B$2:$J$200,6,FALSE)),"") -> 4.43 | G4: =IFERROR(IF(ISBLANK(VLOOKUP($B4,ARTICLE!$B$2:$J$200,7,FALSE)),"",VLOOKUP($B4,ARTICLE!$B$2:$J$200,7,FALSE)),"") -> 10.162686 | H4: =IFERROR(IF(ISBLANK(VLOOKUP($B4,ARTICLE!$B$2:$J$200,8,FALSE)),"",VLOOKUP($B4,ARTICLE!$B$2:$J$200,8,FALSE)),"") -> 4.4038307
B5: Laine minérale 150 mm | C5: =IFERROR(IF(ISBLANK(VLOOKUP($B5,ARTICLE!$B$2:$J$200,3,FALSE)),"",VLOOKUP($B5,ARTICLE!$B$2:$J$200,3,FALSE)),"") -> m2 | D5: =IFERROR(IF(ISBLANK(VLOOKUP($B5,ARTICLE!$B$2:$J$200,4,FALSE)),"",VLOOKUP($B5,ARTICLE!$B$2:$J$200,4,FALSE)),"") -> 17.1171 | E5: =IFERROR(IF(ISBLANK(VLOOKUP($B5,ARTICLE!$B$2:$J$200,5,FALSE)),"",VLOOKUP($B5,ARTICLE!$B$2:$J$200,5,FALSE)),"") -> 10.53 | F5: =IFERROR(IF(ISBLANK(VLOOKUP($B5,ARTICLE!$B$2:$J$200,6,FALSE)),"",VLOOKUP($B5,ARTICLE!$B$2:$J$200,6,FALSE)),"") -> 1.44 | G5: =IFERROR(IF(ISBLANK(VLOOKUP($B5,ARTICLE!$B$2:$J$200,7,FALSE)),"",VLOOKUP($B5,ARTICLE!$B$2:$J$200,7,FALSE)),"") -> 3.591 | H5: =IFERROR(IF(ISBLANK(VLOOKUP($B5,ARTICLE!$B$2:$J$200,8,FALSE)),"",VLOOKUP($B5,ARTICLE!$B$2:$J$200,8,FALSE)),"") -> 1.5561
B6: OSB 12 | C6: =IFERROR(IF(ISBLANK(VLOOKUP($B6,ARTICLE!$B$2:$J$200,3,FALSE)),"",VLOOKUP($B6,ARTICLE!$B$2:$J$200,3,FALSE)),"") -> m2 | D6: =IFERROR(IF(ISBLANK(VLOOKUP($B6,ARTICLE!$B$2:$J$200,4,FALSE)),"",VLOOKUP($B6,ARTICLE!$B$2:$J$200,4,FALSE)),"") -> 11.8404 | E6: =IFERROR(IF(ISBLANK(VLOOKUP($B6,ARTICLE!$B$2:$J$200,5,FALSE)),"",VLOOKUP($B6,ARTICLE!$B$2:$J$200,5,FALSE)),"") -> 7.45 | F6: =IFERROR(IF(ISBLANK(VLOOKUP($B6,ARTICLE!$B$2:$J$200,6,FALSE)),"",VLOOKUP($B6,ARTICLE!$B$2:$J$200,6,FALSE)),"") -> 0.83 | G6: =IFERROR(IF(ISBLANK(VLOOKUP($B6,ARTICLE!$B$2:$J$200,7,FALSE)),"",VLOOKUP($B6,ARTICLE!$B$2:$J$200,7,FALSE)),"") -> 2.484 | H6: =IFERROR(IF(ISBLANK(VLOOKUP($B6,ARTICLE!$B$2:$J$200,8,FALSE)),"",VLOOKUP($B6,ARTICLE!$B$2:$J$200,8,FALSE)),"") -> 1.0764
B7: Bache de protection provisoire | C7: =IFERROR(IF(ISBLANK(VLOOKUP($B7,ARTICLE!$B$2:$J$200,3,FALSE)),"",VLOOKUP($B7,ARTICLE!$B$2:$J$200,3,FALSE)),"") -> m2 | D7: =IFERROR(IF(ISBLANK(VLOOKUP($B7,ARTICLE!$B$2:$J$200,4,FALSE)),"",VLOOKUP($B7,ARTICLE!$B$2:$J$200,4,FALSE)),"") -> 1.9162 | E7: =IFERROR(IF(ISBLANK(VLOOKUP($B7,ARTICLE!$B$2:$J$200,5,FALSE)),"",VLOOKUP($B7,ARTICLE!$B$2:$J$200,5,FALSE)),"") -> 0.73 | F7: =IFERROR(IF(ISBLANK(VLOOKUP($B7,ARTICLE!$B$2:$J$200,6,FALSE)),"",VLOOKUP($B7,ARTICLE!$B$2:$J$200,6,FALSE)),"") -> 0.61 | G7: =IFERROR(IF(ISBLANK(VLOOKUP($B7,ARTICLE!$B$2:$J$200,7,FALSE)),"",VLOOKUP($B7,ARTICLE!$B$2:$J$200,7,FALSE)),"") -> 0.402 | H7: =IFERROR(IF(ISBLANK(VLOOKUP($B7,ARTICLE!$B$2:$J$200,8,FALSE)),"",VLOOKUP($B7,ARTICLE!$B$2:$J$200,8,FALSE)),"") -> 0.1742
C8: =IFERROR(IF(ISBLANK(VLOOKUP($B8,ARTICLE!$B$2:$J$200,3,FALSE)),"",VLOOKUP($B8,ARTICLE!$B$2:$J$200,3,FALSE)),"") | D8: =IFERROR(IF(ISBLANK(VLOOKUP($B8,ARTICLE!$B$2:$J$200,4,FALSE)),"",VLOOKUP($B8,ARTICLE!$B$2:$J$200,4,FALSE)),"") | E8: =IFERROR(IF(ISBLANK(VLOOKUP($B8,ARTICLE!$B$2:$J$200,5,FALSE)),"",VLOOKUP($B8,ARTICLE!$B$2:$J$200,5,FALSE)),"") | F8: =IFERROR(IF(ISBLANK(VLOOKUP($B8,ARTICLE!$B$2:$J$200,6,FALSE)),"",VLOOKUP($B8,ARTICLE!$B$2:$J$200,6,FALSE)),"") | G8: =IFERROR(IF(ISBLANK(VLOOKUP($B8,ARTICLE!$B$2:$J$200,7,FALSE)),"",VLOOKUP($B8,ARTICLE!$B$2:$J$200,7,FALSE)),"") | H8: =IFERROR(IF(ISBLANK(VLOOKUP($B8,ARTICLE!$B$2:$J$200,8,FALSE)),"",VLOOKUP($B8,ARTICLE!$B$2:$J$200,8,FALSE)),"")
C9: =IFERROR(IF(ISBLANK(VLOOKUP($B9,ARTICLE!$B$2:$J$200,3,FALSE)),"",VLOOKUP($B9,ARTICLE!$B$2:$J$200,3,FALSE)),"") | D9: =IFERROR(IF(ISBLANK(VLOOKUP($B9,ARTICLE!$B$2:$J$200,4,FALSE)),"",VLOOKUP($B9,ARTICLE!$B$2:$J$200,4,FALSE)),"") | E9: =IFERROR(IF(ISBLANK(VLOOKUP($B9,ARTICLE!$B$2:$J$200,5,FALSE)),"",VLOOKUP($B9,ARTICLE!$B$2:$J$200,5,FALSE)),"") | F9: =IFERROR(IF(ISBLANK(VLOOKUP($B9,ARTICLE!$B$2:$J$200,6,FALSE)),"",VLOOKUP($B9,ARTICLE!$B$2:$J$200,6,FALSE)),"") | G9: =IFERROR(IF(ISBLANK(VLOOKUP($B9,ARTICLE!$B$2:$J$200,7,FALSE)),"",VLOOKUP($B9,ARTICLE!$B$2:$J$200,7,FALSE)),"") | H9: =IFERROR(IF(ISBLANK(VLOOKUP($B9,ARTICLE!$B$2:$J$200,8,FALSE)),"",VLOOKUP($B9,ARTICLE!$B$2:$J$200,8,FALSE)),"")
C10: =IFERROR(IF(ISBLANK(VLOOKUP($B10,ARTICLE!$B$2:$J$200,3,FALSE)),"",VLOOKUP($B10,ARTICLE!$B$2:$J$200,3,FALSE)),"") | D10: =IFERROR(IF(ISBLANK(VLOOKUP($B10,ARTICLE!$B$2:$J$200,4,FALSE)),"",VLOOKUP($B10,ARTICLE!$B$2:$J$200,4,FALSE)),"") | E10: =IFERROR(IF(ISBLANK(VLOOKUP($B10,ARTICLE!$B$2:$J$200,5,FALSE)),"",VLOOKUP($B10,ARTICLE!$B$2:$J$200,5,FALSE)),"") | F10: =IFERROR(IF(ISBLANK(VLOOKUP($B10,ARTICLE!$B$2:$J$200,6,FALSE)),"",VLOOKUP($B10,ARTICLE!$B$2:$J$200,6,FALSE)),"") | G10: =IFERROR(IF(ISBLANK(VLOOKUP($B10,ARTICLE!$B$2:$J$200,7,FALSE)),"",VLOOKUP($B10,ARTICLE!$B$2:$J$200,7,FALSE)),"") | H10: =IFERROR(IF(ISBLANK(VLOOKUP($B10,ARTICLE!$B$2:$J$200,8,FALSE)),"",VLOOKUP($B10,ARTICLE!$B$2:$J$200,8,FALSE)),"")
C11: =IFERROR(IF(ISBLANK(VLOOKUP($B11,ARTICLE!$B$2:$J$200,3,FALSE)),"",VLOOKUP($B11,ARTICLE!$B$2:$J$200,3,FALSE)),"") | D11: =IFERROR(IF(ISBLANK(VLOOKUP($B11,ARTICLE!$B$2:$J$200,4,FALSE)),"",VLOOKUP($B11,ARTICLE!$B$2:$J$200,4,FALSE)),"") | E11: =IFERROR(IF(ISBLANK(VLOOKUP($B11,ARTICLE!$B$2:$J$200,5,FALSE)),"",VLOOKUP($B11,ARTICLE!$B$2:$J$200,5,FALSE)),"") | F11: =IFERROR(IF(ISBLANK(VLOOKUP($B11,ARTICLE!$B$2:$J$200,6,FALSE)),"",VLOOKUP($B11,ARTICLE!$B$2:$J$200,6,FALSE)),"") | G11: =IFERROR(IF(ISBLANK(VLOOKUP($B11,ARTICLE!$B$2:$J$200,7,FALSE)),"",VLOOKUP($B11,ARTICLE!$B$2:$J$200,7,FALSE)),"") | H11: =IFERROR(IF(ISBLANK(VLOOKUP($B11,ARTICLE!$B$2:$J$200,8,FALSE)),"",VLOOKUP($B11,ARTICLE!$B$2:$J$200,8,FALSE)),"")
C12: =IFERROR(IF(ISBLANK(VLOOKUP($B12,ARTICLE!$B$2:$J$200,3,FALSE)),"",VLOOKUP($B12,ARTICLE!$B$2:$J$200,3,FALSE)),"") | D12: =IFERROR(IF(ISBLANK(VLOOKUP($B12,ARTICLE!$B$2:$J$200,4,FALSE)),"",VLOOKUP($B12,ARTICLE!$B$2:$J$200,4,FALSE)),"") | E12: =IFERROR(IF(ISBLANK(VLOOKUP($B12,ARTICLE!$B$2:$J$200,5,FALSE)),"",VLOOKUP($B12,ARTICLE!$B$2:$J$200,5,FALSE)),"") | F12: =IFERROR(IF(ISBLANK(VLOOKUP($B12,ARTICLE!$B$2:$J$200,6,FALSE)),"",VLOOKUP($B12,ARTICLE!$B$2:$J$200,6,FALSE)),"") | G12: =IFERROR(IF(ISBLANK(VLOOKUP($B12,ARTICLE!$B$2:$J$200,7,FALSE)),"",VLOOKUP($B12,ARTICLE!$B$2:$J$200,7,FALSE)),"") | H12: =IFERROR(IF(ISBLANK(VLOOKUP($B12,ARTICLE!$B$2:$J$200,8,FALSE)),"",VLOOKUP($B12,ARTICLE!$B$2:$J$200,8,FALSE)),"")
A13: =B13 -> Structure 100 mm / OSB 12 / Bache de protection provisoire / Pignon | B13: =CONCATENATE(B14,IF(B15="",""," / "),B15,IF(B16="",""," / "),B16,IF(B17="",""," / "),B17,IF(B18="",""," / "),B18,IF(B19="",""," / "),B19,IF(B20="",""," / "),B20,B20,IF(B21="",""," / "),B21) -> Structure 100 mm / OSB 12 / Bache de protection provisoire / Pignon | C13: =C14 -> m2 | D13: =IF(SUM(E13:H13)=0,0,SUM(E13:H13)) -> 63.852748 | E13: =SUM(E14:E23) -> 27.002271 | F13: =SUM(F14:F23) -> 17.65 | G13: =SUM(G14:G23) -> 13.395681 | H13: =SUM(H14:H23) -> 5.8047952 | I13: PEST-10 | J13: =31+46 -> 77 | K13: =ROUNDUP(D13,0)*J13 -> 4928 | L13: =ROUNDUP(J13*E13,0) -> 2080 | M13: =L13/K13 -> 0.42207792 | N13: =ROUNDUP(J13*F13,0) -> 1360 | O13: =N13/K13 -> 0.27597403 | P13: =ROUNDUP(J13*G13,0) -> 1032 | Q13: =P13/K13 -> 0.20941558 | R13: =ROUNDUP(J13*H13,0) -> 447 | S13: =R13/K13 -> 0.090706169
B14: Structure 100 mm | C14: =IFERROR(IF(ISBLANK(VLOOKUP($B14,ARTICLE!$B$2:$J$200,3,FALSE)),"",VLOOKUP($B14,ARTICLE!$B$2:$J$200,3,FALSE)),"") -> m2 | D14: =IFERROR(IF(ISBLANK(VLOOKUP($B14,ARTICLE!$B$2:$J$200,4,FALSE)),"",VLOOKUP($B14,ARTICLE!$B$2:$J$200,4,FALSE)),"") -> 32.392748 | E14: =IFERROR(IF(ISBLANK(VLOOKUP($B14,ARTICLE!$B$2:$J$200,5,FALSE)),"",VLOOKUP($B14,ARTICLE!$B$2:$J$200,5,FALSE)),"") -> 18.822271 | F14: =IFERROR(IF(ISBLANK(VLOOKUP($B14,ARTICLE!$B$2:$J$200,6,FALSE)),"",VLOOKUP($B14,ARTICLE!$B$2:$J$200,6,FALSE)),"") -> 3.83 | G14: =IFERROR(IF(ISBLANK(VLOOKUP($B14,ARTICLE!$B$2:$J$200,7,FALSE)),"",VLOOKUP($B14,ARTICLE!$B$2:$J$200,7,FALSE)),"") -> 6.7956813 | H14: =IFERROR(IF(ISBLANK(VLOOKUP($B14,ARTICLE!$B$2:$J$200,8,FALSE)),"",VLOOKUP($B14,ARTICLE!$B$2:$J$200,8,FALSE)),"") -> 2.9447952
B15: OSB 12 | C15: =IFERROR(IF(ISBLANK(VLOOKUP($B15,ARTICLE!$B$2:$J$200,3,FALSE)),"",VLOOKUP($B15,ARTICLE!$B$2:$J$200,3,FALSE)),"") -> m2 | D15: =IFERROR(IF(ISBLANK(VLOOKUP($B15,ARTICLE!$B$2:$J$200,4,FALSE)),"",VLOOKUP($B15,ARTICLE!$B$2:$J$200,4,FALSE)),"") -> 11.8404 | E15: =IFERROR(IF(ISBLANK(VLOOKUP($B15,ARTICLE!$B$2:$J$200,5,FALSE)),"",VLOOKUP($B15,ARTICLE!$B$2:$J$200,5,FALSE)),"") -> 7.45 | F15: =IFERROR(IF(ISBLANK(VLOOKUP($B15,ARTICLE!$B$2:$J$200,6,FALSE)),"",VLOOKUP($B15,ARTICLE!$B$2:$J$200,6,FALSE)),"") -> 0.83 | G15: =IFERROR(IF(ISBLANK(VLOOKUP($B15,ARTICLE!$B$2:$J$200,7,FALSE)),"",VLOOKUP($B15,ARTICLE!$B$2:$J$200,7,FALSE)),"") -> 2.484 | H15: =IFERROR(IF(ISBLANK(VLOOKUP($B15,ARTICLE!$B$2:$J$200,8,FALSE)),"",VLOOKUP($B15,ARTICLE!$B$2:$J$200,8,FALSE)),"") -> 1.0764
B16: Bache de protection provisoire | C16: =IFERROR(IF(ISBLANK(VLOOKUP($B16,ARTICLE!$B$2:$J$200,3,FALSE)),"",VLOOKUP($B16,ARTICLE!$B$2:$J$200,3,FALSE)),"") -> m2 | D16: =IFERROR(IF(ISBLANK(VLOOKUP($B16,ARTICLE!$B$2:$J$200,4,FALSE)),"",VLOOKUP($B16,ARTICLE!$B$2:$J$200,4,FALSE)),"") -> 1.9162 | E16: =IFERROR(IF(ISBLANK(VLOOKUP($B16,ARTICLE!$B$2:$J$200,5,FALSE)),"",VLOOKUP($B16,ARTICLE!$B$2:$J$200,5,FALSE)),"") -> 0.73 | F16: =IFERROR(IF(ISBLANK(VLOOKUP($B16,ARTICLE!$B$2:$J$200,6,FALSE)),"",VLOOKUP($B16,ARTICLE!$B$2:$J$200,6,FALSE)),"") -> 0.61 | G16: =IFERROR(IF(ISBLANK(VLOOKUP($B16,ARTICLE!$B$2:$J$200,7,FALSE)),"",VLOOKUP($B16,ARTICLE!$B$2:$J$200,7,FALSE)),"") -> 0.402 | H16: =IFERROR(IF(ISBLANK(VLOOKUP($B16,ARTICLE!$B$2:$J$200,8,FALSE)),"",VLOOKUP($B16,ARTICLE!$B$2:$J$200,8,FALSE)),"") -> 0.1742
B17: Pignon | C17: =IFERROR(IF(ISBLANK(VLOOKUP($B17,ARTICLE!$B$2:$J$200,3,FALSE)),"",VLOOKUP($B17,ARTICLE!$B$2:$J$200,3,FALSE)),"") -> m2 | D17: =IFERROR(IF(ISBLANK(VLOOKUP($B17,ARTICLE!$B$2:$J$200,4,FALSE)),"",VLOOKUP($B17,ARTICLE!$B$2:$J$200,4,FALSE)),"") -> 17.7034 | E17: =IFERROR(IF(ISBLANK(VLOOKUP($B17,ARTICLE!$B$2:$J$200,5,FALSE)),"",VLOOKUP($B17,ARTICLE!$B$2:$J$200,5,FALSE)),"") -> 0 | F17: =IFERROR(IF(ISBLANK(VLOOKUP($B17,ARTICLE!$B$2:$J$200,6,FALSE)),"",VLOOKUP($B17,ARTICLE!$B$2:$J$200,6,FALSE)),"") -> 12.38 | G17: =IFERROR(IF(ISBLANK(VLOOKUP($B17,ARTICLE!$B$2:$J$200,7,FALSE)),"",VLOOKUP($B17,ARTICLE!$B$2:$J$200,7,FALSE)),"") -> 3.714 | H17: =IFERROR(IF(ISBLANK(VLOOKUP($B17,ARTICLE!$B$2:$J$200,8,FALSE)),"",VLOOKUP($B17,ARTICLE!$B$2:$J$200,8,FALSE)),"") -> 1.6094
C18: =IFERROR(IF(ISBLANK(VLOOKUP($B18,ARTICLE!$B$2:$J$200,3,FALSE)),"",VLOOKUP($B18,ARTICLE!$B$2:$J$200,3,FALSE)),"") | D18: =IFERROR(IF(ISBLANK(VLOOKUP($B18,ARTICLE!$B$2:$J$200,4,FALSE)),"",VLOOKUP($B18,ARTICLE!$B$2:$J$200,4,FALSE)),"") | E18: =IFERROR(IF(ISBLANK(VLOOKUP($B18,ARTICLE!$B$2:$J$200,5,FALSE)),"",VLOOKUP($B18,ARTICLE!$B$2:$J$200,5,FALSE)),"") | F18: =IFERROR(IF(ISBLANK(VLOOKUP($B18,ARTICLE!$B$2:$J$200,6,FALSE)),"",VLOOKUP($B18,ARTICLE!$B$2:$J$200,6,FALSE)),"") | G18: =IFERROR(IF(ISBLANK(VLOOKUP($B18,ARTICLE!$B$2:$J$200,7,FALSE)),"",VLOOKUP($B18,ARTICLE!$B$2:$J$200,7,FALSE)),"") | H18: =IFERROR(IF(ISBLANK(VLOOKUP($B18,ARTICLE!$B$2:$J$200,8,FALSE)),"",VLOOKUP($B18,ARTICLE!$B$2:$J$200,8,FALSE)),"")
C19: =IFERROR(IF(ISBLANK(VLOOKUP($B19,ARTICLE!$B$2:$J$200,3,FALSE)),"",VLOOKUP($B19,ARTICLE!$B$2:$J$200,3,FALSE)),"") | D19: =IFERROR(IF(ISBLANK(VLOOKUP($B19,ARTICLE!$B$2:$J$200,4,FALSE)),"",VLOOKUP($B19,ARTICLE!$B$2:$J$200,4,FALSE)),"") | E19: =IFERROR(IF(ISBLANK(VLOOKUP($B19,ARTICLE!$B$2:$J$200,5,FALSE)),"",VLOOKUP($B19,ARTICLE!$B$2:$J$200,5,FALSE)),"") | F19: =IFERROR(IF(ISBLANK(VLOOKUP($B19,ARTICLE!$B$2:$J$200,6,FALSE)),"",VLOOKUP($B19,ARTICLE!$B$2:$J$200,6,FALSE)),"") | G19: =IFERROR(IF(ISBLANK(VLOOKUP($B19,ARTICLE!$B$2:$J$200,7,FALSE)),"",VLOOKUP($B19,ARTICLE!$B$2:$J$200,7,FALSE)),"") | H19: =IFERROR(IF(ISBLANK(VLOOKUP($B19,ARTICLE!$B$2:$J$200,8,FALSE)),"",VLOOKUP($B19,ARTICLE!$B$2:$J$200,8,FALSE)),"")
C20: =IFERROR(IF(ISBLANK(VLOOKUP($B20,ARTICLE!$B$2:$J$200,3,FALSE)),"",VLOOKUP($B20,ARTICLE!$B$2:$J$200,3,FALSE)),"") | D20: =IFERROR(IF(ISBLANK(VLOOKUP($B20,ARTICLE!$B$2:$J$200,4,FALSE)),"",VLOOKUP($B20,ARTICLE!$B$2:$J$200,4,FALSE)),"") | E20: =IFERROR(IF(ISBLANK(VLOOKUP($B20,ARTICLE!$B$2:$J$200,5,FALSE)),"",VLOOKUP($B20,ARTICLE!$B$2:$J$200,5,FALSE)),"") | F20: =IFERROR(IF(ISBLANK(VLOOKUP($B20,ARTICLE!$B$2:$J$200,6,FALSE)),"",VLOOKUP($B20,ARTICLE!$B$2:$J$200,6,FALSE)),"") | G20: =IFERROR(IF(ISBLANK(VLOOKUP($B20,ARTICLE!$B$2:$J$200,7,FALSE)),"",VLOOKUP($B20,ARTICLE!$B$2:$J$200,7,FALSE)),"") | H20: =IFERROR(IF(ISBLANK(VLOOKUP($B20,ARTICLE!$B$2:$J$200,8,FALSE)),"",VLOOKUP($B20,ARTICLE!$B$2:$J$200,8,FALSE)),"")
C21: =IFERROR(IF(ISBLANK(VLOOKUP($B21,ARTICLE!$B$2:$J$200,3,FALSE)),"",VLOOKUP($B21,ARTICLE!$B$2:$J$200,3,FALSE)),"") | D21: =IFERROR(IF(ISBLANK(VLOOKUP($B21,ARTICLE!$B$2:$J$200,4,FALSE)),"",VLOOKUP($B21,ARTICLE!$B$2:$J$200,4,FALSE)),"") | E21: =IFERROR(IF(ISBLANK(VLOOKUP($B21,ARTICLE!$B$2:$J$200,5,FALSE)),"",VLOOKUP($B21,ARTICLE!$B$2:$J$200,5,FALSE)),"") | F21: =IFERROR(IF(ISBLANK(VLOOKUP($B21,ARTICLE!$B$2:$J$200,6,FALSE)),"",VLOOKUP($B21,ARTICLE!$B$2:$J$200,6,FALSE)),"") | G21: =IFERROR(IF(ISBLANK(VLOOKUP($B21,ARTICLE!$B$2:$J$200,7,FALSE)),"",VLOOKUP($B21,ARTICLE!$B$2:$J$200,7,FALSE)),"") | H21: =IFERROR(IF(ISBLANK(VLOOKUP($B21,ARTICLE!$B$2:$J$200,8,FALSE)),"",VLOOKUP($B21,ARTICLE!$B$2:$J$200,8,FALSE)),"")
C22: =IFERROR(IF(ISBLANK(VLOOKUP($B22,ARTICLE!$B$2:$J$200,3,FALSE)),"",VLOOKUP($B22,ARTICLE!$B$2:$J$200,3,FALSE)),"") | D22: =IFERROR(IF(ISBLANK(VLOOKUP($B22,ARTICLE!$B$2:$J$200,4,FALSE)),"",VLOOKUP($B22,ARTICLE!$B$2:$J$200,4,FALSE)),"") | E22: =IFERROR(IF(ISBLANK(VLOOKUP($B22,ARTICLE!$B$2:$J$200,5,FALSE)),"",VLOOKUP($B22,ARTICLE!$B$2:$J$200,5,FALSE)),"") | F22: =IFERROR(IF(ISBLANK(VLOOKUP($B22,ARTICLE!$B$2:$J$200,6,FALSE)),"",VLOOKUP($B22,ARTICLE!$B$2:$J$200,6,FALSE)),"") | G22: =IFERROR(IF(ISBLANK(VLOOKUP($B22,ARTICLE!$B$2:$J$200,7,FALSE)),"",VLOOKUP($B22,ARTICLE!$B$2:$J$200,7,FALSE)),"") | H22: =IFERROR(IF(ISBLANK(VLOOKUP($B22,ARTICLE!$B$2:$J$200,8,FALSE)),"",VLOOKUP($B22,ARTICLE!$B$2:$J$200,8,FALSE)),"")
C23: =IFERROR(IF(ISBLANK(VLOOKUP($B23,ARTICLE!$B$2:$J$200,3,FALSE)),"",VLOOKUP($B23,ARTICLE!$B$2:$J$200,3,FALSE)),"") | D23: =IFERROR(IF(ISBLANK(VLOOKUP($B23,ARTICLE!$B$2:$J$200,4,FALSE)),"",VLOOKUP($B23,ARTICLE!$B$2:$J$200,4,FALSE)),"") | E23: =IFERROR(IF(ISBLANK(VLOOKUP($B23,ARTICLE!$B$2:$J$200,5,FALSE)),"",VLOOKUP($B23,ARTICLE!$B$2:$J$200,5,FALSE)),"") | F23: =IFERROR(IF(ISBLANK(VLOOKUP($B23,ARTICLE!$B$2:$J$200,6,FALSE)),"",VLOOKUP($B23,ARTICLE!$B$2:$J$200,6,FALSE)),"") | G23: =IFERROR(IF(ISBLANK(VLOOKUP($B23,ARTICLE!$B$2:$J$200,7,FALSE)),"",VLOOKUP($B23,ARTICLE!$B$2:$J$200,7,FALSE)),"") | H23: =IFERROR(IF(ISBLANK(VLOOKUP($B23,ARTICLE!$B$2:$J$200,8,FALSE)),"",VLOOKUP($B23,ARTICLE!$B$2:$J$200,8,FALSE)),"")
A24: =B24 -> Structure 100 mm / Bardage horizontal cl4 | B24: =CONCATENATE(B25,IF(B26="",""," / "),B26,IF(B27="",""," / "),B27,IF(B28="",""," / "),B28,IF(B29="",""," / "),B29,IF(B30="",""," / "),B30,IF(B31="",""," / "),B31,B31,IF(B32="",""," / "),B32) -> Structure 100 mm / Bardage horizontal cl4 | C24: =C25 -> m2 | D24: =IF(SUM(E24:H24)=0,0,SUM(E24:H24)) -> 61.764948 | E24: =SUM(E25:E34) -> 36.342271 | F24: =SUM(F25:F34) -> 6.85 | G24: =SUM(G25:G34) -> 12.957681 | H24: =SUM(H25:H34) -> 5.6149952 | I24: PEST-10-BARDAGE | J24: ='MODELE LAROX'!E31 -> 527 | K24: =ROUNDUP(D24,0)*J24 -> 32674 | L24: =ROUNDUP(J24*E24,0) -> 19153 | M24: =L24/K24 -> 0.58618473 | N24: =ROUNDUP(J24*F24,0) -> 3610 | O24: =N24/K24 -> 0.1104854 | P24: =ROUNDUP(J24*G24,0) -> 6829 | Q24: =P24/K24 -> 0.2090041 | R24: =ROUNDUP(J24*H24,0) -> 2960 | S24: =R24/K24 -> 0.090591908
B25: Structure 100 mm | C25: =IFERROR(IF(ISBLANK(VLOOKUP($B25,ARTICLE!$B$2:$J$200,3,FALSE)),"",VLOOKUP($B25,ARTICLE!$B$2:$J$200,3,FALSE)),"") -> m2 | D25: =IFERROR(IF(ISBLANK(VLOOKUP($B25,ARTICLE!$B$2:$J$200,4,FALSE)),"",VLOOKUP($B25,ARTICLE!$B$2:$J$200,4,FALSE)),"") -> 32.392748 | E25: =IFERROR(IF(ISBLANK(VLOOKUP($B25,ARTICLE!$B$2:$J$200,5,FALSE)),"",VLOOKUP($B25,ARTICLE!$B$2:$J$200,5,FALSE)),"") -> 18.822271 | F25: =IFERROR(IF(ISBLANK(VLOOKUP($B25,ARTICLE!$B$2:$J$200,6,FALSE)),"",VLOOKUP($B25,ARTICLE!$B$2:$J$200,6,FALSE)),"") -> 3.83 | G25: =IFERROR(IF(ISBLANK(VLOOKUP($B25,ARTICLE!$B$2:$J$200,7,FALSE)),"",VLOOKUP($B25,ARTICLE!$B$2:$J$200,7,FALSE)),"") -> 6.7956813 | H25: =IFERROR(IF(ISBLANK(VLOOKUP($B25,ARTICLE!$B$2:$J$200,8,FALSE)),"",VLOOKUP($B25,ARTICLE!$B$2:$J$200,8,FALSE)),"") -> 2.9447952
B26: Bardage horizontal cl4 | C26: =IFERROR(IF(ISBLANK(VLOOKUP($B26,ARTICLE!$B$2:$J$200,3,FALSE)),"",VLOOKUP($B26,ARTICLE!$B$2:$J$200,3,FALSE)),"") -> m2 | D26: =IFERROR(IF(ISBLANK(VLOOKUP($B26,ARTICLE!$B$2:$J$200,4,FALSE)),"",VLOOKUP($B26,ARTICLE!$B$2:$J$200,4,FALSE)),"") -> 29.3722 | E26: =IFERROR(IF(ISBLANK(VLOOKUP($B26,ARTICLE!$B$2:$J$200,5,FALSE)),"",VLOOKUP($B26,ARTICLE!$B$2:$J$200,5,FALSE)),"") -> 17.52 | F26: =IFERROR(IF(ISBLANK(VLOOKUP($B26,ARTICLE!$B$2:$J$200,6,FALSE)),"",VLOOKUP($B26,ARTICLE!$B$2:$J$200,6,FALSE)),"") -> 3.02 | G26: =IFERROR(IF(ISBLANK(VLOOKUP($B26,ARTICLE!$B$2:$J$200,7,FALSE)),"",VLOOKUP($B26,ARTICLE!$B$2:$J$200,7,FALSE)),"") -> 6.162 | H26: =IFERROR(IF(ISBLANK(VLOOKUP($B26,ARTICLE!$B$2:$J$200,8,FALSE)),"",VLOOKUP($B26,ARTICLE!$B$2:$J$200,8,FALSE)),"") -> 2.6702
C27: =IFERROR(IF(ISBLANK(VLOOKUP($B27,ARTICLE!$B$2:$J$200,3,FALSE)),"",VLOOKUP($B27,ARTICLE!$B$2:$J$200,3,FALSE)),"") | D27: =IFERROR(IF(ISBLANK(VLOOKUP($B27,ARTICLE!$B$2:$J$200,4,FALSE)),"",VLOOKUP($B27,ARTICLE!$B$2:$J$200,4,FALSE)),"") | E27: =IFERROR(IF(ISBLANK(VLOOKUP($B27,ARTICLE!$B$2:$J$200,5,FALSE)),"",VLOOKUP($B27,ARTICLE!$B$2:$J$200,5,FALSE)),"") | F27: =IFERROR(IF(ISBLANK(VLOOKUP($B27,ARTICLE!$B$2:$J$200,6,FALSE)),"",VLOOKUP($B27,ARTICLE!$B$2:$J$200,6,FALSE)),"") | G27: =IFERROR(IF(ISBLANK(VLOOKUP($B27,ARTICLE!$B$2:$J$200,7,FALSE)),"",VLOOKUP($B27,ARTICLE!$B$2:$J$200,7,FALSE)),"") | H27: =IFERROR(IF(ISBLANK(VLOOKUP($B27,ARTICLE!$B$2:$J$200,8,FALSE)),"",VLOOKUP($B27,ARTICLE!$B$2:$J$200,8,FALSE)),"")
C28: =IFERROR(IF(ISBLANK(VLOOKUP($B28,ARTICLE!$B$2:$J$200,3,FALSE)),"",VLOOKUP($B28,ARTICLE!$B$2:$J$200,3,FALSE)),"") | D28: =IFERROR(IF(ISBLANK(VLOOKUP($B28,ARTICLE!$B$2:$J$200,4,FALSE)),"",VLOOKUP($B28,ARTICLE!$B$2:$J$200,4,FALSE)),"") | E28: =IFERROR(IF(ISBLANK(VLOOKUP($B28,ARTICLE!$B$2:$J$200,5,FALSE)),"",VLOOKUP($B28,ARTICLE!$B$2:$J$200,5,FALSE)),"") | F28: =IFERROR(IF(ISBLANK(VLOOKUP($B28,ARTICLE!$B$2:$J$200,6,FALSE)),"",VLOOKUP($B28,ARTICLE!$B$2:$J$200,6,FALSE)),"") | G28: =IFERROR(IF(ISBLANK(VLOOKUP($B28,ARTICLE!$B$2:$J$200,7,FALSE)),"",VLOOKUP($B28,ARTICLE!$B$2:$J$200,7,FALSE)),"") | H28: =IFERROR(IF(ISBLANK(VLOOKUP($B28,ARTICLE!$B$2:$J$200,8,FALSE)),"",VLOOKUP($B28,ARTICLE!$B$2:$J$200,8,FALSE)),"")
C29: =IFERROR(IF(ISBLANK(VLOOKUP($B29,ARTICLE!$B$2:$J$200,3,FALSE)),"",VLOOKUP($B29,ARTICLE!$B$2:$J$200,3,FALSE)),"") | D29: =IFERROR(IF(ISBLANK(VLOOKUP($B29,ARTICLE!$B$2:$J$200,4,FALSE)),"",VLOOKUP($B29,ARTICLE!$B$2:$J$200,4,FALSE)),"") | E29: =IFERROR(IF(ISBLANK(VLOOKUP($B29,ARTICLE!$B$2:$J$200,5,FALSE)),"",VLOOKUP($B29,ARTICLE!$B$2:$J$200,5,FALSE)),"") | F29: =IFERROR(IF(ISBLANK(VLOOKUP($B29,ARTICLE!$B$2:$J$200,6,FALSE)),"",VLOOKUP($B29,ARTICLE!$B$2:$J$200,6,FALSE)),"") | G29: =IFERROR(IF(ISBLANK(VLOOKUP($B29,ARTICLE!$B$2:$J$200,7,FALSE)),"",VLOOKUP($B29,ARTICLE!$B$2:$J$200,7,FALSE)),"") | H29: =IFERROR(IF(ISBLANK(VLOOKUP($B29,ARTICLE!$B$2:$J$200,8,FALSE)),"",VLOOKUP($B29,ARTICLE!$B$2:$J$200,8,FALSE)),"")
C30: =IFERROR(IF(ISBLANK(VLOOKUP($B30,ARTICLE!$B$2:$J$200,3,FALSE)),"",VLOOKUP($B30,ARTICLE!$B$2:$J$200,3,FALSE)),"") | D30: =IFERROR(IF(ISBLANK(VLOOKUP($B30,ARTICLE!$B$2:$J$200,4,FALSE)),"",VLOOKUP($B30,ARTICLE!$B$2:$J$200,4,FALSE)),"") | E30: =IFERROR(IF(ISBLANK(VLOOKUP($B30,ARTICLE!$B$2:$J$200,5,FALSE)),"",VLOOKUP($B30,ARTICLE!$B$2:$J$200,5,FALSE)),"") | F30: =IFERROR(IF(ISBLANK(VLOOKUP($B30,ARTICLE!$B$2:$J$200,6,FALSE)),"",VLOOKUP($B30,ARTICLE!$B$2:$J$200,6,FALSE)),"") | G30: =IFERROR(IF(ISBLANK(VLOOKUP($B30,ARTICLE!$B$2:$J$200,7,FALSE)),"",VLOOKUP($B30,ARTICLE!$B$2:$J$200,7,FALSE)),"") | H30: =IFERROR(IF(ISBLANK(VLOOKUP($B30,ARTICLE!$B$2:$J$200,8,FALSE)),"",VLOOKUP($B30,ARTICLE!$B$2:$J$200,8,FALSE)),"")
C31: =IFERROR(IF(ISBLANK(VLOOKUP($B31,ARTICLE!$B$2:$J$200,3,FALSE)),"",VLOOKUP($B31,ARTICLE!$B$2:$J$200,3,FALSE)),"") | D31: =IFERROR(IF(ISBLANK(VLOOKUP($B31,ARTICLE!$B$2:$J$200,4,FALSE)),"",VLOOKUP($B31,ARTICLE!$B$2:$J$200,4,FALSE)),"") | E31: =IFERROR(IF(ISBLANK(VLOOKUP($B31,ARTICLE!$B$2:$J$200,5,FALSE)),"",VLOOKUP($B31,ARTICLE!$B$2:$J$200,5,FALSE)),"") | F31: =IFERROR(IF(ISBLANK(VLOOKUP($B31,ARTICLE!$B$2:$J$200,6,FALSE)),"",VLOOKUP($B31,ARTICLE!$B$2:$J$200,6,FALSE)),"") | G31: =IFERROR(IF(ISBLANK(VLOOKUP($B31,ARTICLE!$B$2:$J$200,7,FALSE)),"",VLOOKUP($B31,ARTICLE!$B$2:$J$200,7,FALSE)),"") | H31: =IFERROR(IF(ISBLANK(VLOOKUP($B31,ARTICLE!$B$2:$J$200,8,FALSE)),"",VLOOKUP($B31,ARTICLE!$B$2:$J$200,8,FALSE)),"")
C32: =IFERROR(IF(ISBLANK(VLOOKUP($B32,ARTICLE!$B$2:$J$200,3,FALSE)),"",VLOOKUP($B32,ARTICLE!$B$2:$J$200,3,FALSE)),"") | D32: =IFERROR(IF(ISBLANK(VLOOKUP($B32,ARTICLE!$B$2:$J$200,4,FALSE)),"",VLOOKUP($B32,ARTICLE!$B$2:$J$200,4,FALSE)),"") | E32: =IFERROR(IF(ISBLANK(VLOOKUP($B32,ARTICLE!$B$2:$J$200,5,FALSE)),"",VLOOKUP($B32,ARTICLE!$B$2:$J$200,5,FALSE)),"") | F32: =IFERROR(IF(ISBLANK(VLOOKUP($B32,ARTICLE!$B$2:$J$200,6,FALSE)),"",VLOOKUP($B32,ARTICLE!$B$2:$J$200,6,FALSE)),"") | G32: =IFERROR(IF(ISBLANK(VLOOKUP($B32,ARTICLE!$B$2:$J$200,7,FALSE)),"",VLOOKUP($B32,ARTICLE!$B$2:$J$200,7,FALSE)),"") | H32: =IFERROR(IF(ISBLANK(VLOOKUP($B32,ARTICLE!$B$2:$J$200,8,FALSE)),"",VLOOKUP($B32,ARTICLE!$B$2:$J$200,8,FALSE)),"")
C33: =IFERROR(IF(ISBLANK(VLOOKUP($B33,ARTICLE!$B$2:$J$200,3,FALSE)),"",VLOOKUP($B33,ARTICLE!$B$2:$J$200,3,FALSE)),"") | D33: =IFERROR(IF(ISBLANK(VLOOKUP($B33,ARTICLE!$B$2:$J$200,4,FALSE)),"",VLOOKUP($B33,ARTICLE!$B$2:$J$200,4,FALSE)),"") | E33: =IFERROR(IF(ISBLANK(VLOOKUP($B33,ARTICLE!$B$2:$J$200,5,FALSE)),"",VLOOKUP($B33,ARTICLE!$B$2:$J$200,5,FALSE)),"") | F33: =IFERROR(IF(ISBLANK(VLOOKUP($B33,ARTICLE!$B$2:$J$200,6,FALSE)),"",VLOOKUP($B33,ARTICLE!$B$2:$J$200,6,FALSE)),"") | G33: =IFERROR(IF(ISBLANK(VLOOKUP($B33,ARTICLE!$B$2:$J$200,7,FALSE)),"",VLOOKUP($B33,ARTICLE!$B$2:$J$200,7,FALSE)),"") | H33: =IFERROR(IF(ISBLANK(VLOOKUP($B33,ARTICLE!$B$2:$J$200,8,FALSE)),"",VLOOKUP($B33,ARTICLE!$B$2:$J$200,8,FALSE)),"")
C34: =IFERROR(IF(ISBLANK(VLOOKUP($B34,ARTICLE!$B$2:$J$200,3,FALSE)),"",VLOOKUP($B34,ARTICLE!$B$2:$J$200,3,FALSE)),"") | D34: =IFERROR(IF(ISBLANK(VLOOKUP($B34,ARTICLE!$B$2:$J$200,4,FALSE)),"",VLOOKUP($B34,ARTICLE!$B$2:$J$200,4,FALSE)),"") | E34: =IFERROR(IF(ISBLANK(VLOOKUP($B34,ARTICLE!$B$2:$J$200,5,FALSE)),"",VLOOKUP($B34,ARTICLE!$B$2:$J$200,5,FALSE)),"") | F34: =IFERROR(IF(ISBLANK(VLOOKUP($B34,ARTICLE!$B$2:$J$200,6,FALSE)),"",VLOOKUP($B34,ARTICLE!$B$2:$J$200,6,FALSE)),"") | G34: =IFERROR(IF(ISBLANK(VLOOKUP($B34,ARTICLE!$B$2:$J$200,7,FALSE)),"",VLOOKUP($B34,ARTICLE!$B$2:$J$200,7,FALSE)),"") | H34: =IFERROR(IF(ISBLANK(VLOOKUP($B34,ARTICLE!$B$2:$J$200,8,FALSE)),"",VLOOKUP($B34,ARTICLE!$B$2:$J$200,8,FALSE)),"")
A35: =B35 -> Structure 100 mm / Bardage horizontal cl4 / Pignon | B35: =CONCATENATE(B36,IF(B37="",""," / "),B37,IF(B38="",""," / "),B38,IF(B39="",""," / "),B39,IF(B40="",""," / "),B40,IF(B41="",""," / "),B41,IF(B42="",""," / "),B42,B42,IF(B43="",""," / "),B43) -> Structure 100 mm / Bardage horizontal cl4 / Pignon | C35: =C36 -> m2 | D35: =IF(SUM(E35:H35)=0,0,SUM(E35:H35)) -> 79.468348 | E35: =SUM(E36:E45) -> 36.342271 | F35: =SUM(F36:F45) -> 19.23 | G35: =SUM(G36:G45) -> 16.671681 | H35: =SUM(H36:H45) -> 7.2243952 | I35: PEST-10-BARDAGE PIGNON | J35: ='MODELE LAROX'!E32 -> 100 | K35: =ROUNDUP(D35,0)*J35 -> 8000 | L35: =ROUNDUP(J35*E35,0) -> 3635 | M35: =L35/K35 -> 0.454375 | N35: =ROUNDUP(J35*F35,0) -> 1923 | O35: =N35/K35 -> 0.240375 | P35: =ROUNDUP(J35*G35,0) -> 1668 | Q35: =P35/K35 -> 0.2085 | R35: =ROUNDUP(J35*H35,0) -> 723 | S35: =R35/K35 -> 0.090375
B36: Structure 100 mm | C36: =IFERROR(IF(ISBLANK(VLOOKUP($B36,ARTICLE!$B$2:$J$200,3,FALSE)),"",VLOOKUP($B36,ARTICLE!$B$2:$J$200,3,FALSE)),"") -> m2 | D36: =IFERROR(IF(ISBLANK(VLOOKUP($B36,ARTICLE!$B$2:$J$200,4,FALSE)),"",VLOOKUP($B36,ARTICLE!$B$2:$J$200,4,FALSE)),"") -> 32.392748 | E36: =IFERROR(IF(ISBLANK(VLOOKUP($B36,ARTICLE!$B$2:$J$200,5,FALSE)),"",VLOOKUP($B36,ARTICLE!$B$2:$J$200,5,FALSE)),"") -> 18.822271 | F36: =IFERROR(IF(ISBLANK(VLOOKUP($B36,ARTICLE!$B$2:$J$200,6,FALSE)),"",VLOOKUP($B36,ARTICLE!$B$2:$J$200,6,FALSE)),"") -> 3.83 | G36: =IFERROR(IF(ISBLANK(VLOOKUP($B36,ARTICLE!$B$2:$J$200,7,FALSE)),"",VLOOKUP($B36,ARTICLE!$B$2:$J$200,7,FALSE)),"") -> 6.7956813 | H36: =IFERROR(IF(ISBLANK(VLOOKUP($B36,ARTICLE!$B$2:$J$200,8,FALSE)),"",VLOOKUP($B36,ARTICLE!$B$2:$J$200,8,FALSE)),"") -> 2.9447952
B37: Bardage horizontal cl4 | C37: =IFERROR(IF(ISBLANK(VLOOKUP($B37,ARTICLE!$B$2:$J$200,3,FALSE)),"",VLOOKUP($B37,ARTICLE!$B$2:$J$200,3,FALSE)),"") -> m2 | D37: =IFERROR(IF(ISBLANK(VLOOKUP($B37,ARTICLE!$B$2:$J$200,4,FALSE)),"",VLOOKUP($B37,ARTICLE!$B$2:$J$200,4,FALSE)),"") -> 29.3722 | E37: =IFERROR(IF(ISBLANK(VLOOKUP($B37,ARTICLE!$B$2:$J$200,5,FALSE)),"",VLOOKUP($B37,ARTICLE!$B$2:$J$200,5,FALSE)),"") -> 17.52 | F37: =IFERROR(IF(ISBLANK(VLOOKUP($B37,ARTICLE!$B$2:$J$200,6,FALSE)),"",VLOOKUP($B37,ARTICLE!$B$2:$J$200,6,FALSE)),"") -> 3.02 | G37: =IFERROR(IF(ISBLANK(VLOOKUP($B37,ARTICLE!$B$2:$J$200,7,FALSE)),"",VLOOKUP($B37,ARTICLE!$B$2:$J$200,7,FALSE)),"") -> 6.162 | H37: =IFERROR(IF(ISBLANK(VLOOKUP($B37,ARTICLE!$B$2:$J$200,8,FALSE)),"",VLOOKUP($B37,ARTICLE!$B$2:$J$200,8,FALSE)),"") -> 2.6702
B38: Pignon | C38: =IFERROR(IF(ISBLANK(VLOOKUP($B38,ARTICLE!$B$2:$J$200,3,FALSE)),"",VLOOKUP($B38,ARTICLE!$B$2:$J$200,3,FALSE)),"") -> m2 | D38: =IFERROR(IF(ISBLANK(VLOOKUP($B38,ARTICLE!$B$2:$J$200,4,FALSE)),"",VLOOKUP($B38,ARTICLE!$B$2:$J$200,4,FALSE)),"") -> 17.7034 | E38: =IFERROR(IF(ISBLANK(VLOOKUP($B38,ARTICLE!$B$2:$J$200,5,FALSE)),"",VLOOKUP($B38,ARTICLE!$B$2:$J$200,5,FALSE)),"") -> 0 | F38: =IFERROR(IF(ISBLANK(VLOOKUP($B38,ARTICLE!$B$2:$J$200,6,FALSE)),"",VLOOKUP($B38,ARTICLE!$B$2:$J$200,6,FALSE)),"") -> 12.38 | G38: =IFERROR(IF(ISBLANK(VLOOKUP($B38,ARTICLE!$B$2:$J$200,7,FALSE)),"",VLOOKUP($B38,ARTICLE!$B$2:$J$200,7,FALSE)),"") -> 3.714 | H38: =IFERROR(IF(ISBLANK(VLOOKUP($B38,ARTICLE!$B$2:$J$200,8,FALSE)),"",VLOOKUP($B38,ARTICLE!$B$2:$J$200,8,FALSE)),"") -> 1.6094
C39: =IFERROR(IF(ISBLANK(VLOOKUP($B39,ARTICLE!$B$2:$J$200,3,FALSE)),"",VLOOKUP($B39,ARTICLE!$B$2:$J$200,3,FALSE)),"") | D39: =IFERROR(IF(ISBLANK(VLOOKUP($B39,ARTICLE!$B$2:$J$200,4,FALSE)),"",VLOOKUP($B39,ARTICLE!$B$2:$J$200,4,FALSE)),"") | E39: =IFERROR(IF(ISBLANK(VLOOKUP($B39,ARTICLE!$B$2:$J$200,5,FALSE)),"",VLOOKUP($B39,ARTICLE!$B$2:$J$200,5,FALSE)),"") | F39: =IFERROR(IF(ISBLANK(VLOOKUP($B39,ARTICLE!$B$2:$J$200,6,FALSE)),"",VLOOKUP($B39,ARTICLE!$B$2:$J$200,6,FALSE)),"") | G39: =IFERROR(IF(ISBLANK(VLOOKUP($B39,ARTICLE!$B$2:$J$200,7,FALSE)),"",VLOOKUP($B39,ARTICLE!$B$2:$J$200,7,FALSE)),"") | H39: =IFERROR(IF(ISBLANK(VLOOKUP($B39,ARTICLE!$B$2:$J$200,8,FALSE)),"",VLOOKUP($B39,ARTICLE!$B$2:$J$200,8,FALSE)),"")
C40: =IFERROR(IF(ISBLANK(VLOOKUP($B40,ARTICLE!$B$2:$J$200,3,FALSE)),"",VLOOKUP($B40,ARTICLE!$B$2:$J$200,3,FALSE)),"") | D40: =IFERROR(IF(ISBLANK(VLOOKUP($B40,ARTICLE!$B$2:$J$200,4,FALSE)),"",VLOOKUP($B40,ARTICLE!$B$2:$J$200,4,FALSE)),"") | E40: =IFERROR(IF(ISBLANK(VLOOKUP($B40,ARTICLE!$B$2:$J$200,5,FALSE)),"",VLOOKUP($B40,ARTICLE!$B$2:$J$200,5,FALSE)),"") | F40: =IFERROR(IF(ISBLANK(VLOOKUP($B40,ARTICLE!$B$2:$J$200,6,FALSE)),"",VLOOKUP($B40,ARTICLE!$B$2:$J$200,6,FALSE)),"") | G40: =IFERROR(IF(ISBLANK(VLOOKUP($B40,ARTICLE!$B$2:$J$200,7,FALSE)),"",VLOOKUP($B40,ARTICLE!$B$2:$J$200,7,FALSE)),"") | H40: =IFERROR(IF(ISBLANK(VLOOKUP($B40,ARTICLE!$B$2:$J$200,8,FALSE)),"",VLOOKUP($B40,ARTICLE!$B$2:$J$200,8,FALSE)),"")
C41: =IFERROR(IF(ISBLANK(VLOOKUP($B41,ARTICLE!$B$2:$J$200,3,FALSE)),"",VLOOKUP($B41,ARTICLE!$B$2:$J$200,3,FALSE)),"") | D41: =IFERROR(IF(ISBLANK(VLOOKUP($B41,ARTICLE!$B$2:$J$200,4,FALSE)),"",VLOOKUP($B41,ARTICLE!$B$2:$J$200,4,FALSE)),"") | E41: =IFERROR(IF(ISBLANK(VLOOKUP($B41,ARTICLE!$B$2:$J$200,5,FALSE)),"",VLOOKUP($B41,ARTICLE!$B$2:$J$200,5,FALSE)),"") | F41: =IFERROR(IF(ISBLANK(VLOOKUP($B41,ARTICLE!$B$2:$J$200,6,FALSE)),"",VLOOKUP($B41,ARTICLE!$B$2:$J$200,6,FALSE)),"") | G41: =IFERROR(IF(ISBLANK(VLOOKUP($B41,ARTICLE!$B$2:$J$200,7,FALSE)),"",VLOOKUP($B41,ARTICLE!$B$2:$J$200,7,FALSE)),"") | H41: =IFERROR(IF(ISBLANK(VLOOKUP($B41,ARTICLE!$B$2:$J$200,8,FALSE)),"",VLOOKUP($B41,ARTICLE!$B$2:$J$200,8,FALSE)),"")
C42: =IFERROR(IF(ISBLANK(VLOOKUP($B42,ARTICLE!$B$2:$J$200,3,FALSE)),"",VLOOKUP($B42,ARTICLE!$B$2:$J$200,3,FALSE)),"") | D42: =IFERROR(IF(ISBLANK(VLOOKUP($B42,ARTICLE!$B$2:$J$200,4,FALSE)),"",VLOOKUP($B42,ARTICLE!$B$2:$J$200,4,FALSE)),"") | E42: =IFERROR(IF(ISBLANK(VLOOKUP($B42,ARTICLE!$B$2:$J$200,5,FALSE)),"",VLOOKUP($B42,ARTICLE!$B$2:$J$200,5,FALSE)),"") | F42: =IFERROR(IF(ISBLANK(VLOOKUP($B42,ARTICLE!$B$2:$J$200,6,FALSE)),"",VLOOKUP($B42,ARTICLE!$B$2:$J$200,6,FALSE)),"") | G42: =IFERROR(IF(ISBLANK(VLOOKUP($B42,ARTICLE!$B$2:$J$200,7,FALSE)),"",VLOOKUP($B42,ARTICLE!$B$2:$J$200,7,FALSE)),"") | H42: =IFERROR(IF(ISBLANK(VLOOKUP($B42,ARTICLE!$B$2:$J$200,8,FALSE)),"",VLOOKUP($B42,ARTICLE!$B$2:$J$200,8,FALSE)),"")
C43: =IFERROR(IF(ISBLANK(VLOOKUP($B43,ARTICLE!$B$2:$J$200,3,FALSE)),"",VLOOKUP($B43,ARTICLE!$B$2:$J$200,3,FALSE)),"") | D43: =IFERROR(IF(ISBLANK(VLOOKUP($B43,ARTICLE!$B$2:$J$200,4,FALSE)),"",VLOOKUP($B43,ARTICLE!$B$2:$J$200,4,FALSE)),"") | E43: =IFERROR(IF(ISBLANK(VLOOKUP($B43,ARTICLE!$B$2:$J$200,5,FALSE)),"",VLOOKUP($B43,ARTICLE!$B$2:$J$200,5,FALSE)),"") | F43: =IFERROR(IF(ISBLANK(VLOOKUP($B43,ARTICLE!$B$2:$J$200,6,FALSE)),"",VLOOKUP($B43,ARTICLE!$B$2:$J$200,6,FALSE)),"") | G43: =IFERROR(IF(ISBLANK(VLOOKUP($B43,ARTICLE!$B$2:$J$200,7,FALSE)),"",VLOOKUP($B43,ARTICLE!$B$2:$J$200,7,FALSE)),"") | H43: =IFERROR(IF(ISBLANK(VLOOKUP($B43,ARTICLE!$B$2:$J$200,8,FALSE)),"",VLOOKUP($B43,ARTICLE!$B$2:$J$200,8,FALSE)),"")
C44: =IFERROR(IF(ISBLANK(VLOOKUP($B44,ARTICLE!$B$2:$J$200,3,FALSE)),"",VLOOKUP($B44,ARTICLE!$B$2:$J$200,3,FALSE)),"") | D44: =IFERROR(IF(ISBLANK(VLOOKUP($B44,ARTICLE!$B$2:$J$200,4,FALSE)),"",VLOOKUP($B44,ARTICLE!$B$2:$J$200,4,FALSE)),"") | E44: =IFERROR(IF(ISBLANK(VLOOKUP($B44,ARTICLE!$B$2:$J$200,5,FALSE)),"",VLOOKUP($B44,ARTICLE!$B$2:$J$200,5,FALSE)),"") | F44: =IFERROR(IF(ISBLANK(VLOOKUP($B44,ARTICLE!$B$2:$J$200,6,FALSE)),"",VLOOKUP($B44,ARTICLE!$B$2:$J$200,6,FALSE)),"") | G44: =IFERROR(IF(ISBLANK(VLOOKUP($B44,ARTICLE!$B$2:$J$200,7,FALSE)),"",VLOOKUP($B44,ARTICLE!$B$2:$J$200,7,FALSE)),"") | H44: =IFERROR(IF(ISBLANK(VLOOKUP($B44,ARTICLE!$B$2:$J$200,8,FALSE)),"",VLOOKUP($B44,ARTICLE!$B$2:$J$200,8,FALSE)),"")
C45: =IFERROR(IF(ISBLANK(VLOOKUP($B45,ARTICLE!$B$2:$J$200,3,FALSE)),"",VLOOKUP($B45,ARTICLE!$B$2:$J$200,3,FALSE)),"") | D45: =IFERROR(IF(ISBLANK(VLOOKUP($B45,ARTICLE!$B$2:$J$200,4,FALSE)),"",VLOOKUP($B45,ARTICLE!$B$2:$J$200,4,FALSE)),"") | E45: =IFERROR(IF(ISBLANK(VLOOKUP($B45,ARTICLE!$B$2:$J$200,5,FALSE)),"",VLOOKUP($B45,ARTICLE!$B$2:$J$200,5,FALSE)),"") | F45: =IFERROR(IF(ISBLANK(VLOOKUP($B45,ARTICLE!$B$2:$J$200,6,FALSE)),"",VLOOKUP($B45,ARTICLE!$B$2:$J$200,6,FALSE)),"") | G45: =IFERROR(IF(ISBLANK(VLOOKUP($B45,ARTICLE!$B$2:$J$200,7,FALSE)),"",VLOOKUP($B45,ARTICLE!$B$2:$J$200,7,FALSE)),"") | H45: =IFERROR(IF(ISBLANK(VLOOKUP($B45,ARTICLE!$B$2:$J$200,8,FALSE)),"",VLOOKUP($B45,ARTICLE!$B$2:$J$200,8,FALSE)),"")
A46: =B46 -> OSB 22 / Structure PP 260-625 | B46: =CONCATENATE(B47,IF(B48="",""," / "),B48,IF(B49="",""," / "),B49,IF(B50="",""," / "),B50,IF(B51="",""," / "),B51,IF(B52="",""," / "),B52,IF(B53="",""," / "),B53,B53,IF(B54="",""," / "),B54) -> OSB 22 / Structure PP 260-625 | C46: =C47 -> m2 | D46: =IF(SUM(E46:H46)=0,0,SUM(E46:H46)) -> 62.557923 | E46: =SUM(E47:E56) -> 36.636799 | F46: =SUM(F47:F56) -> 7.11 | G46: =SUM(G47:G56) -> 13.12404 | H46: =SUM(H47:H56) -> 5.6870839 | I46: PP-625 | J46: ='MODELE LAROX'!E33 -> 96 | K46: =ROUNDUP(D46,0)*J46 -> 6048 | L46: =ROUNDUP(J46*E46,0) -> 3518 | M46: =L46/K46 -> 0.58167989 | N46: =ROUNDUP(J46*F46,0) -> 683 | O46: =N46/K46 -> 0.11292989 | P46: =ROUNDUP(J46*G46,0) -> 1260 | Q46: =P46/K46 -> 0.20833333 | R46: =ROUNDUP(J46*H46,0) -> 546 | S46: =R46/K46 -> 0.090277778
B47: OSB 22 | C47: =IFERROR(IF(ISBLANK(VLOOKUP($B47,ARTICLE!$B$2:$J$200,3,FALSE)),"",VLOOKUP($B47,ARTICLE!$B$2:$J$200,3,FALSE)),"") -> m2 | D47: =IFERROR(IF(ISBLANK(VLOOKUP($B47,ARTICLE!$B$2:$J$200,4,FALSE)),"",VLOOKUP($B47,ARTICLE!$B$2:$J$200,4,FALSE)),"") -> 14.6575 | E47: =IFERROR(IF(ISBLANK(VLOOKUP($B47,ARTICLE!$B$2:$J$200,5,FALSE)),"",VLOOKUP($B47,ARTICLE!$B$2:$J$200,5,FALSE)),"") -> 9.42 | F47: =IFERROR(IF(ISBLANK(VLOOKUP($B47,ARTICLE!$B$2:$J$200,6,FALSE)),"",VLOOKUP($B47,ARTICLE!$B$2:$J$200,6,FALSE)),"") -> 0.83 | G47: =IFERROR(IF(ISBLANK(VLOOKUP($B47,ARTICLE!$B$2:$J$200,7,FALSE)),"",VLOOKUP($B47,ARTICLE!$B$2:$J$200,7,FALSE)),"") -> 3.075 | H47: =IFERROR(IF(ISBLANK(VLOOKUP($B47,ARTICLE!$B$2:$J$200,8,FALSE)),"",VLOOKUP($B47,ARTICLE!$B$2:$J$200,8,FALSE)),"") -> 1.3325
B48: Structure PP 260-625 | C48: =IFERROR(IF(ISBLANK(VLOOKUP($B48,ARTICLE!$B$2:$J$200,3,FALSE)),"",VLOOKUP($B48,ARTICLE!$B$2:$J$200,3,FALSE)),"") -> m2 | D48: =IFERROR(IF(ISBLANK(VLOOKUP($B48,ARTICLE!$B$2:$J$200,4,FALSE)),"",VLOOKUP($B48,ARTICLE!$B$2:$J$200,4,FALSE)),"") -> 47.900423 | E48: =IFERROR(IF(ISBLANK(VLOOKUP($B48,ARTICLE!$B$2:$J$200,5,FALSE)),"",VLOOKUP($B48,ARTICLE!$B$2:$J$200,5,FALSE)),"") -> 27.216799 | F48: =IFERROR(IF(ISBLANK(VLOOKUP($B48,ARTICLE!$B$2:$J$200,6,FALSE)),"",VLOOKUP($B48,ARTICLE!$B$2:$J$200,6,FALSE)),"") -> 6.28 | G48: =IFERROR(IF(ISBLANK(VLOOKUP($B48,ARTICLE!$B$2:$J$200,7,FALSE)),"",VLOOKUP($B48,ARTICLE!$B$2:$J$200,7,FALSE)),"") -> 10.04904 | H48: =IFERROR(IF(ISBLANK(VLOOKUP($B48,ARTICLE!$B$2:$J$200,8,FALSE)),"",VLOOKUP($B48,ARTICLE!$B$2:$J$200,8,FALSE)),"") -> 4.3545839
C49: =IFERROR(IF(ISBLANK(VLOOKUP($B49,ARTICLE!$B$2:$J$200,3,FALSE)),"",VLOOKUP($B49,ARTICLE!$B$2:$J$200,3,FALSE)),"") | D49: =IFERROR(IF(ISBLANK(VLOOKUP($B49,ARTICLE!$B$2:$J$200,4,FALSE)),"",VLOOKUP($B49,ARTICLE!$B$2:$J$200,4,FALSE)),"") | E49: =IFERROR(IF(ISBLANK(VLOOKUP($B49,ARTICLE!$B$2:$J$200,5,FALSE)),"",VLOOKUP($B49,ARTICLE!$B$2:$J$200,5,FALSE)),"") | F49: =IFERROR(IF(ISBLANK(VLOOKUP($B49,ARTICLE!$B$2:$J$200,6,FALSE)),"",VLOOKUP($B49,ARTICLE!$B$2:$J$200,6,FALSE)),"") | G49: =IFERROR(IF(ISBLANK(VLOOKUP($B49,ARTICLE!$B$2:$J$200,7,FALSE)),"",VLOOKUP($B49,ARTICLE!$B$2:$J$200,7,FALSE)),"") | H49: =IFERROR(IF(ISBLANK(VLOOKUP($B49,ARTICLE!$B$2:$J$200,8,FALSE)),"",VLOOKUP($B49,ARTICLE!$B$2:$J$200,8,FALSE)),"")
C50: =IFERROR(IF(ISBLANK(VLOOKUP($B50,ARTICLE!$B$2:$J$200,3,FALSE)),"",VLOOKUP($B50,ARTICLE!$B$2:$J$200,3,FALSE)),"") | D50: =IFERROR(IF(ISBLANK(VLOOKUP($B50,ARTICLE!$B$2:$J$200,4,FALSE)),"",VLOOKUP($B50,ARTICLE!$B$2:$J$200,4,FALSE)),"") | E50: =IFERROR(IF(ISBLANK(VLOOKUP($B50,ARTICLE!$B$2:$J$200,5,FALSE)),"",VLOOKUP($B50,ARTICLE!$B$2:$J$200,5,FALSE)),"") | F50: =IFERROR(IF(ISBLANK(VLOOKUP($B50,ARTICLE!$B$2:$J$200,6,FALSE)),"",VLOOKUP($B50,ARTICLE!$B$2:$J$200,6,FALSE)),"") | G50: =IFERROR(IF(ISBLANK(VLOOKUP($B50,ARTICLE!$B$2:$J$200,7,FALSE)),"",VLOOKUP($B50,ARTICLE!$B$2:$J$200,7,FALSE)),"") | H50: =IFERROR(IF(ISBLANK(VLOOKUP($B50,ARTICLE!$B$2:$J$200,8,FALSE)),"",VLOOKUP($B50,ARTICLE!$B$2:$J$200,8,FALSE)),"")
C51: =IFERROR(IF(ISBLANK(VLOOKUP($B51,ARTICLE!$B$2:$J$200,3,FALSE)),"",VLOOKUP($B51,ARTICLE!$B$2:$J$200,3,FALSE)),"") | D51: =IFERROR(IF(ISBLANK(VLOOKUP($B51,ARTICLE!$B$2:$J$200,4,FALSE)),"",VLOOKUP($B51,ARTICLE!$B$2:$J$200,4,FALSE)),"") | E51: =IFERROR(IF(ISBLANK(VLOOKUP($B51,ARTICLE!$B$2:$J$200,5,FALSE)),"",VLOOKUP($B51,ARTICLE!$B$2:$J$200,5,FALSE)),"") | F51: =IFERROR(IF(ISBLANK(VLOOKUP($B51,ARTICLE!$B$2:$J$200,6,FALSE)),"",VLOOKUP($B51,ARTICLE!$B$2:$J$200,6,FALSE)),"") | G51: =IFERROR(IF(ISBLANK(VLOOKUP($B51,ARTICLE!$B$2:$J$200,7,FALSE)),"",VLOOKUP($B51,ARTICLE!$B$2:$J$200,7,FALSE)),"") | H51: =IFERROR(IF(ISBLANK(VLOOKUP($B51,ARTICLE!$B$2:$J$200,8,FALSE)),"",VLOOKUP($B51,ARTICLE!$B$2:$J$200,8,FALSE)),"")
C52: =IFERROR(IF(ISBLANK(VLOOKUP($B52,ARTICLE!$B$2:$J$200,3,FALSE)),"",VLOOKUP($B52,ARTICLE!$B$2:$J$200,3,FALSE)),"") | D52: =IFERROR(IF(ISBLANK(VLOOKUP($B52,ARTICLE!$B$2:$J$200,4,FALSE)),"",VLOOKUP($B52,ARTICLE!$B$2:$J$200,4,FALSE)),"") | E52: =IFERROR(IF(ISBLANK(VLOOKUP($B52,ARTICLE!$B$2:$J$200,5,FALSE)),"",VLOOKUP($B52,ARTICLE!$B$2:$J$200,5,FALSE)),"") | F52: =IFERROR(IF(ISBLANK(VLOOKUP($B52,ARTICLE!$B$2:$J$200,6,FALSE)),"",VLOOKUP($B52,ARTICLE!$B$2:$J$200,6,FALSE)),"") | G52: =IFERROR(IF(ISBLANK(VLOOKUP($B52,ARTICLE!$B$2:$J$200,7,FALSE)),"",VLOOKUP($B52,ARTICLE!$B$2:$J$200,7,FALSE)),"") | H52: =IFERROR(IF(ISBLANK(VLOOKUP($B52,ARTICLE!$B$2:$J$200,8,FALSE)),"",VLOOKUP($B52,ARTICLE!$B$2:$J$200,8,FALSE)),"")
C53: =IFERROR(IF(ISBLANK(VLOOKUP($B53,ARTICLE!$B$2:$J$200,3,FALSE)),"",VLOOKUP($B53,ARTICLE!$B$2:$J$200,3,FALSE)),"") | D53: =IFERROR(IF(ISBLANK(VLOOKUP($B53,ARTICLE!$B$2:$J$200,4,FALSE)),"",VLOOKUP($B53,ARTICLE!$B$2:$J$200,4,FALSE)),"") | E53: =IFERROR(IF(ISBLANK(VLOOKUP($B53,ARTICLE!$B$2:$J$200,5,FALSE)),"",VLOOKUP($B53,ARTICLE!$B$2:$J$200,5,FALSE)),"") | F53: =IFERROR(IF(ISBLANK(VLOOKUP($B53,ARTICLE!$B$2:$J$200,6,FALSE)),"",VLOOKUP($B53,ARTICLE!$B$2:$J$200,6,FALSE)),"") | G53: =IFERROR(IF(ISBLANK(VLOOKUP($B53,ARTICLE!$B$2:$J$200,7,FALSE)),"",VLOOKUP($B53,ARTICLE!$B$2:$J$200,7,FALSE)),"") | H53: =IFERROR(IF(ISBLANK(VLOOKUP($B53,ARTICLE!$B$2:$J$200,8,FALSE)),"",VLOOKUP($B53,ARTICLE!$B$2:$J$200,8,FALSE)),"")
C54: =IFERROR(IF(ISBLANK(VLOOKUP($B54,ARTICLE!$B$2:$J$200,3,FALSE)),"",VLOOKUP($B54,ARTICLE!$B$2:$J$200,3,FALSE)),"") | D54: =IFERROR(IF(ISBLANK(VLOOKUP($B54,ARTICLE!$B$2:$J$200,4,FALSE)),"",VLOOKUP($B54,ARTICLE!$B$2:$J$200,4,FALSE)),"") | E54: =IFERROR(IF(ISBLANK(VLOOKUP($B54,ARTICLE!$B$2:$J$200,5,FALSE)),"",VLOOKUP($B54,ARTICLE!$B$2:$J$200,5,FALSE)),"") | F54: =IFERROR(IF(ISBLANK(VLOOKUP($B54,ARTICLE!$B$2:$J$200,6,FALSE)),"",VLOOKUP($B54,ARTICLE!$B$2:$J$200,6,FALSE)),"") | G54: =IFERROR(IF(ISBLANK(VLOOKUP($B54,ARTICLE!$B$2:$J$200,7,FALSE)),"",VLOOKUP($B54,ARTICLE!$B$2:$J$200,7,FALSE)),"") | H54: =IFERROR(IF(ISBLANK(VLOOKUP($B54,ARTICLE!$B$2:$J$200,8,FALSE)),"",VLOOKUP($B54,ARTICLE!$B$2:$J$200,8,FALSE)),"")
C55: =IFERROR(IF(ISBLANK(VLOOKUP($B55,ARTICLE!$B$2:$J$200,3,FALSE)),"",VLOOKUP($B55,ARTICLE!$B$2:$J$200,3,FALSE)),"") | D55: =IFERROR(IF(ISBLANK(VLOOKUP($B55,ARTICLE!$B$2:$J$200,4,FALSE)),"",VLOOKUP($B55,ARTICLE!$B$2:$J$200,4,FALSE)),"") | E55: =IFERROR(IF(ISBLANK(VLOOKUP($B55,ARTICLE!$B$2:$J$200,5,FALSE)),"",VLOOKUP($B55,ARTICLE!$B$2:$J$200,5,FALSE)),"") | F55: =IFERROR(IF(ISBLANK(VLOOKUP($B55,ARTICLE!$B$2:$J$200,6,FALSE)),"",VLOOKUP($B55,ARTICLE!$B$2:$J$200,6,FALSE)),"") | G55: =IFERROR(IF(ISBLANK(VLOOKUP($B55,ARTICLE!$B$2:$J$200,7,FALSE)),"",VLOOKUP($B55,ARTICLE!$B$2:$J$200,7,FALSE)),"") | H55: =IFERROR(IF(ISBLANK(VLOOKUP($B55,ARTICLE!$B$2:$J$200,8,FALSE)),"",VLOOKUP($B55,ARTICLE!$B$2:$J$200,8,FALSE)),"")
C56: =IFERROR(IF(ISBLANK(VLOOKUP($B56,ARTICLE!$B$2:$J$200,3,FALSE)),"",VLOOKUP($B56,ARTICLE!$B$2:$J$200,3,FALSE)),"") | D56: =IFERROR(IF(ISBLANK(VLOOKUP($B56,ARTICLE!$B$2:$J$200,4,FALSE)),"",VLOOKUP($B56,ARTICLE!$B$2:$J$200,4,FALSE)),"") | E56: =IFERROR(IF(ISBLANK(VLOOKUP($B56,ARTICLE!$B$2:$J$200,5,FALSE)),"",VLOOKUP($B56,ARTICLE!$B$2:$J$200,5,FALSE)),"") | F56: =IFERROR(IF(ISBLANK(VLOOKUP($B56,ARTICLE!$B$2:$J$200,6,FALSE)),"",VLOOKUP($B56,ARTICLE!$B$2:$J$200,6,FALSE)),"") | G56: =IFERROR(IF(ISBLANK(VLOOKUP($B56,ARTICLE!$B$2:$J$200,7,FALSE)),"",VLOOKUP($B56,ARTICLE!$B$2:$J$200,7,FALSE)),"") | H56: =IFERROR(IF(ISBLANK(VLOOKUP($B56,ARTICLE!$B$2:$J$200,8,FALSE)),"",VLOOKUP($B56,ARTICLE!$B$2:$J$200,8,FALSE)),"")
A57: =B57 -> OSB 22 / Structure PP 260-313 | B57: =CONCATENATE(B58,IF(B59="",""," / "),B59,IF(B60="",""," / "),B60,IF(B61="",""," / "),B61,IF(B62="",""," / "),B62,IF(B63="",""," / "),B63,IF(B64="",""," / "),B64,B64,IF(B65="",""," / "),B65) -> OSB 22 / Structure PP 260-313 | C57: =C58 -> m2 | D57: =IF(SUM(E57:H57)=0,0,SUM(E57:H57)) -> 81.405737 | E57: =SUM(E58:E67) -> 46.887089 | F57: =SUM(F58:F67) -> 10.04 | G57: =SUM(G58:G67) -> 17.078127 | H57: =SUM(H58:H67) -> 7.4005216 | I57: PP-313 | K57: =ROUNDUP(D57,0)*J57 -> 0 | L57: =ROUNDUP(J57*E57,0) -> 0 | M57: =L57/K57 -> #DIV/0! | N57: =ROUNDUP(J57*F57,0) -> 0 | O57: =N57/K57 -> #DIV/0! | P57: =ROUNDUP(J57*G57,0) -> 0 | Q57: =P57/K57 -> #DIV/0! | R57: =ROUNDUP(J57*H57,0) -> 0 | S57: =R57/K57 -> #DIV/0!
B58: OSB 22 | C58: =IFERROR(IF(ISBLANK(VLOOKUP($B58,ARTICLE!$B$2:$J$200,3,FALSE)),"",VLOOKUP($B58,ARTICLE!$B$2:$J$200,3,FALSE)),"") -> m2 | D58: =IFERROR(IF(ISBLANK(VLOOKUP($B58,ARTICLE!$B$2:$J$200,4,FALSE)),"",VLOOKUP($B58,ARTICLE!$B$2:$J$200,4,FALSE)),"") -> 14.6575 | E58: =IFERROR(IF(ISBLANK(VLOOKUP($B58,ARTICLE!$B$2:$J$200,5,FALSE)),"",VLOOKUP($B58,ARTICLE!$B$2:$J$200,5,FALSE)),"") -> 9.42 | F58: =IFERROR(IF(ISBLANK(VLOOKUP($B58,ARTICLE!$B$2:$J$200,6,FALSE)),"",VLOOKUP($B58,ARTICLE!$B$2:$J$200,6,FALSE)),"") -> 0.83 | G58: =IFERROR(IF(ISBLANK(VLOOKUP($B58,ARTICLE!$B$2:$J$200,7,FALSE)),"",VLOOKUP($B58,ARTICLE!$B$2:$J$200,7,FALSE)),"") -> 3.075 | H58: =IFERROR(IF(ISBLANK(VLOOKUP($B58,ARTICLE!$B$2:$J$200,8,FALSE)),"",VLOOKUP($B58,ARTICLE!$B$2:$J$200,8,FALSE)),"") -> 1.3325
B59: Structure PP 260-313 | C59: =IFERROR(IF(ISBLANK(VLOOKUP($B59,ARTICLE!$B$2:$J$200,3,FALSE)),"",VLOOKUP($B59,ARTICLE!$B$2:$J$200,3,FALSE)),"") -> m2 | D59: =IFERROR(IF(ISBLANK(VLOOKUP($B59,ARTICLE!$B$2:$J$200,4,FALSE)),"",VLOOKUP($B59,ARTICLE!$B$2:$J$200,4,FALSE)),"") -> 66.748237 | E59: =IFERROR(IF(ISBLANK(VLOOKUP($B59,ARTICLE!$B$2:$J$200,5,FALSE)),"",VLOOKUP($B59,ARTICLE!$B$2:$J$200,5,FALSE)),"") -> 37.467089 | F59: =IFERROR(IF(ISBLANK(VLOOKUP($B59,ARTICLE!$B$2:$J$200,6,FALSE)),"",VLOOKUP($B59,ARTICLE!$B$2:$J$200,6,FALSE)),"") -> 9.21 | G59: =IFERROR(IF(ISBLANK(VLOOKUP($B59,ARTICLE!$B$2:$J$200,7,FALSE)),"",VLOOKUP($B59,ARTICLE!$B$2:$J$200,7,FALSE)),"") -> 14.003127 | H59: =IFERROR(IF(ISBLANK(VLOOKUP($B59,ARTICLE!$B$2:$J$200,8,FALSE)),"",VLOOKUP($B59,ARTICLE!$B$2:$J$200,8,FALSE)),"") -> 6.0680216
C60: =IFERROR(IF(ISBLANK(VLOOKUP($B60,ARTICLE!$B$2:$J$200,3,FALSE)),"",VLOOKUP($B60,ARTICLE!$B$2:$J$200,3,FALSE)),"") | D60: =IFERROR(IF(ISBLANK(VLOOKUP($B60,ARTICLE!$B$2:$J$200,4,FALSE)),"",VLOOKUP($B60,ARTICLE!$B$2:$J$200,4,FALSE)),"") | E60: =IFERROR(IF(ISBLANK(VLOOKUP($B60,ARTICLE!$B$2:$J$200,5,FALSE)),"",VLOOKUP($B60,ARTICLE!$B$2:$J$200,5,FALSE)),"") | F60: =IFERROR(IF(ISBLANK(VLOOKUP($B60,ARTICLE!$B$2:$J$200,6,FALSE)),"",VLOOKUP($B60,ARTICLE!$B$2:$J$200,6,FALSE)),"") | G60: =IFERROR(IF(ISBLANK(VLOOKUP($B60,ARTICLE!$B$2:$J$200,7,FALSE)),"",VLOOKUP($B60,ARTICLE!$B$2:$J$200,7,FALSE)),"") | H60: =IFERROR(IF(ISBLANK(VLOOKUP($B60,ARTICLE!$B$2:$J$200,8,FALSE)),"",VLOOKUP($B60,ARTICLE!$B$2:$J$200,8,FALSE)),"")
C61: =IFERROR(IF(ISBLANK(VLOOKUP($B61,ARTICLE!$B$2:$J$200,3,FALSE)),"",VLOOKUP($B61,ARTICLE!$B$2:$J$200,3,FALSE)),"") | D61: =IFERROR(IF(ISBLANK(VLOOKUP($B61,ARTICLE!$B$2:$J$200,4,FALSE)),"",VLOOKUP($B61,ARTICLE!$B$2:$J$200,4,FALSE)),"") | E61: =IFERROR(IF(ISBLANK(VLOOKUP($B61,ARTICLE!$B$2:$J$200,5,FALSE)),"",VLOOKUP($B61,ARTICLE!$B$2:$J$200,5,FALSE)),"") | F61: =IFERROR(IF(ISBLANK(VLOOKUP($B61,ARTICLE!$B$2:$J$200,6,FALSE)),"",VLOOKUP($B61,ARTICLE!$B$2:$J$200,6,FALSE)),"") | G61: =IFERROR(IF(ISBLANK(VLOOKUP($B61,ARTICLE!$B$2:$J$200,7,FALSE)),"",VLOOKUP($B61,ARTICLE!$B$2:$J$200,7,FALSE)),"") | H61: =IFERROR(IF(ISBLANK(VLOOKUP($B61,ARTICLE!$B$2:$J$200,8,FALSE)),"",VLOOKUP($B61,ARTICLE!$B$2:$J$200,8,FALSE)),"")
C62: =IFERROR(IF(ISBLANK(VLOOKUP($B62,ARTICLE!$B$2:$J$200,3,FALSE)),"",VLOOKUP($B62,ARTICLE!$B$2:$J$200,3,FALSE)),"") | D62: =IFERROR(IF(ISBLANK(VLOOKUP($B62,ARTICLE!$B$2:$J$200,4,FALSE)),"",VLOOKUP($B62,ARTICLE!$B$2:$J$200,4,FALSE)),"") | E62: =IFERROR(IF(ISBLANK(VLOOKUP($B62,ARTICLE!$B$2:$J$200,5,FALSE)),"",VLOOKUP($B62,ARTICLE!$B$2:$J$200,5,FALSE)),"") | F62: =IFERROR(IF(ISBLANK(VLOOKUP($B62,ARTICLE!$B$2:$J$200,6,FALSE)),"",VLOOKUP($B62,ARTICLE!$B$2:$J$200,6,FALSE)),"") | G62: =IFERROR(IF(ISBLANK(VLOOKUP($B62,ARTICLE!$B$2:$J$200,7,FALSE)),"",VLOOKUP($B62,ARTICLE!$B$2:$J$200,7,FALSE)),"") | H62: =IFERROR(IF(ISBLANK(VLOOKUP($B62,ARTICLE!$B$2:$J$200,8,FALSE)),"",VLOOKUP($B62,ARTICLE!$B$2:$J$200,8,FALSE)),"")
C63: =IFERROR(IF(ISBLANK(VLOOKUP($B63,ARTICLE!$B$2:$J$200,3,FALSE)),"",VLOOKUP($B63,ARTICLE!$B$2:$J$200,3,FALSE)),"") | D63: =IFERROR(IF(ISBLANK(VLOOKUP($B63,ARTICLE!$B$2:$J$200,4,FALSE)),"",VLOOKUP($B63,ARTICLE!$B$2:$J$200,4,FALSE)),"") | E63: =IFERROR(IF(ISBLANK(VLOOKUP($B63,ARTICLE!$B$2:$J$200,5,FALSE)),"",VLOOKUP($B63,ARTICLE!$B$2:$J$200,5,FALSE)),"") | F63: =IFERROR(IF(ISBLANK(VLOOKUP($B63,ARTICLE!$B$2:$J$200,6,FALSE)),"",VLOOKUP($B63,ARTICLE!$B$2:$J$200,6,FALSE)),"") | G63: =IFERROR(IF(ISBLANK(VLOOKUP($B63,ARTICLE!$B$2:$J$200,7,FALSE)),"",VLOOKUP($B63,ARTICLE!$B$2:$J$200,7,FALSE)),"") | H63: =IFERROR(IF(ISBLANK(VLOOKUP($B63,ARTICLE!$B$2:$J$200,8,FALSE)),"",VLOOKUP($B63,ARTICLE!$B$2:$J$200,8,FALSE)),"")
C64: =IFERROR(IF(ISBLANK(VLOOKUP($B64,ARTICLE!$B$2:$J$200,3,FALSE)),"",VLOOKUP($B64,ARTICLE!$B$2:$J$200,3,FALSE)),"") | D64: =IFERROR(IF(ISBLANK(VLOOKUP($B64,ARTICLE!$B$2:$J$200,4,FALSE)),"",VLOOKUP($B64,ARTICLE!$B$2:$J$200,4,FALSE)),"") | E64: =IFERROR(IF(ISBLANK(VLOOKUP($B64,ARTICLE!$B$2:$J$200,5,FALSE)),"",VLOOKUP($B64,ARTICLE!$B$2:$J$200,5,FALSE)),"") | F64: =IFERROR(IF(ISBLANK(VLOOKUP($B64,ARTICLE!$B$2:$J$200,6,FALSE)),"",VLOOKUP($B64,ARTICLE!$B$2:$J$200,6,FALSE)),"") | G64: =IFERROR(IF(ISBLANK(VLOOKUP($B64,ARTICLE!$B$2:$J$200,7,FALSE)),"",VLOOKUP($B64,ARTICLE!$B$2:$J$200,7,FALSE)),"") | H64: =IFERROR(IF(ISBLANK(VLOOKUP($B64,ARTICLE!$B$2:$J$200,8,FALSE)),"",VLOOKUP($B64,ARTICLE!$B$2:$J$200,8,FALSE)),"")
C65: =IFERROR(IF(ISBLANK(VLOOKUP($B65,ARTICLE!$B$2:$J$200,3,FALSE)),"",VLOOKUP($B65,ARTICLE!$B$2:$J$200,3,FALSE)),"") | D65: =IFERROR(IF(ISBLANK(VLOOKUP($B65,ARTICLE!$B$2:$J$200,4,FALSE)),"",VLOOKUP($B65,ARTICLE!$B$2:$J$200,4,FALSE)),"") | E65: =IFERROR(IF(ISBLANK(VLOOKUP($B65,ARTICLE!$B$2:$J$200,5,FALSE)),"",VLOOKUP($B65,ARTICLE!$B$2:$J$200,5,FALSE)),"") | F65: =IFERROR(IF(ISBLANK(VLOOKUP($B65,ARTICLE!$B$2:$J$200,6,FALSE)),"",VLOOKUP($B65,ARTICLE!$B$2:$J$200,6,FALSE)),"") | G65: =IFERROR(IF(ISBLANK(VLOOKUP($B65,ARTICLE!$B$2:$J$200,7,FALSE)),"",VLOOKUP($B65,ARTICLE!$B$2:$J$200,7,FALSE)),"") | H65: =IFERROR(IF(ISBLANK(VLOOKUP($B65,ARTICLE!$B$2:$J$200,8,FALSE)),"",VLOOKUP($B65,ARTICLE!$B$2:$J$200,8,FALSE)),"")
C66: =IFERROR(IF(ISBLANK(VLOOKUP($B66,ARTICLE!$B$2:$J$200,3,FALSE)),"",VLOOKUP($B66,ARTICLE!$B$2:$J$200,3,FALSE)),"") | D66: =IFERROR(IF(ISBLANK(VLOOKUP($B66,ARTICLE!$B$2:$J$200,4,FALSE)),"",VLOOKUP($B66,ARTICLE!$B$2:$J$200,4,FALSE)),"") | E66: =IFERROR(IF(ISBLANK(VLOOKUP($B66,ARTICLE!$B$2:$J$200,5,FALSE)),"",VLOOKUP($B66,ARTICLE!$B$2:$J$200,5,FALSE)),"") | F66: =IFERROR(IF(ISBLANK(VLOOKUP($B66,ARTICLE!$B$2:$J$200,6,FALSE)),"",VLOOKUP($B66,ARTICLE!$B$2:$J$200,6,FALSE)),"") | G66: =IFERROR(IF(ISBLANK(VLOOKUP($B66,ARTICLE!$B$2:$J$200,7,FALSE)),"",VLOOKUP($B66,ARTICLE!$B$2:$J$200,7,FALSE)),"") | H66: =IFERROR(IF(ISBLANK(VLOOKUP($B66,ARTICLE!$B$2:$J$200,8,FALSE)),"",VLOOKUP($B66,ARTICLE!$B$2:$J$200,8,FALSE)),"")
C67: =IFERROR(IF(ISBLANK(VLOOKUP($B67,ARTICLE!$B$2:$J$200,3,FALSE)),"",VLOOKUP($B67,ARTICLE!$B$2:$J$200,3,FALSE)),"") | D67: =IFERROR(IF(ISBLANK(VLOOKUP($B67,ARTICLE!$B$2:$J$200,4,FALSE)),"",VLOOKUP($B67,ARTICLE!$B$2:$J$200,4,FALSE)),"") | E67: =IFERROR(IF(ISBLANK(VLOOKUP($B67,ARTICLE!$B$2:$J$200,5,FALSE)),"",VLOOKUP($B67,ARTICLE!$B$2:$J$200,5,FALSE)),"") | F67: =IFERROR(IF(ISBLANK(VLOOKUP($B67,ARTICLE!$B$2:$J$200,6,FALSE)),"",VLOOKUP($B67,ARTICLE!$B$2:$J$200,6,FALSE)),"") | G67: =IFERROR(IF(ISBLANK(VLOOKUP($B67,ARTICLE!$B$2:$J$200,7,FALSE)),"",VLOOKUP($B67,ARTICLE!$B$2:$J$200,7,FALSE)),"") | H67: =IFERROR(IF(ISBLANK(VLOOKUP($B67,ARTICLE!$B$2:$J$200,8,FALSE)),"",VLOOKUP($B67,ARTICLE!$B$2:$J$200,8,FALSE)),"")
A68: =B68 | B68: =CONCATENATE(B69,IF(B70="",""," / "),B70,IF(B71="",""," / "),B71,IF(B72="",""," / "),B72,IF(B73="",""," / "),B73,IF(B74="",""," / "),B74,IF(B75="",""," / "),B75,B75,IF(B76="",""," / "),B76) | C68: =C69 | D68: =IF(SUM(E68:H68)=0,0,SUM(E68:H68)) -> 0 | E68: =SUM(E69:E78) -> 0 | F68: =SUM(F69:F78) -> 0 | G68: =SUM(G69:G78) -> 0 | H68: =SUM(H69:H78) -> 0 | K68: =ROUNDUP(D68,0)*J68 -> 0 | L68: =ROUNDUP(J68*E68,0) -> 0 | M68: =L68/K68 -> #DIV/0! | N68: =ROUNDUP(J68*F68,0) -> 0 | O68: =N68/K68 -> #DIV/0! | P68: =ROUNDUP(J68*G68,0) -> 0 | Q68: =P68/K68 -> #DIV/0! | R68: =ROUNDUP(J68*H68,0) -> 0 | S68: =R68/K68 -> #DIV/0!
C69: =IFERROR(IF(ISBLANK(VLOOKUP($B69,ARTICLE!$B$2:$J$200,3,FALSE)),"",VLOOKUP($B69,ARTICLE!$B$2:$J$200,3,FALSE)),"") | D69: =IFERROR(IF(ISBLANK(VLOOKUP($B69,ARTICLE!$B$2:$J$200,4,FALSE)),"",VLOOKUP($B69,ARTICLE!$B$2:$J$200,4,FALSE)),"") | E69: =IFERROR(IF(ISBLANK(VLOOKUP($B69,ARTICLE!$B$2:$J$200,5,FALSE)),"",VLOOKUP($B69,ARTICLE!$B$2:$J$200,5,FALSE)),"") | F69: =IFERROR(IF(ISBLANK(VLOOKUP($B69,ARTICLE!$B$2:$J$200,6,FALSE)),"",VLOOKUP($B69,ARTICLE!$B$2:$J$200,6,FALSE)),"") | G69: =IFERROR(IF(ISBLANK(VLOOKUP($B69,ARTICLE!$B$2:$J$200,7,FALSE)),"",VLOOKUP($B69,ARTICLE!$B$2:$J$200,7,FALSE)),"") | H69: =IFERROR(IF(ISBLANK(VLOOKUP($B69,ARTICLE!$B$2:$J$200,8,FALSE)),"",VLOOKUP($B69,ARTICLE!$B$2:$J$200,8,FALSE)),"")
C70: =IFERROR(IF(ISBLANK(VLOOKUP($B70,ARTICLE!$B$2:$J$200,3,FALSE)),"",VLOOKUP($B70,ARTICLE!$B$2:$J$200,3,FALSE)),"") | D70: =IFERROR(IF(ISBLANK(VLOOKUP($B70,ARTICLE!$B$2:$J$200,4,FALSE)),"",VLOOKUP($B70,ARTICLE!$B$2:$J$200,4,FALSE)),"") | E70: =IFERROR(IF(ISBLANK(VLOOKUP($B70,ARTICLE!$B$2:$J$200,5,FALSE)),"",VLOOKUP($B70,ARTICLE!$B$2:$J$200,5,FALSE)),"") | F70: =IFERROR(IF(ISBLANK(VLOOKUP($B70,ARTICLE!$B$2:$J$200,6,FALSE)),"",VLOOKUP($B70,ARTICLE!$B$2:$J$200,6,FALSE)),"") | G70: =IFERROR(IF(ISBLANK(VLOOKUP($B70,ARTICLE!$B$2:$J$200,7,FALSE)),"",VLOOKUP($B70,ARTICLE!$B$2:$J$200,7,FALSE)),"") | H70: =IFERROR(IF(ISBLANK(VLOOKUP($B70,ARTICLE!$B$2:$J$200,8,FALSE)),"",VLOOKUP($B70,ARTICLE!$B$2:$J$200,8,FALSE)),"")
C71: =IFERROR(IF(ISBLANK(VLOOKUP($B71,ARTICLE!$B$2:$J$200,3,FALSE)),"",VLOOKUP($B71,ARTICLE!$B$2:$J$200,3,FALSE)),"") | D71: =IFERROR(IF(ISBLANK(VLOOKUP($B71,ARTICLE!$B$2:$J$200,4,FALSE)),"",VLOOKUP($B71,ARTICLE!$B$2:$J$200,4,FALSE)),"") | E71: =IFERROR(IF(ISBLANK(VLOOKUP($B71,ARTICLE!$B$2:$J$200,5,FALSE)),"",VLOOKUP($B71,ARTICLE!$B$2:$J$200,5,FALSE)),"") | F71: =IFERROR(IF(ISBLANK(VLOOKUP($B71,ARTICLE!$B$2:$J$200,6,FALSE)),"",VLOOKUP($B71,ARTICLE!$B$2:$J$200,6,FALSE)),"") | G71: =IFERROR(IF(ISBLANK(VLOOKUP($B71,ARTICLE!$B$2:$J$200,7,FALSE)),"",VLOOKUP($B71,ARTICLE!$B$2:$J$200,7,FALSE)),"") | H71: =IFERROR(IF(ISBLANK(VLOOKUP($B71,ARTICLE!$B$2:$J$200,8,FALSE)),"",VLOOKUP($B71,ARTICLE!$B$2:$J$200,8,FALSE)),"")
C72: =IFERROR(IF(ISBLANK(VLOOKUP($B72,ARTICLE!$B$2:$J$200,3,FALSE)),"",VLOOKUP($B72,ARTICLE!$B$2:$J$200,3,FALSE)),"") | D72: =IFERROR(IF(ISBLANK(VLOOKUP($B72,ARTICLE!$B$2:$J$200,4,FALSE)),"",VLOOKUP($B72,ARTICLE!$B$2:$J$200,4,FALSE)),"") | E72: =IFERROR(IF(ISBLANK(VLOOKUP($B72,ARTICLE!$B$2:$J$200,5,FALSE)),"",VLOOKUP($B72,ARTICLE!$B$2:$J$200,5,FALSE)),"") | F72: =IFERROR(IF(ISBLANK(VLOOKUP($B72,ARTICLE!$B$2:$J$200,6,FALSE)),"",VLOOKUP($B72,ARTICLE!$B$2:$J$200,6,FALSE)),"") | G72: =IFERROR(IF(ISBLANK(VLOOKUP($B72,ARTICLE!$B$2:$J$200,7,FALSE)),"",VLOOKUP($B72,ARTICLE!$B$2:$J$200,7,FALSE)),"") | H72: =IFERROR(IF(ISBLANK(VLOOKUP($B72,ARTICLE!$B$2:$J$200,8,FALSE)),"",VLOOKUP($B72,ARTICLE!$B$2:$J$200,8,FALSE)),"")
C73: =IFERROR(IF(ISBLANK(VLOOKUP($B73,ARTICLE!$B$2:$J$200,3,FALSE)),"",VLOOKUP($B73,ARTICLE!$B$2:$J$200,3,FALSE)),"") | D73: =IFERROR(IF(ISBLANK(VLOOKUP($B73,ARTICLE!$B$2:$J$200,4,FALSE)),"",VLOOKUP($B73,ARTICLE!$B$2:$J$200,4,FALSE)),"") | E73: =IFERROR(IF(ISBLANK(VLOOKUP($B73,ARTICLE!$B$2:$J$200,5,FALSE)),"",VLOOKUP($B73,ARTICLE!$B$2:$J$200,5,FALSE)),"") | F73: =IFERROR(IF(ISBLANK(VLOOKUP($B73,ARTICLE!$B$2:$J$200,6,FALSE)),"",VLOOKUP($B73,ARTICLE!$B$2:$J$200,6,FALSE)),"") | G73: =IFERROR(IF(ISBLANK(VLOOKUP($B73,ARTICLE!$B$2:$J$200,7,FALSE)),"",VLOOKUP($B73,ARTICLE!$B$2:$J$200,7,FALSE)),"") | H73: =IFERROR(IF(ISBLANK(VLOOKUP($B73,ARTICLE!$B$2:$J$200,8,FALSE)),"",VLOOKUP($B73,ARTICLE!$B$2:$J$200,8,FALSE)),"")
C74: =IFERROR(IF(ISBLANK(VLOOKUP($B74,ARTICLE!$B$2:$J$200,3,FALSE)),"",VLOOKUP($B74,ARTICLE!$B$2:$J$200,3,FALSE)),"") | D74: =IFERROR(IF(ISBLANK(VLOOKUP($B74,ARTICLE!$B$2:$J$200,4,FALSE)),"",VLOOKUP($B74,ARTICLE!$B$2:$J$200,4,FALSE)),"") | E74: =IFERROR(IF(ISBLANK(VLOOKUP($B74,ARTICLE!$B$2:$J$200,5,FALSE)),"",VLOOKUP($B74,ARTICLE!$B$2:$J$200,5,FALSE)),"") | F74: =IFERROR(IF(ISBLANK(VLOOKUP($B74,ARTICLE!$B$2:$J$200,6,FALSE)),"",VLOOKUP($B74,ARTICLE!$B$2:$J$200,6,FALSE)),"") | G74: =IFERROR(IF(ISBLANK(VLOOKUP($B74,ARTICLE!$B$2:$J$200,7,FALSE)),"",VLOOKUP($B74,ARTICLE!$B$2:$J$200,7,FALSE)),"") | H74: =IFERROR(IF(ISBLANK(VLOOKUP($B74,ARTICLE!$B$2:$J$200,8,FALSE)),"",VLOOKUP($B74,ARTICLE!$B$2:$J$200,8,FALSE)),"")
C75: =IFERROR(IF(ISBLANK(VLOOKUP($B75,ARTICLE!$B$2:$J$200,3,FALSE)),"",VLOOKUP($B75,ARTICLE!$B$2:$J$200,3,FALSE)),"") | D75: =IFERROR(IF(ISBLANK(VLOOKUP($B75,ARTICLE!$B$2:$J$200,4,FALSE)),"",VLOOKUP($B75,ARTICLE!$B$2:$J$200,4,FALSE)),"") | E75: =IFERROR(IF(ISBLANK(VLOOKUP($B75,ARTICLE!$B$2:$J$200,5,FALSE)),"",VLOOKUP($B75,ARTICLE!$B$2:$J$200,5,FALSE)),"") | F75: =IFERROR(IF(ISBLANK(VLOOKUP($B75,ARTICLE!$B$2:$J$200,6,FALSE)),"",VLOOKUP($B75,ARTICLE!$B$2:$J$200,6,FALSE)),"") | G75: =IFERROR(IF(ISBLANK(VLOOKUP($B75,ARTICLE!$B$2:$J$200,7,FALSE)),"",VLOOKUP($B75,ARTICLE!$B$2:$J$200,7,FALSE)),"") | H75: =IFERROR(IF(ISBLANK(VLOOKUP($B75,ARTICLE!$B$2:$J$200,8,FALSE)),"",VLOOKUP($B75,ARTICLE!$B$2:$J$200,8,FALSE)),"")
C76: =IFERROR(IF(ISBLANK(VLOOKUP($B76,ARTICLE!$B$2:$J$200,3,FALSE)),"",VLOOKUP($B76,ARTICLE!$B$2:$J$200,3,FALSE)),"") | D76: =IFERROR(IF(ISBLANK(VLOOKUP($B76,ARTICLE!$B$2:$J$200,4,FALSE)),"",VLOOKUP($B76,ARTICLE!$B$2:$J$200,4,FALSE)),"") | E76: =IFERROR(IF(ISBLANK(VLOOKUP($B76,ARTICLE!$B$2:$J$200,5,FALSE)),"",VLOOKUP($B76,ARTICLE!$B$2:$J$200,5,FALSE)),"") | F76: =IFERROR(IF(ISBLANK(VLOOKUP($B76,ARTICLE!$B$2:$J$200,6,FALSE)),"",VLOOKUP($B76,ARTICLE!$B$2:$J$200,6,FALSE)),"") | G76: =IFERROR(IF(ISBLANK(VLOOKUP($B76,ARTICLE!$B$2:$J$200,7,FALSE)),"",VLOOKUP($B76,ARTICLE!$B$2:$J$200,7,FALSE)),"") | H76: =IFERROR(IF(ISBLANK(VLOOKUP($B76,ARTICLE!$B$2:$J$200,8,FALSE)),"",VLOOKUP($B76,ARTICLE!$B$2:$J$200,8,FALSE)),"")
C77: =IFERROR(IF(ISBLANK(VLOOKUP($B77,ARTICLE!$B$2:$J$200,3,FALSE)),"",VLOOKUP($B77,ARTICLE!$B$2:$J$200,3,FALSE)),"") | D77: =IFERROR(IF(ISBLANK(VLOOKUP($B77,ARTICLE!$B$2:$J$200,4,FALSE)),"",VLOOKUP($B77,ARTICLE!$B$2:$J$200,4,FALSE)),"") | E77: =IFERROR(IF(ISBLANK(VLOOKUP($B77,ARTICLE!$B$2:$J$200,5,FALSE)),"",VLOOKUP($B77,ARTICLE!$B$2:$J$200,5,FALSE)),"") | F77: =IFERROR(IF(ISBLANK(VLOOKUP($B77,ARTICLE!$B$2:$J$200,6,FALSE)),"",VLOOKUP($B77,ARTICLE!$B$2:$J$200,6,FALSE)),"") | G77: =IFERROR(IF(ISBLANK(VLOOKUP($B77,ARTICLE!$B$2:$J$200,7,FALSE)),"",VLOOKUP($B77,ARTICLE!$B$2:$J$200,7,FALSE)),"") | H77: =IFERROR(IF(ISBLANK(VLOOKUP($B77,ARTICLE!$B$2:$J$200,8,FALSE)),"",VLOOKUP($B77,ARTICLE!$B$2:$J$200,8,FALSE)),"")
C78: =IFERROR(IF(ISBLANK(VLOOKUP($B78,ARTICLE!$B$2:$J$200,3,FALSE)),"",VLOOKUP($B78,ARTICLE!$B$2:$J$200,3,FALSE)),"") | D78: =IFERROR(IF(ISBLANK(VLOOKUP($B78,ARTICLE!$B$2:$J$200,4,FALSE)),"",VLOOKUP($B78,ARTICLE!$B$2:$J$200,4,FALSE)),"") | E78: =IFERROR(IF(ISBLANK(VLOOKUP($B78,ARTICLE!$B$2:$J$200,5,FALSE)),"",VLOOKUP($B78,ARTICLE!$B$2:$J$200,5,FALSE)),"") | F78: =IFERROR(IF(ISBLANK(VLOOKUP($B78,ARTICLE!$B$2:$J$200,6,FALSE)),"",VLOOKUP($B78,ARTICLE!$B$2:$J$200,6,FALSE)),"") | G78: =IFERROR(IF(ISBLANK(VLOOKUP($B78,ARTICLE!$B$2:$J$200,7,FALSE)),"",VLOOKUP($B78,ARTICLE!$B$2:$J$200,7,FALSE)),"") | H78: =IFERROR(IF(ISBLANK(VLOOKUP($B78,ARTICLE!$B$2:$J$200,8,FALSE)),"",VLOOKUP($B78,ARTICLE!$B$2:$J$200,8,FALSE)),"")
A79: =B79 | B79: =CONCATENATE(B80,IF(B81="",""," / "),B81,IF(B82="",""," / "),B82,IF(B83="",""," / "),B83,IF(B84="",""," / "),B84,IF(B85="",""," / "),B85,IF(B86="",""," / "),B86,B86,IF(B87="",""," / "),B87) | C79: =C80 | D79: =IF(SUM(E79:H79)=0,0,SUM(E79:H79)) -> 0 | E79: =SUM(E80:E89) -> 0 | F79: =SUM(F80:F89) -> 0 | G79: =SUM(G80:G89) -> 0 | H79: =SUM(H80:H89) -> 0 | K79: =ROUNDUP(D79,0)*J79 -> 0 | L79: =ROUNDUP(J79*E79,0) -> 0 | M79: =L79/K79 -> #DIV/0! | N79: =ROUNDUP(J79*F79,0) -> 0 | O79: =N79/K79 -> #DIV/0! | P79: =ROUNDUP(J79*G79,0) -> 0 | Q79: =P79/K79 -> #DIV/0! | R79: =ROUNDUP(J79*H79,0) -> 0 | S79: =R79/K79 -> #DIV/0!
C80: =IFERROR(IF(ISBLANK(VLOOKUP($B80,ARTICLE!$B$2:$J$200,3,FALSE)),"",VLOOKUP($B80,ARTICLE!$B$2:$J$200,3,FALSE)),"") | D80: =IFERROR(IF(ISBLANK(VLOOKUP($B80,ARTICLE!$B$2:$J$200,4,FALSE)),"",VLOOKUP($B80,ARTICLE!$B$2:$J$200,4,FALSE)),"") | E80: =IFERROR(IF(ISBLANK(VLOOKUP($B80,ARTICLE!$B$2:$J$200,5,FALSE)),"",VLOOKUP($B80,ARTICLE!$B$2:$J$200,5,FALSE)),"") | F80: =IFERROR(IF(ISBLANK(VLOOKUP($B80,ARTICLE!$B$2:$J$200,6,FALSE)),"",VLOOKUP($B80,ARTICLE!$B$2:$J$200,6,FALSE)),"") | G80: =IFERROR(IF(ISBLANK(VLOOKUP($B80,ARTICLE!$B$2:$J$200,7,FALSE)),"",VLOOKUP($B80,ARTICLE!$B$2:$J$200,7,FALSE)),"") | H80: =IFERROR(IF(ISBLANK(VLOOKUP($B80,ARTICLE!$B$2:$J$200,8,FALSE)),"",VLOOKUP($B80,ARTICLE!$B$2:$J$200,8,FALSE)),"")
C81: =IFERROR(IF(ISBLANK(VLOOKUP($B81,ARTICLE!$B$2:$J$200,3,FALSE)),"",VLOOKUP($B81,ARTICLE!$B$2:$J$200,3,FALSE)),"") | D81: =IFERROR(IF(ISBLANK(VLOOKUP($B81,ARTICLE!$B$2:$J$200,4,FALSE)),"",VLOOKUP($B81,ARTICLE!$B$2:$J$200,4,FALSE)),"") | E81: =IFERROR(IF(ISBLANK(VLOOKUP($B81,ARTICLE!$B$2:$J$200,5,FALSE)),"",VLOOKUP($B81,ARTICLE!$B$2:$J$200,5,FALSE)),"") | F81: =IFERROR(IF(ISBLANK(VLOOKUP($B81,ARTICLE!$B$2:$J$200,6,FALSE)),"",VLOOKUP($B81,ARTICLE!$B$2:$J$200,6,FALSE)),"") | G81: =IFERROR(IF(ISBLANK(VLOOKUP($B81,ARTICLE!$B$2:$J$200,7,FALSE)),"",VLOOKUP($B81,ARTICLE!$B$2:$J$200,7,FALSE)),"") | H81: =IFERROR(IF(ISBLANK(VLOOKUP($B81,ARTICLE!$B$2:$J$200,8,FALSE)),"",VLOOKUP($B81,ARTICLE!$B$2:$J$200,8,FALSE)),"")
C82: =IFERROR(IF(ISBLANK(VLOOKUP($B82,ARTICLE!$B$2:$J$200,3,FALSE)),"",VLOOKUP($B82,ARTICLE!$B$2:$J$200,3,FALSE)),"") | D82: =IFERROR(IF(ISBLANK(VLOOKUP($B82,ARTICLE!$B$2:$J$200,4,FALSE)),"",VLOOKUP($B82,ARTICLE!$B$2:$J$200,4,FALSE)),"") | E82: =IFERROR(IF(ISBLANK(VLOOKUP($B82,ARTICLE!$B$2:$J$200,5,FALSE)),"",VLOOKUP($B82,ARTICLE!$B$2:$J$200,5,FALSE)),"") | F82: =IFERROR(IF(ISBLANK(VLOOKUP($B82,ARTICLE!$B$2:$J$200,6,FALSE)),"",VLOOKUP($B82,ARTICLE!$B$2:$J$200,6,FALSE)),"") | G82: =IFERROR(IF(ISBLANK(VLOOKUP($B82,ARTICLE!$B$2:$J$200,7,FALSE)),"",VLOOKUP($B82,ARTICLE!$B$2:$J$200,7,FALSE)),"") | H82: =IFERROR(IF(ISBLANK(VLOOKUP($B82,ARTICLE!$B$2:$J$200,8,FALSE)),"",VLOOKUP($B82,ARTICLE!$B$2:$J$200,8,FALSE)),"")
C83: =IFERROR(IF(ISBLANK(VLOOKUP($B83,ARTICLE!$B$2:$J$200,3,FALSE)),"",VLOOKUP($B83,ARTICLE!$B$2:$J$200,3,FALSE)),"") | D83: =IFERROR(IF(ISBLANK(VLOOKUP($B83,ARTICLE!$B$2:$J$200,4,FALSE)),"",VLOOKUP($B83,ARTICLE!$B$2:$J$200,4,FALSE)),"") | E83: =IFERROR(IF(ISBLANK(VLOOKUP($B83,ARTICLE!$B$2:$J$200,5,FALSE)),"",VLOOKUP($B83,ARTICLE!$B$2:$J$200,5,FALSE)),"") | F83: =IFERROR(IF(ISBLANK(VLOOKUP($B83,ARTICLE!$B$2:$J$200,6,FALSE)),"",VLOOKUP($B83,ARTICLE!$B$2:$J$200,6,FALSE)),"") | G83: =IFERROR(IF(ISBLANK(VLOOKUP($B83,ARTICLE!$B$2:$J$200,7,FALSE)),"",VLOOKUP($B83,ARTICLE!$B$2:$J$200,7,FALSE)),"") | H83: =IFERROR(IF(ISBLANK(VLOOKUP($B83,ARTICLE!$B$2:$J$200,8,FALSE)),"",VLOOKUP($B83,ARTICLE!$B$2:$J$200,8,FALSE)),"")
C84: =IFERROR(IF(ISBLANK(VLOOKUP($B84,ARTICLE!$B$2:$J$200,3,FALSE)),"",VLOOKUP($B84,ARTICLE!$B$2:$J$200,3,FALSE)),"") | D84: =IFERROR(IF(ISBLANK(VLOOKUP($B84,ARTICLE!$B$2:$J$200,4,FALSE)),"",VLOOKUP($B84,ARTICLE!$B$2:$J$200,4,FALSE)),"") | E84: =IFERROR(IF(ISBLANK(VLOOKUP($B84,ARTICLE!$B$2:$J$200,5,FALSE)),"",VLOOKUP($B84,ARTICLE!$B$2:$J$200,5,FALSE)),"") | F84: =IFERROR(IF(ISBLANK(VLOOKUP($B84,ARTICLE!$B$2:$J$200,6,FALSE)),"",VLOOKUP($B84,ARTICLE!$B$2:$J$200,6,FALSE)),"") | G84: =IFERROR(IF(ISBLANK(VLOOKUP($B84,ARTICLE!$B$2:$J$200,7,FALSE)),"",VLOOKUP($B84,ARTICLE!$B$2:$J$200,7,FALSE)),"") | H84: =IFERROR(IF(ISBLANK(VLOOKUP($B84,ARTICLE!$B$2:$J$200,8,FALSE)),"",VLOOKUP($B84,ARTICLE!$B$2:$J$200,8,FALSE)),"")
C85: =IFERROR(IF(ISBLANK(VLOOKUP($B85,ARTICLE!$B$2:$J$200,3,FALSE)),"",VLOOKUP($B85,ARTICLE!$B$2:$J$200,3,FALSE)),"") | D85: =IFERROR(IF(ISBLANK(VLOOKUP($B85,ARTICLE!$B$2:$J$200,4,FALSE)),"",VLOOKUP($B85,ARTICLE!$B$2:$J$200,4,FALSE)),"") | E85: =IFERROR(IF(ISBLANK(VLOOKUP($B85,ARTICLE!$B$2:$J$200,5,FALSE)),"",VLOOKUP($B85,ARTICLE!$B$2:$J$200,5,FALSE)),"") | F85: =IFERROR(IF(ISBLANK(VLOOKUP($B85,ARTICLE!$B$2:$J$200,6,FALSE)),"",VLOOKUP($B85,ARTICLE!$B$2:$J$200,6,FALSE)),"") | G85: =IFERROR(IF(ISBLANK(VLOOKUP($B85,ARTICLE!$B$2:$J$200,7,FALSE)),"",VLOOKUP($B85,ARTICLE!$B$2:$J$200,7,FALSE)),"") | H85: =IFERROR(IF(ISBLANK(VLOOKUP($B85,ARTICLE!$B$2:$J$200,8,FALSE)),"",VLOOKUP($B85,ARTICLE!$B$2:$J$200,8,FALSE)),"")
C86: =IFERROR(IF(ISBLANK(VLOOKUP($B86,ARTICLE!$B$2:$J$200,3,FALSE)),"",VLOOKUP($B86,ARTICLE!$B$2:$J$200,3,FALSE)),"") | D86: =IFERROR(IF(ISBLANK(VLOOKUP($B86,ARTICLE!$B$2:$J$200,4,FALSE)),"",VLOOKUP($B86,ARTICLE!$B$2:$J$200,4,FALSE)),"") | E86: =IFERROR(IF(ISBLANK(VLOOKUP($B86,ARTICLE!$B$2:$J$200,5,FALSE)),"",VLOOKUP($B86,ARTICLE!$B$2:$J$200,5,FALSE)),"") | F86: =IFERROR(IF(ISBLANK(VLOOKUP($B86,ARTICLE!$B$2:$J$200,6,FALSE)),"",VLOOKUP($B86,ARTICLE!$B$2:$J$200,6,FALSE)),"") | G86: =IFERROR(IF(ISBLANK(VLOOKUP($B86,ARTICLE!$B$2:$J$200,7,FALSE)),"",VLOOKUP($B86,ARTICLE!$B$2:$J$200,7,FALSE)),"") | H86: =IFERROR(IF(ISBLANK(VLOOKUP($B86,ARTICLE!$B$2:$J$200,8,FALSE)),"",VLOOKUP($B86,ARTICLE!$B$2:$J$200,8,FALSE)),"")
C87: =IFERROR(IF(ISBLANK(VLOOKUP($B87,ARTICLE!$B$2:$J$200,3,FALSE)),"",VLOOKUP($B87,ARTICLE!$B$2:$J$200,3,FALSE)),"") | D87: =IFERROR(IF(ISBLANK(VLOOKUP($B87,ARTICLE!$B$2:$J$200,4,FALSE)),"",VLOOKUP($B87,ARTICLE!$B$2:$J$200,4,FALSE)),"") | E87: =IFERROR(IF(ISBLANK(VLOOKUP($B87,ARTICLE!$B$2:$J$200,5,FALSE)),"",VLOOKUP($B87,ARTICLE!$B$2:$J$200,5,FALSE)),"") | F87: =IFERROR(IF(ISBLANK(VLOOKUP($B87,ARTICLE!$B$2:$J$200,6,FALSE)),"",VLOOKUP($B87,ARTICLE!$B$2:$J$200,6,FALSE)),"") | G87: =IFERROR(IF(ISBLANK(VLOOKUP($B87,ARTICLE!$B$2:$J$200,7,FALSE)),"",VLOOKUP($B87,ARTICLE!$B$2:$J$200,7,FALSE)),"") | H87: =IFERROR(IF(ISBLANK(VLOOKUP($B87,ARTICLE!$B$2:$J$200,8,FALSE)),"",VLOOKUP($B87,ARTICLE!$B$2:$J$200,8,FALSE)),"")
C88: =IFERROR(IF(ISBLANK(VLOOKUP($B88,ARTICLE!$B$2:$J$200,3,FALSE)),"",VLOOKUP($B88,ARTICLE!$B$2:$J$200,3,FALSE)),"") | D88: =IFERROR(IF(ISBLANK(VLOOKUP($B88,ARTICLE!$B$2:$J$200,4,FALSE)),"",VLOOKUP($B88,ARTICLE!$B$2:$J$200,4,FALSE)),"") | E88: =IFERROR(IF(ISBLANK(VLOOKUP($B88,ARTICLE!$B$2:$J$200,5,FALSE)),"",VLOOKUP($B88,ARTICLE!$B$2:$J$200,5,FALSE)),"") | F88: =IFERROR(IF(ISBLANK(VLOOKUP($B88,ARTICLE!$B$2:$J$200,6,FALSE)),"",VLOOKUP($B88,ARTICLE!$B$2:$J$200,6,FALSE)),"") | G88: =IFERROR(IF(ISBLANK(VLOOKUP($B88,ARTICLE!$B$2:$J$200,7,FALSE)),"",VLOOKUP($B88,ARTICLE!$B$2:$J$200,7,FALSE)),"") | H88: =IFERROR(IF(ISBLANK(VLOOKUP($B88,ARTICLE!$B$2:$J$200,8,FALSE)),"",VLOOKUP($B88,ARTICLE!$B$2:$J$200,8,FALSE)),"")
C89: =IFERROR(IF(ISBLANK(VLOOKUP($B89,ARTICLE!$B$2:$J$200,3,FALSE)),"",VLOOKUP($B89,ARTICLE!$B$2:$J$200,3,FALSE)),"") | D89: =IFERROR(IF(ISBLANK(VLOOKUP($B89,ARTICLE!$B$2:$J$200,4,FALSE)),"",VLOOKUP($B89,ARTICLE!$B$2:$J$200,4,FALSE)),"") | E89: =IFERROR(IF(ISBLANK(VLOOKUP($B89,ARTICLE!$B$2:$J$200,5,FALSE)),"",VLOOKUP($B89,ARTICLE!$B$2:$J$200,5,FALSE)),"") | F89: =IFERROR(IF(ISBLANK(VLOOKUP($B89,ARTICLE!$B$2:$J$200,6,FALSE)),"",VLOOKUP($B89,ARTICLE!$B$2:$J$200,6,FALSE)),"") | G89: =IFERROR(IF(ISBLANK(VLOOKUP($B89,ARTICLE!$B$2:$J$200,7,FALSE)),"",VLOOKUP($B89,ARTICLE!$B$2:$J$200,7,FALSE)),"") | H89: =IFERROR(IF(ISBLANK(VLOOKUP($B89,ARTICLE!$B$2:$J$200,8,FALSE)),"",VLOOKUP($B89,ARTICLE!$B$2:$J$200,8,FALSE)),"")
A90: =B90 | B90: =CONCATENATE(B91,IF(B92="",""," / "),B92,IF(B93="",""," / "),B93,IF(B94="",""," / "),B94,IF(B95="",""," / "),B95,IF(B96="",""," / "),B96,IF(B97="",""," / "),B97,B97,IF(B98="",""," / "),B98) | C90: =C91 | D90: =IF(SUM(E90:H90)=0,0,SUM(E90:H90)) -> 0 | E90: =SUM(E91:E100) -> 0 | F90: =SUM(F91:F100) -> 0 | G90: =SUM(G91:G100) -> 0 | H90: =SUM(H91:H100) -> 0 | K90: =ROUNDUP(D90,0)*J90 -> 0 | L90: =ROUNDUP(J90*E90,0) -> 0 | M90: =L90/K90 -> #DIV/0! | N90: =ROUNDUP(J90*F90,0) -> 0 | O90: =N90/K90 -> #DIV/0! | P90: =ROUNDUP(J90*G90,0) -> 0 | Q90: =P90/K90 -> #DIV/0! | R90: =ROUNDUP(J90*H90,0) -> 0 | S90: =R90/K90 -> #DIV/0!
C91: =IFERROR(IF(ISBLANK(VLOOKUP($B91,ARTICLE!$B$2:$J$200,3,FALSE)),"",VLOOKUP($B91,ARTICLE!$B$2:$J$200,3,FALSE)),"") | D91: =IFERROR(IF(ISBLANK(VLOOKUP($B91,ARTICLE!$B$2:$J$200,4,FALSE)),"",VLOOKUP($B91,ARTICLE!$B$2:$J$200,4,FALSE)),"") | E91: =IFERROR(IF(ISBLANK(VLOOKUP($B91,ARTICLE!$B$2:$J$200,5,FALSE)),"",VLOOKUP($B91,ARTICLE!$B$2:$J$200,5,FALSE)),"") | F91: =IFERROR(IF(ISBLANK(VLOOKUP($B91,ARTICLE!$B$2:$J$200,6,FALSE)),"",VLOOKUP($B91,ARTICLE!$B$2:$J$200,6,FALSE)),"") | G91: =IFERROR(IF(ISBLANK(VLOOKUP($B91,ARTICLE!$B$2:$J$200,7,FALSE)),"",VLOOKUP($B91,ARTICLE!$B$2:$J$200,7,FALSE)),"") | H91: =IFERROR(IF(ISBLANK(VLOOKUP($B91,ARTICLE!$B$2:$J$200,8,FALSE)),"",VLOOKUP($B91,ARTICLE!$B$2:$J$200,8,FALSE)),"")
C92: =IFERROR(IF(ISBLANK(VLOOKUP($B92,ARTICLE!$B$2:$J$200,3,FALSE)),"",VLOOKUP($B92,ARTICLE!$B$2:$J$200,3,FALSE)),"") | D92: =IFERROR(IF(ISBLANK(VLOOKUP($B92,ARTICLE!$B$2:$J$200,4,FALSE)),"",VLOOKUP($B92,ARTICLE!$B$2:$J$200,4,FALSE)),"") | E92: =IFERROR(IF(ISBLANK(VLOOKUP($B92,ARTICLE!$B$2:$J$200,5,FALSE)),"",VLOOKUP($B92,ARTICLE!$B$2:$J$200,5,FALSE)),"") | F92: =IFERROR(IF(ISBLANK(VLOOKUP($B92,ARTICLE!$B$2:$J$200,6,FALSE)),"",VLOOKUP($B92,ARTICLE!$B$2:$J$200,6,FALSE)),"") | G92: =IFERROR(IF(ISBLANK(VLOOKUP($B92,ARTICLE!$B$2:$J$200,7,FALSE)),"",VLOOKUP($B92,ARTICLE!$B$2:$J$200,7,FALSE)),"") | H92: =IFERROR(IF(ISBLANK(VLOOKUP($B92,ARTICLE!$B$2:$J$200,8,FALSE)),"",VLOOKUP($B92,ARTICLE!$B$2:$J$200,8,FALSE)),"")
C93: =IFERROR(IF(ISBLANK(VLOOKUP($B93,ARTICLE!$B$2:$J$200,3,FALSE)),"",VLOOKUP($B93,ARTICLE!$B$2:$J$200,3,FALSE)),"") | D93: =IFERROR(IF(ISBLANK(VLOOKUP($B93,ARTICLE!$B$2:$J$200,4,FALSE)),"",VLOOKUP($B93,ARTICLE!$B$2:$J$200,4,FALSE)),"") | E93: =IFERROR(IF(ISBLANK(VLOOKUP($B93,ARTICLE!$B$2:$J$200,5,FALSE)),"",VLOOKUP($B93,ARTICLE!$B$2:$J$200,5,FALSE)),"") | F93: =IFERROR(IF(ISBLANK(VLOOKUP($B93,ARTICLE!$B$2:$J$200,6,FALSE)),"",VLOOKUP($B93,ARTICLE!$B$2:$J$200,6,FALSE)),"") | G93: =IFERROR(IF(ISBLANK(VLOOKUP($B93,ARTICLE!$B$2:$J$200,7,FALSE)),"",VLOOKUP($B93,ARTICLE!$B$2:$J$200,7,FALSE)),"") | H93: =IFERROR(IF(ISBLANK(VLOOKUP($B93,ARTICLE!$B$2:$J$200,8,FALSE)),"",VLOOKUP($B93,ARTICLE!$B$2:$J$200,8,FALSE)),"")
C94: =IFERROR(IF(ISBLANK(VLOOKUP($B94,ARTICLE!$B$2:$J$200,3,FALSE)),"",VLOOKUP($B94,ARTICLE!$B$2:$J$200,3,FALSE)),"") | D94: =IFERROR(IF(ISBLANK(VLOOKUP($B94,ARTICLE!$B$2:$J$200,4,FALSE)),"",VLOOKUP($B94,ARTICLE!$B$2:$J$200,4,FALSE)),"") | E94: =IFERROR(IF(ISBLANK(VLOOKUP($B94,ARTICLE!$B$2:$J$200,5,FALSE)),"",VLOOKUP($B94,ARTICLE!$B$2:$J$200,5,FALSE)),"") | F94: =IFERROR(IF(ISBLANK(VLOOKUP($B94,ARTICLE!$B$2:$J$200,6,FALSE)),"",VLOOKUP($B94,ARTICLE!$B$2:$J$200,6,FALSE)),"") | G94: =IFERROR(IF(ISBLANK(VLOOKUP($B94,ARTICLE!$B$2:$J$200,7,FALSE)),"",VLOOKUP($B94,ARTICLE!$B$2:$J$200,7,FALSE)),"") | H94: =IFERROR(IF(ISBLANK(VLOOKUP($B94,ARTICLE!$B$2:$J$200,8,FALSE)),"",VLOOKUP($B94,ARTICLE!$B$2:$J$200,8,FALSE)),"")
C95: =IFERROR(IF(ISBLANK(VLOOKUP($B95,ARTICLE!$B$2:$J$200,3,FALSE)),"",VLOOKUP($B95,ARTICLE!$B$2:$J$200,3,FALSE)),"") | D95: =IFERROR(IF(ISBLANK(VLOOKUP($B95,ARTICLE!$B$2:$J$200,4,FALSE)),"",VLOOKUP($B95,ARTICLE!$B$2:$J$200,4,FALSE)),"") | E95: =IFERROR(IF(ISBLANK(VLOOKUP($B95,ARTICLE!$B$2:$J$200,5,FALSE)),"",VLOOKUP($B95,ARTICLE!$B$2:$J$200,5,FALSE)),"") | F95: =IFERROR(IF(ISBLANK(VLOOKUP($B95,ARTICLE!$B$2:$J$200,6,FALSE)),"",VLOOKUP($B95,ARTICLE!$B$2:$J$200,6,FALSE)),"") | G95: =IFERROR(IF(ISBLANK(VLOOKUP($B95,ARTICLE!$B$2:$J$200,7,FALSE)),"",VLOOKUP($B95,ARTICLE!$B$2:$J$200,7,FALSE)),"") | H95: =IFERROR(IF(ISBLANK(VLOOKUP($B95,ARTICLE!$B$2:$J$200,8,FALSE)),"",VLOOKUP($B95,ARTICLE!$B$2:$J$200,8,FALSE)),"")
C96: =IFERROR(IF(ISBLANK(VLOOKUP($B96,ARTICLE!$B$2:$J$200,3,FALSE)),"",VLOOKUP($B96,ARTICLE!$B$2:$J$200,3,FALSE)),"") | D96: =IFERROR(IF(ISBLANK(VLOOKUP($B96,ARTICLE!$B$2:$J$200,4,FALSE)),"",VLOOKUP($B96,ARTICLE!$B$2:$J$200,4,FALSE)),"") | E96: =IFERROR(IF(ISBLANK(VLOOKUP($B96,ARTICLE!$B$2:$J$200,5,FALSE)),"",VLOOKUP($B96,ARTICLE!$B$2:$J$200,5,FALSE)),"") | F96: =IFERROR(IF(ISBLANK(VLOOKUP($B96,ARTICLE!$B$2:$J$200,6,FALSE)),"",VLOOKUP($B96,ARTICLE!$B$2:$J$200,6,FALSE)),"") | G96: =IFERROR(IF(ISBLANK(VLOOKUP($B96,ARTICLE!$B$2:$J$200,7,FALSE)),"",VLOOKUP($B96,ARTICLE!$B$2:$J$200,7,FALSE)),"") | H96: =IFERROR(IF(ISBLANK(VLOOKUP($B96,ARTICLE!$B$2:$J$200,8,FALSE)),"",VLOOKUP($B96,ARTICLE!$B$2:$J$200,8,FALSE)),"")
C97: =IFERROR(IF(ISBLANK(VLOOKUP($B97,ARTICLE!$B$2:$J$200,3,FALSE)),"",VLOOKUP($B97,ARTICLE!$B$2:$J$200,3,FALSE)),"") | D97: =IFERROR(IF(ISBLANK(VLOOKUP($B97,ARTICLE!$B$2:$J$200,4,FALSE)),"",VLOOKUP($B97,ARTICLE!$B$2:$J$200,4,FALSE)),"") | E97: =IFERROR(IF(ISBLANK(VLOOKUP($B97,ARTICLE!$B$2:$J$200,5,FALSE)),"",VLOOKUP($B97,ARTICLE!$B$2:$J$200,5,FALSE)),"") | F97: =IFERROR(IF(ISBLANK(VLOOKUP($B97,ARTICLE!$B$2:$J$200,6,FALSE)),"",VLOOKUP($B97,ARTICLE!$B$2:$J$200,6,FALSE)),"") | G97: =IFERROR(IF(ISBLANK(VLOOKUP($B97,ARTICLE!$B$2:$J$200,7,FALSE)),"",VLOOKUP($B97,ARTICLE!$B$2:$J$200,7,FALSE)),"") | H97: =IFERROR(IF(ISBLANK(VLOOKUP($B97,ARTICLE!$B$2:$J$200,8,FALSE)),"",VLOOKUP($B97,ARTICLE!$B$2:$J$200,8,FALSE)),"")
C98: =IFERROR(IF(ISBLANK(VLOOKUP($B98,ARTICLE!$B$2:$J$200,3,FALSE)),"",VLOOKUP($B98,ARTICLE!$B$2:$J$200,3,FALSE)),"") | D98: =IFERROR(IF(ISBLANK(VLOOKUP($B98,ARTICLE!$B$2:$J$200,4,FALSE)),"",VLOOKUP($B98,ARTICLE!$B$2:$J$200,4,FALSE)),"") | E98: =IFERROR(IF(ISBLANK(VLOOKUP($B98,ARTICLE!$B$2:$J$200,5,FALSE)),"",VLOOKUP($B98,ARTICLE!$B$2:$J$200,5,FALSE)),"") | F98: =IFERROR(IF(ISBLANK(VLOOKUP($B98,ARTICLE!$B$2:$J$200,6,FALSE)),"",VLOOKUP($B98,ARTICLE!$B$2:$J$200,6,FALSE)),"") | G98: =IFERROR(IF(ISBLANK(VLOOKUP($B98,ARTICLE!$B$2:$J$200,7,FALSE)),"",VLOOKUP($B98,ARTICLE!$B$2:$J$200,7,FALSE)),"") | H98: =IFERROR(IF(ISBLANK(VLOOKUP($B98,ARTICLE!$B$2:$J$200,8,FALSE)),"",VLOOKUP($B98,ARTICLE!$B$2:$J$200,8,FALSE)),"")
C99: =IFERROR(IF(ISBLANK(VLOOKUP($B99,ARTICLE!$B$2:$J$200,3,FALSE)),"",VLOOKUP($B99,ARTICLE!$B$2:$J$200,3,FALSE)),"") | D99: =IFERROR(IF(ISBLANK(VLOOKUP($B99,ARTICLE!$B$2:$J$200,4,FALSE)),"",VLOOKUP($B99,ARTICLE!$B$2:$J$200,4,FALSE)),"") | E99: =IFERROR(IF(ISBLANK(VLOOKUP($B99,ARTICLE!$B$2:$J$200,5,FALSE)),"",VLOOKUP($B99,ARTICLE!$B$2:$J$200,5,FALSE)),"") | F99: =IFERROR(IF(ISBLANK(VLOOKUP($B99,ARTICLE!$B$2:$J$200,6,FALSE)),"",VLOOKUP($B99,ARTICLE!$B$2:$J$200,6,FALSE)),"") | G99: =IFERROR(IF(ISBLANK(VLOOKUP($B99,ARTICLE!$B$2:$J$200,7,FALSE)),"",VLOOKUP($B99,ARTICLE!$B$2:$J$200,7,FALSE)),"") | H99: =IFERROR(IF(ISBLANK(VLOOKUP($B99,ARTICLE!$B$2:$J$200,8,FALSE)),"",VLOOKUP($B99,ARTICLE!$B$2:$J$200,8,FALSE)),"")
C100: =IFERROR(IF(ISBLANK(VLOOKUP($B100,ARTICLE!$B$2:$J$200,3,FALSE)),"",VLOOKUP($B100,ARTICLE!$B$2:$J$200,3,FALSE)),"") | D100: =IFERROR(IF(ISBLANK(VLOOKUP($B100,ARTICLE!$B$2:$J$200,4,FALSE)),"",VLOOKUP($B100,ARTICLE!$B$2:$J$200,4,FALSE)),"") | E100: =IFERROR(IF(ISBLANK(VLOOKUP($B100,ARTICLE!$B$2:$J$200,5,FALSE)),"",VLOOKUP($B100,ARTICLE!$B$2:$J$200,5,FALSE)),"") | F100: =IFERROR(IF(ISBLANK(VLOOKUP($B100,ARTICLE!$B$2:$J$200,6,FALSE)),"",VLOOKUP($B100,ARTICLE!$B$2:$J$200,6,FALSE)),"") | G100: =IFERROR(IF(ISBLANK(VLOOKUP($B100,ARTICLE!$B$2:$J$200,7,FALSE)),"",VLOOKUP($B100,ARTICLE!$B$2:$J$200,7,FALSE)),"") | H100: =IFERROR(IF(ISBLANK(VLOOKUP($B100,ARTICLE!$B$2:$J$200,8,FALSE)),"",VLOOKUP($B100,ARTICLE!$B$2:$J$200,8,FALSE)),"")
...

Sheet Matrice Combo - date
A1: BOTANICAL
A2: OSB 22 RL / Pare-vapeur Sd>28 / Structure PP 260-625 / Laine minérale 150 mm / Laine minérale 100 mm / OSB 8 / Pare-pluie support continu / Lattage 20x45mm | B2: m2 | C2: 118.25836 | D2: 68.138153 | E2: 14.56 | F2: 24.809446 | G2: 10.75076 | H2: PP RDC | I2: 271
A3: OSB 22 RL | B3: m2 | C3: 15.7729 | D3: 9.9 | E3: 1.13 | F3: 3.309 | G3: 1.4339
A4: Pare-vapeur Sd>28 | B4: m2 | C4: 4.719 | D4: 2.75 | E4: 0.55 | F4: 0.99 | G4: 0.429
A5: Structure PP 260-625 | B5: m2 | C5: 44.776729 | D5: 26.722398 | E5: 4.59 | F5: 9.3937194 | G5: 4.0706117
A6: Laine minérale 150 mm | B6: m2 | C6: 18.7902 | D6: 11.84 | E6: 1.3 | F6: 3.942 | G6: 1.7082
A7: Laine minérale 100 mm | B7: m2 | C7: 12.2122 | D7: 7.89 | E7: 0.65 | F7: 2.562 | G7: 1.1102
A8: OSB 8 | B8: m2 | C8: 6.435 | D8: 3.75 | E8: 0.75 | F8: 1.35 | G8: 0.585
A9: Pare-pluie support continu | B9: m2 | C9: 4.8763 | D9: 2.86 | E9: 0.55 | F9: 1.023 | G9: 0.4433
A10: Lattage 20x45mm | B10: m2 | C10: 10.676029 | D10: 2.4257547 | E10: 5.04 | F10: 2.2397264 | G10: 0.97054811
A12: OSB 22 RL / Pare-vapeur Sd>28 / Structure PP 260-625 / Laine minérale 150 mm / Laine minérale 100 mm / OSB 12
A13: OSB 22 RL | B13: m2 | C13: 106.49553 | D13: 65.502398 | E13: 8.97 | F13: 22.341719 | G13: 9.6814117 | H13: PP R+1 | I13: 153
A14: Pare-vapeur Sd>28 | B14: m2 | C14: 15.7729 | D14: 9.9 | E14: 1.13 | F14: 3.309 | G14: 1.4339
A15: Structure PP 260-625 | B15: m2 | C15: 4.719 | D15: 2.75 | E15: 0.55 | F15: 0.99 | G15: 0.429
A16: Laine minérale 150 mm | B16: m2 | C16: 44.776729 | D16: 26.722398 | E16: 4.59 | F16: 9.3937194 | G16: 4.0706117
A17: Laine minérale 100 mm | B17: m2 | C17: 18.7902 | D17: 11.84 | E17: 1.3 | F17: 3.942 | G17: 1.7082
A18: OSB 12 | B18: m2 | C18: 12.2122 | D18: 7.89 | E18: 0.65 | F18: 2.562 | G18: 1.1102
B19: m2 | C19: 10.2245 | D19: 6.4 | E19: 0.75 | F19: 2.145 | G19: 0.9295
A20: OSB 15 / Structure PA 260-625 / Laine minérale 100 mm / Pare-vapeur Sd>28 / OSB 12
A21: OSB 15 | B21: m2 | C21: 86.332529 | D21: 52.082398 | E21: 8.29 | F21: 18.111719 | G21: 7.8484117 | H21: PP ACOPERIS | I21: 211
A22: Structure PA 260-625 | B22: m2 | C22: 12.9701 | D22: 8.32 | E22: 0.75 | F22: 2.721 | G22: 1.1791
A23: Laine minérale 100 mm | B23: m2 | C23: 46.206729 | D23: 26.722398 | E23: 5.59 | F23: 9.6937194 | G23: 4.2006117
A24: Pare-vapeur Sd>28 | B24: m2 | C24: 12.2122 | D24: 7.89 | E24: 0.65 | F24: 2.562 | G24: 1.1102
A25: OSB 12 | B25: m2 | C25: 4.719 | D25: 2.75 | E25: 0.55 | F25: 0.99 | G25: 0.429
A27: OSB 22 / Structure PA 260-416
A28: OSB 22 | B28: m2 | C28: 70.627437 | D28: 41.229816 | E28: 8.16 | F28: 14.816945 | G28: 6.4206761 | H28: PP ACOPERIS VIDERE | I28: 32
A29: Structure PA 260-416 | B29: m2 | C29: 14.1856 | D29: 9.17 | E29: 0.75 | F29: 2.976 | G29: 1.2896
B30: m2 | C30: 56.441837 | D30: 32.059816 | E30: 7.41 | F30: 11.840945 | G30: 5.1310761
A31: ETAULIERS - 23,01,2023
A32: Pare-vapeur SD 90 / Structure 150 mm / Laine minérale 150 mm / OSB 12 / Pare-pluie sur OSB Sd<1,5 m / Lattage 20x45mm | B32: m2 | C32: 89.141901 | D32: 51.096993 | E32: 11.24 | F32: 18.701098 | G32: 8.1038091 | H32: PE-15 | I32: 97
A33: Pare-vapeur SD 90 | B33: m2 | C33: 3.4034 | D33: 1.83 | E33: 0.55 | F33: 0.714 | G33: 0.3094
A34: Structure 150 mm | B34: m2 | C34: 41.171471 | D34: 25.741239 | E34: 3.05 | F34: 8.6373716 | G34: 3.742861
A35: Laine minérale 150 mm | B35: m2 | C35: 18.7902 | D35: 11.84 | E35: 1.3 | F35: 3.942 | G35: 1.7082
A36: OSB 12 | B36: m2 | C36: 10.2245 | D36: 6.4 | E36: 0.75 | F36: 2.145 | G36: 0.9295
A37: Pare-pluie sur OSB Sd<1,5 m | B37: m2 | C37: 4.8763 | D37: 2.86 | E37: 0.55 | F37: 1.023 | G37: 0.4433
A38: Lattage 20x45mm | B38: m2 | C38: 10.676029 | D38: 2.4257547 | E38: 5.04 | F38: 2.2397264 | G38: 0.97054811
A43: Pare-vapeur SD 90 / Structure 150 mm / OSB 12 / Pare-pluie sur OSB Sd<1,5 m / Lattage 20x45mm | B43: m2 | C43: 84.422041 | D43: 39.256993 | E43: 9.94 | F43: 14.759098 | G43: 6.3956091 | H43: PEST-15 | I43: 41
A44: Pare-vapeur SD 90 | B44: m2 | C44: 3.4034 | D44: 1.83 | E44: 0.55 | F44: 0.714 | G44: 0.3094
A45: Structure 150 mm | B45: m2 | C45: 41.171471 | D45: 25.741239 | E45: 3.05 | F45: 8.6373716 | G45: 3.742861
A46: OSB 12 | B46: m2 | C46: 10.2245 | D46: 6.4 | E46: 0.75 | F46: 2.145 | G46: 0.9295
A47: Pare-pluie sur OSB Sd<1,5 m | B47: m2 | C47: 4.8763 | D47: 2.86 | E47: 0.55 | F47: 1.023 | G47: 0.4433
A48: Lattage 20x45mm | B48: m2 | C48: 10.676029 | D48: 2.4257547 | E48: 5.04 | F48: 2.2397264 | G48: 0.97054811
A54: Structure 100 mm / OSB 12 | B54: m2 | C54: 38.013741 | D54: 22.973036 | E54: 3.61 | F54: 7.9749108 | G54: 3.4557947 | H54: PIST-10 | I54: 11
A55: Structure 100 mm | B55: m2 | C55: 27.789241 | D55: 16.573036 | E55: 2.86 | F55: 5.8299108 | G55: 2.5262947
A56: OSB 12 | B56: m2 | C56: 10.2245 | D56: 6.4 | E56: 0.75 | F56: 2.145 | G56: 0.9295
A65: Structure PA 260-416 / OSB 22 | B65: m2 | C65: 70.627437 | D65: 41.229816 | E65: 8.16 | F65: 14.816945 | G65: 6.4206761 | H65: PP-250-416 | I65: 0
A66: Structure PA 260-416 | B66: m2 | C66: 56.441837 | D66: 32.059816 | E66: 7.41 | F66: 11.840945 | G66: 5.1310761
A67: OSB 22 | B67: m2 | C67: 14.1856 | D67: 9.17 | E67: 0.75 | F67: 2.976 | G67: 1.2896
A76: OSB 12 | B76: m2 | C76: 18.7902 | D76: 11.84 | E76: 1.3 | F76: 3.942 | G76: 1.7082
A77: Pare-pluie sur OSB Sd<1,5 m | B77: m2 | C77: 10.2245 | D77: 6.4 | E77: 0.75 | F77: 2.145 | G77: 0.9295
A78: Lattage vertical 30x45mm | B78: m2 | C78: 4.8763 | D78: 2.86 | E78: 0.55 | F78: 1.023 | G78: 0.4433
B79: m2 | C79: 10.29537 | D79: 2.1595598 | E79: 5.04 | F79: 2.1598679 | G79: 0.93594277
A82: OSB 8 / Pare-vapeur SD 90 / Structure 150 mm / Laine minérale 150 mm / OSB 12 / Bache de protection provisoire
A83: OSB 8 | B83: m2 | C83: 81.197171 | D83: 49.831239 | E83: 6.95 | F83: 17.034372 | G83: 7.381561 | H83: AE-15-POLYSTYREN | I83: 60
A84: Pare-vapeur SD 90 | B84: m2 | C84: 6.435 | D84: 3.75 | E84: 0.75 | F84: 1.35 | G84: 0.585
A85: Structure 150 mm | B85: m2 | C85: 3.4034 | D85: 1.83 | E85: 0.55 | F85: 0.714 | G85: 0.3094
A86: Laine minérale 150 mm | B86: m2 | C86: 41.171471 | D86: 25.741239 | E86: 3.05 | F86: 8.6373716 | G86: 3.742861
A87: OSB 12 | B87: m2 | C87: 18.7902 | D87: 11.84 | E87: 1.3 | F87: 3.942 | G87: 1.7082
A88: Bache de protection provisoire | B88: m2 | C88: 10.2245 | D88: 6.4 | E88: 0.75 | F88: 2.145 | G88: 0.9295
B89: m2 | C89: 1.1726 | D89: 0.27 | E89: 0.55 | F89: 0.246 | G89: 0.1066
A93: OSB 8 / Pare-vapeur Sd>28 / Structure 150 mm / OSB 12 / Pare-pluie sur OSB Sd<1,5 m / Lattage vertical 30x45mm
A94: OSB 8 | B94: m2 | C94: 77.721642 | D94: 43.660798 | E94: 10.69 | F94: 16.30524 | G94: 7.0656038 | H94: AE-15 TERRASA-BARDAGE | I94: 36
A95: Pare-vapeur Sd>28 | B95: m2 | C95: 6.435 | D95: 3.75 | E95: 0.75 | F95: 1.35 | G95: 0.585
A96: Structure 150 mm | B96: m2 | C96: 4.719 | D96: 2.75 | E96: 0.55 | F96: 0.99 | G96: 0.429
A97: OSB 12 | B97: m2 | C97: 41.171471 | D97: 25.741239 | E97: 3.05 | F97: 8.6373716 | G97: 3.742861
A98: Pare-pluie sur OSB Sd<1,5 m | B98: m2 | C98: 10.2245 | D98: 6.4 | E98: 0.75 | F98: 2.145 | G98: 0.9295
A99: Lattage vertical 30x45mm | B99: m2 | C99: 4.8763 | D99: 2.86 | E99: 0.55 | F99: 1.023 | G99: 0.4433
B100: m2 | C100: 10.29537 | D100: 2.1595598 | E100: 5.04 | F100: 2.1598679 | G100: 0.93594277
A104: OSB 8 / Pare-vapeur SD 90 / Structure 150 mm / OSB 12 / Bache de protection provisoire
A105: OSB 8 | B105: m2 | C105: 62.406971 | D105: 37.991239 | E105: 5.65 | F105: 13.092372 | G105: 5.673361 | H105: AE-15 TERRASA-POLYSTIREN | I105: 11
A106: Pare-vapeur SD 90 | B106: m2 | C106: 6.435 | D106: 3.75 | E106: 0.75 | F106: 1.35 | G106: 0.585
A107: Structure 150 mm | B107: m2 | C107: 3.4034 | D107: 1.83 | E107: 0.55 | F107: 0.714 | G107: 0.3094
A108: OSB 12 | B108: m2 | C108: 41.171471 | D108: 25.741239 | E108: 3.05 | F108: 8.6373716 | G108: 3.742861
A109: Bache de protection provisoire | B109: m2 | C109: 10.2245 | D109: 6.4 | E109: 0.75 | F109: 2.145 | G109: 0.9295
B110: m2 | C110: 1.1726 | D110: 0.27 | E110: 0.55 | F110: 0.246 | G110: 0.1066

Sheet ARTICLE
A1: Liste déroulante | B1: ARTICLES | C1: ID | D1: U | E1: PRIX | F1: MAT | G1: MO | H1: =GESTION!B4 -> 0.3 | I1: =GESTION!B3 -> 0.1
A2: {=_xlfn.UNIQUE(_xlfn._xlws.FILTER('MATRICE ARTICLE'!A2:A1395,NOT(ISBLANK('MATRICE ARTICLE'!A2:A1395))))} -> Structure 50 mm | B2: =IF(A2=0,"",A2) -> Structure 50 mm | D2: =IFERROR(VLOOKUP($B2,'MATRICE ARTICLE'!$A$2:$N$1395,2,FALSE),"") -> m2 | E2: =IF(SUM(F2:I2)=0,"",SUM(F2:I2)) -> 17.228034 | F2: =IFERROR(VLOOKUP($B2,'MATRICE ARTICLE'!$A$2:$N$1395,9,FALSE),"") -> 8.777576 | G2: =IFERROR(VLOOKUP($B2,'MATRICE ARTICLE'!$A$2:$N$1395,14,FALSE),"") -> 3.27 | H2: =IF(SUM(F2:G2)*$H$1=0,"",SUM(F2:G2)*$H$1) -> 3.6142728 | I2: =IF(SUM(F2:H2)*$I$1=0,"",SUM(F2:H2)*$I$1) -> 1.5661849
A3: Structure 100 mm | B3: =IF(A3=0,"",A3) -> Structure 100 mm | D3: =IFERROR(VLOOKUP($B3,'MATRICE ARTICLE'!$A$2:$N$1395,2,FALSE),"") -> m2 | E3: =IF(SUM(F3:I3)=0,"",SUM(F3:I3)) -> 32.392748 | F3: =IFERROR(VLOOKUP($B3,'MATRICE ARTICLE'!$A$2:$N$1395,9,FALSE),"") -> 18.822271 | G3: =IFERROR(VLOOKUP($B3,'MATRICE ARTICLE'!$A$2:$N$1395,14,FALSE),"") -> 3.83 | H3: =IF(SUM(F3:G3)*$H$1=0,"",SUM(F3:G3)*$H$1) -> 6.7956813 | I3: =IF(SUM(F3:H3)*$I$1=0,"",SUM(F3:H3)*$I$1) -> 2.9447952
A4: Structure 145 mm | B4: =IF(A4=0,"",A4) -> Structure 145 mm | D4: =IFERROR(VLOOKUP($B4,'MATRICE ARTICLE'!$A$2:$N$1395,2,FALSE),"") -> m2 | E4: =IF(SUM(F4:I4)=0,"",SUM(F4:I4)) -> 48.442138 | F4: =IFERROR(VLOOKUP($B4,'MATRICE ARTICLE'!$A$2:$N$1395,9,FALSE),"") -> 29.445621 | G4: =IFERROR(VLOOKUP($B4,'MATRICE ARTICLE'!$A$2:$N$1395,14,FALSE),"") -> 4.43 | H4: =IF(SUM(F4:G4)*$H$1=0,"",SUM(F4:G4)*$H$1) -> 10.162686 | I4: =IF(SUM(F4:H4)*$I$1=0,"",SUM(F4:H4)*$I$1) -> 4.4038307
A5: Structure PP 240-250 | B5: =IF(A5=0,"",A5) -> Structure PP 240-250 | D5: =IFERROR(VLOOKUP($B5,'MATRICE ARTICLE'!$A$2:$N$1395,2,FALSE),"") -> m2 | E5: =IF(SUM(F5:I5)=0,"",SUM(F5:I5)) -> 55.89461 | F5: =IFERROR(VLOOKUP($B5,'MATRICE ARTICLE'!$A$2:$N$1395,9,FALSE),"") -> 29.96714 | G5: =IFERROR(VLOOKUP($B5,'MATRICE ARTICLE'!$A$2:$N$1395,14,FALSE),"") -> 9.12 | H5: =IF(SUM(F5:G5)*$H$1=0,"",SUM(F5:G5)*$H$1) -> 11.726142 | I5: =IF(SUM(F5:H5)*$I$1=0,"",SUM(F5:H5)*$I$1) -> 5.0813282
A6: Structure PP 240-313 | B6: =IF(A6=0,"",A6) -> Structure PP 240-313 | D6: =IFERROR(VLOOKUP($B6,'MATRICE ARTICLE'!$A$2:$N$1395,2,FALSE),"") -> m2 | E6: =IF(SUM(F6:I6)=0,"",SUM(F6:I6)) -> 50.799929 | F6: =IFERROR(VLOOKUP($B6,'MATRICE ARTICLE'!$A$2:$N$1395,9,FALSE),"") -> 27.054426 | G6: =IFERROR(VLOOKUP($B6,'MATRICE ARTICLE'!$A$2:$N$1395,14,FALSE),"") -> 8.47 | H6: =IF(SUM(F6:G6)*$H$1=0,"",SUM(F6:G6)*$H$1) -> 10.657328 | I6: =IF(SUM(F6:H6)*$I$1=0,"",SUM(F6:H6)*$I$1) -> 4.6181754
A7: Structure PP 240-416 | B7: =IF(A7=0,"",A7) -> Structure PP 240-416 | D7: =IFERROR(VLOOKUP($B7,'MATRICE ARTICLE'!$A$2:$N$1395,2,FALSE),"") -> m2 | E7: =IF(SUM(F7:I7)=0,"",SUM(F7:I7)) -> 40.867967 | F7: =IFERROR(VLOOKUP($B7,'MATRICE ARTICLE'!$A$2:$N$1395,9,FALSE),"") -> 21.218998 | G7: =IFERROR(VLOOKUP($B7,'MATRICE ARTICLE'!$A$2:$N$1395,14,FALSE),"") -> 7.36 | H7: =IF(SUM(F7:G7)*$H$1=0,"",SUM(F7:G7)*$H$1) -> 8.5736994 | I7: =IF(SUM(F7:H7)*$I$1=0,"",SUM(F7:H7)*$I$1) -> 3.7152697
A8: Structure PP 240-625 | B8: =IF(A8=0,"",A8) -> Structure PP 240-625 | D8: =IFERROR(VLOOKUP($B8,'MATRICE ARTICLE'!$A$2:$N$1395,2,FALSE),"") -> m2 | E8: =IF(SUM(F8:I8)=0,"",SUM(F8:I8)) -> 34.257486 | F8: =IFERROR(VLOOKUP($B8,'MATRICE ARTICLE'!$A$2:$N$1395,9,FALSE),"") -> 18.306284 | G8: =IFERROR(VLOOKUP($B8,'MATRICE ARTICLE'!$A$2:$N$1395,14,FALSE),"") -> 5.65 | H8: =IF(SUM(F8:G8)*$H$1=0,"",SUM(F8:G8)*$H$1) -> 7.1868852 | I8: =IF(SUM(F8:H8)*$I$1=0,"",SUM(F8:H8)*$I$1) -> 3.1143169
A9: Structure PP 260-250 | B9: =IF(A9=0,"",A9) -> Structure PP 260-250 | D9: =IFERROR(VLOOKUP($B9,'MATRICE ARTICLE'!$A$2:$N$1395,2,FALSE),"") -> m2 | E9: =IF(SUM(F9:I9)=0,"",SUM(F9:I9)) -> 59.606311 | F9: =IFERROR(VLOOKUP($B9,'MATRICE ARTICLE'!$A$2:$N$1395,9,FALSE),"") -> 32.392735 | G9: =IFERROR(VLOOKUP($B9,'MATRICE ARTICLE'!$A$2:$N$1395,14,FALSE),"") -> 9.29 | H9: =IF(SUM(F9:G9)*$H$1=0,"",SUM(F9:G9)*$H$1) -> 12.50482 | I9: =IF(SUM(F9:H9)*$I$1=0,"",SUM(F9:H9)*$I$1) -> 5.4187556
A10: Structure PP 260-313 | B10: =IF(A10=0,"",A10) -> Structure PP 260-313 | D10: =IFERROR(VLOOKUP($B10,'MATRICE ARTICLE'!$A$2:$N$1395,2,FALSE),"") -> m2 | E10: =IF(SUM(F10:I10)=0,"",SUM(F10:I10)) -> 66.748237 | F10: =IFERROR(VLOOKUP($B10,'MATRICE ARTICLE'!$A$2:$N$1395,9,FALSE),"") -> 37.467089 | G10: =IFERROR(VLOOKUP($B10,'MATRICE ARTICLE'!$A$2:$N$1395,14,FALSE),"") -> 9.21 | H10: =IF(SUM(F10:G10)*$H$1=0,"",SUM(F10:G10)*$H$1) -> 14.003127 | I10: =IF(SUM(F10:H10)*$I$1=0,"",SUM(F10:H10)*$I$1) -> 6.0680216
A11: Structure PP 260-416 | B11: =IF(A11=0,"",A11) -> Structure PP 260-416 | D11: =IFERROR(VLOOKUP($B11,'MATRICE ARTICLE'!$A$2:$N$1395,2,FALSE),"") -> m2 | E11: =IF(SUM(F11:I11)=0,"",SUM(F11:I11)) -> 57.004437 | F11: =IFERROR(VLOOKUP($B11,'MATRICE ARTICLE'!$A$2:$N$1395,9,FALSE),"") -> 31.753243 | G11: =IFERROR(VLOOKUP($B11,'MATRICE ARTICLE'!$A$2:$N$1395,14,FALSE),"") -> 8.11 | H11: =IF(SUM(F11:G11)*$H$1=0,"",SUM(F11:G11)*$H$1) -> 11.958973 | I11: =IF(SUM(F11:H11)*$I$1=0,"",SUM(F11:H11)*$I$1) -> 5.1822216
A12: Structure PP 260-625 | B12: =IF(A12=0,"",A12) -> Structure PP 260-625 | D12: =IFERROR(VLOOKUP($B12,'MATRICE ARTICLE'!$A$2:$N$1395,2,FALSE),"") -> m2 | E12: =IF(SUM(F12:I12)=0,"",SUM(F12:I12)) -> 47.900423 | F12: =IFERROR(VLOOKUP($B12,'MATRICE ARTICLE'!$A$2:$N$1395,9,FALSE),"") -> 27.216799 | G12: =IFERROR(VLOOKUP($B12,'MATRICE ARTICLE'!$A$2:$N$1395,14,FALSE),"") -> 6.28 | H12: =IF(SUM(F12:G12)*$H$1=0,"",SUM(F12:G12)*$H$1) -> 10.04904 | I12: =IF(SUM(F12:H12)*$I$1=0,"",SUM(F12:H12)*$I$1) -> 4.3545839
A13: Structure PA 240-250 | B13: =IF(A13=0,"",A13) -> Structure PA 240-250 | D13: =IFERROR(VLOOKUP($B13,'MATRICE ARTICLE'!$A$2:$N$1395,2,FALSE),"") -> m2 | E13: =IF(SUM(F13:I13)=0,"",SUM(F13:I13)) -> 58.41141 | F13: =IFERROR(VLOOKUP($B13,'MATRICE ARTICLE'!$A$2:$N$1395,9,FALSE),"") -> 29.96714 | G13: =IFERROR(VLOOKUP($B13,'MATRICE ARTICLE'!$A$2:$N$1395,14,FALSE),"") -> 10.88 | H13: =IF(SUM(F13:G13)*$H$1=0,"",SUM(F13:G13)*$H$1) -> 12.254142 | I13: =IF(SUM(F13:H13)*$I$1=0,"",SUM(F13:H13)*$I$1) -> 5.3101282
A14: Structure PA 240-313 | B14: =IF(A14=0,"",A14) -> Structure PA 240-313 | D14: =IFERROR(VLOOKUP($B14,'MATRICE ARTICLE'!$A$2:$N$1395,2,FALSE),"") -> m2 | E14: =IF(SUM(F14:I14)=0,"",SUM(F14:I14)) -> 53.159429 | F14: =IFERROR(VLOOKUP($B14,'MATRICE ARTICLE'!$A$2:$N$1395,9,FALSE),"") -> 27.054426 | G14: =IFERROR(VLOOKUP($B14,'MATRICE ARTICLE'!$A$2:$N$1395,14,FALSE),"") -> 10.12 | H14: =IF(SUM(F14:G14)*$H$1=0,"",SUM(F14:G14)*$H$1) -> 11.152328 | I14: =IF(SUM(F14:H14)*$I$1=0,"",SUM(F14:H14)*$I$1) -> 4.8326754
... A104: Bardage horizontal cl4 | B104: =IF(A104=0,"",A104) -> Bardage horizontal cl4 | D104: =IFERROR(VLOOKUP($B104,'MATRICE ARTICLE'!$A$2:$N$1395,2,FALSE),"") -> m2 | E104: =IF(SUM(F104:I104)=0,"",SUM(F104:I104)) -> 29.3722 | F104: =IFERROR(VLOOKUP($B104,'MATRICE ARTICLE'!$A$2:$N$1395,9,FALSE),"") -> 17.52 | G104: =IFERROR(VLOOKUP($B104,'MATRICE ARTICLE'!$A$2:$N$1395,14,FALSE),"") -> 3.02 | H104: =IF(SUM(F104:G104)*$H$1=0,"",SUM(F104:G104)*$H$1) -> 6.162 | I104: =IF(SUM(F104:H104)*$I$1=0,"",SUM(F104:H104)*$I$1) -> 2.6702
B105: =IF(A105=0,"",A105) | D105: =IFERROR(VLOOKUP($B105,'MATRICE ARTICLE'!$A$2:$N$1395,2,FALSE),"") | E105: =IF(SUM(F105:I105)=0,"",SUM(F105:I105)) | F105: =IFERROR(VLOOKUP($B105,'MATRICE ARTICLE'!$A$2:$N$1395,9,FALSE),"") | G105: =IFERROR(VLOOKUP($B105,'MATRICE ARTICLE'!$A$2:$N$1395,14,FALSE),"") | H105: =IF(SUM(F105:G105)*$H$1=0,"",SUM(F105:G105)*$H$1) | I105: =IF(SUM(F105:H105)*$I$1=0,"",SUM(F105:H105)*$I$1)
B106: =IF(A106=0,"",A106) | D106: =IFERROR(VLOOKUP($B106,'MATRICE ARTICLE'!$A$2:$N$1395,2,FALSE),"") | E106: =IF(SUM(F106:I106)=0,"",SUM(F106:I106)) | F106: =IFERROR(VLOOKUP($B106,'MATRICE ARTICLE'!$A$2:$N$1395,9,FALSE),"") | G106: =IFERROR(VLOOKUP($B106,'MATRICE ARTICLE'!$A$2:$N$1395,14,FALSE),"") | H106: =IF(SUM(F106:G106)*$H$1=0,"",SUM(F106:G106)*$H$1) | I106: =IF(SUM(F106:H106)*$I$1=0,"",SUM(F106:H106)*$I$1)
B107: =IF(A107=0,"",A107) | D107: =IFERROR(VLOOKUP($B107,'MATRICE ARTICLE'!$A$2:$N$1395,2,FALSE),"") | E107: =IF(SUM(F107:I107)=0,"",SUM(F107:I107)) | F107: =IFERROR(VLOOKUP($B107,'MATRICE ARTICLE'!$A$2:$N$1395,9,FALSE),"") | G107: =IFERROR(VLOOKUP($B107,'MATRICE ARTICLE'!$A$2:$N$1395,14,FALSE),"") | H107: =IF(SUM(F107:G107)*$H$1=0,"",SUM(F107:G107)*$H$1) | I107: =IF(SUM(F107:H107)*$I$1=0,"",SUM(F107:H107)*$I$1)
B108: =IF(A108=0,"",A108) | D108: =IFERROR(VLOOKUP($B108,'MATRICE ARTICLE'!$A$2:$N$1395,2,FALSE),"") | E108: =IF(SUM(F108:I108)=0,"",SUM(F108:I108)) | F108: =IFERROR(VLOOKUP($B108,'MATRICE ARTICLE'!$A$2:$N$1395,9,FALSE),"") | G108: =IFERROR(VLOOKUP($B108,'MATRICE ARTICLE'!$A$2:$N$1395,14,FALSE),"") | H108: =IF(SUM(F108:G108)*$H$1=0,"",SUM(F108:G108)*$H$1) | I108: =IF(SUM(F108:H108)*$I$1=0,"",SUM(F108:H108)*$I$1)
B109: =IF(A109=0,"",A109) | D109: =IFERROR(VLOOKUP($B109,'MATRICE ARTICLE'!$A$2:$N$1395,2,FALSE),"") | E109: =IF(SUM(F109:I109)=0,"",SUM(F109:I109)) | F109: =IFERROR(VLOOKUP($B109,'MATRICE ARTICLE'!$A$2:$N$1395,9,FALSE),"") | G109: =IFERROR(VLOOKUP($B109,'MATRICE ARTICLE'!$A$2:$N$1395,14,FALSE),"") | H109: =IF(SUM(F109:G109)*$H$1=0,"",SUM(F109:G109)*$H$1) | I109: =IF(SUM(F109:H109)*$I$1=0,"",SUM(F109:H109)*$I$1)
B110: =IF(A110=0,"",A110) | D110: =IFERROR(VLOOKUP($B110,'MATRICE ARTICLE'!$A$2:$N$1395,2,FALSE),"") | E110: =IF(SUM(F110:I110)=0,"",SUM(F110:I110)) | F110: =IFERROR(VLOOKUP($B110,'MATRICE ARTICLE'!$A$2:$N$1395,9,FALSE),"") | G110: =IFERROR(VLOOKUP($B110,'MATRICE ARTICLE'!$A$2:$N$1395,14,FALSE),"") | H110: =IF(SUM(F110:G110)*$H$1=0,"",SUM(F110:G110)*$H$1) | I110: =IF(SUM(F110:H110)*$I$1=0,"",SUM(F110:H110)*$I$1)
B111: =IF(A111=0,"",A111) | D111: =IFERROR(VLOOKUP($B111,'MATRICE ARTICLE'!$A$2:$N$1395,2,FALSE),"") | E111: =IF(SUM(F111:I111)=0,"",SUM(F111:I111)) | F111: =IFERROR(VLOOKUP($B111,'MATRICE ARTICLE'!$A$2:$N$1395,9,FALSE),"") | G111: =IFERROR(VLOOKUP($B111,'MATRICE ARTICLE'!$A$2:$N$1395,14,FALSE),"") | H111: =IF(SUM(F111:G111)*$H$1=0,"",SUM(F111:G111)*$H$1) | I111: =IF(SUM(F111:H111)*$I$1=0,"",SUM(F111:H111)*$I$1)
B112: =IF(A112=0,"",A112) | D112: =IFERROR(VLOOKUP($B112,'MATRICE ARTICLE'!$A$2:$N$1395,2,FALSE),"") | E112: =IF(SUM(F112:I112)=0,"",SUM(F112:I112)) | F112: =IFERROR(VLOOKUP($B112,'MATRICE ARTICLE'!$A$2:$N$1395,9,FALSE),"") | G112: =IFERROR(VLOOKUP($B112,'MATRICE ARTICLE'!$A$2:$N$1395,14,FALSE),"") | H112: =IF(SUM(F112:G112)*$H$1=0,"",SUM(F112:G112)*$H$1) | I112: =IF(SUM(F112:H112)*$I$1=0,"",SUM(F112:H112)*$I$1)
B113: =IF(A113=0,"",A113) | D113: =IFERROR(VLOOKUP($B113,'MATRICE ARTICLE'!$A$2:$N$1395,2,FALSE),"") | E113: =IF(SUM(F113:I113)=0,"",SUM(F113:I113)) | F113: =IFERROR(VLOOKUP($B113,'MATRICE ARTICLE'!$A$2:$N$1395,9,FALSE),"") | G113: =IFERROR(VLOOKUP($B113,'MATRICE ARTICLE'!$A$2:$N$1395,14,FALSE),"") | H113: =IF(SUM(F113:G113)*$H$1=0,"",SUM(F113:G113)*$H$1) | I113: =IF(SUM(F113:H113)*$I$1=0,"",SUM(F113:H113)*$I$1)
B114: =IF(A114=0,"",A114) | D114: =IFERROR(VLOOKUP($B114,'MATRICE ARTICLE'!$A$2:$N$1395,2,FALSE),"") | E114: =IF(SUM(F114:I114)=0,"",SUM(F114:I114)) | F114: =IFERROR(VLOOKUP($B114,'MATRICE ARTICLE'!$A$2:$N$1395,9,FALSE),"") | G114: =IFERROR(VLOOKUP($B114,'MATRICE ARTICLE'!$A$2:$N$1395,14,FALSE),"") | H114: =IF(SUM(F114:G114)*$H$1=0,"",SUM(F114:G114)*$H$1) | I114: =IF(SUM(F114:H114)*$I$1=0,"",SUM(F114:H114)*$I$1)
B115: =IF(A115=0,"",A115) | D115: =IFERROR(VLOOKUP($B115,'MATRICE ARTICLE'!$A$2:$N$1395,2,FALSE),"") | E115: =IF(SUM(F115:I115)=0,"",SUM(F115:I115)) | F115: =IFERROR(VLOOKUP($B115,'MATRICE ARTICLE'!$A$2:$N$1395,9,FALSE),"") | G115: =IFERROR(VLOOKUP($B115,'MATRICE ARTICLE'!$A$2:$N$1395,14,FALSE),"") | H115: =IF(SUM(F115:G115)*$H$1=0,"",SUM(F115:G115)*$H$1) | I115: =IF(SUM(F115:H115)*$I$1=0,"",SUM(F115:H115)*$I$1)
B116: =IF(A116=0,"",A116) | D116: =IFERROR(VLOOKUP($B116,'MATRICE ARTICLE'!$A$2:$N$1395,2,FALSE),"") | E116: =IF(SUM(F116:I116)=0,"",SUM(F116:I116)) | F116: =IFERROR(VLOOKUP($B116,'MATRICE ARTICLE'!$A$2:$N$1395,9,FALSE),"") | G116: =IFERROR(VLOOKUP($B116,'MATRICE ARTICLE'!$A$2:$N$1395,14,FALSE),"") | H116: =IF(SUM(F116:G116)*$H$1=0,"",SUM(F116:G116)*$H$1) | I116: =IF(SUM(F116:H116)*$I$1=0,"",SUM(F116:H116)*$I$1)
... B1099: =IF(A1099=0,"",A1099) | D1099: =IFERROR(VLOOKUP($B1099,'MATRICE ARTICLE'!$A$2:$N$1395,2,FALSE),"") | E1099: =IF(SUM(F1099:I1099)=0,"",SUM(F1099:I1099)) | F1099: =IFERROR(VLOOKUP($B1099,'MATRICE ARTICLE'!$A$2:$N$1395,9,FALSE),"") | G1099: =IFERROR(VLOOKUP($B1099,'MATRICE ARTICLE'!$A$2:$N$1395,14,FALSE),"") | H1099: =IF(SUM(F1099:G1099)*$H$1=0,"",SUM(F1099:G1099)*$H$1) | I1099: =IF(SUM(F1099:H1099)*$I$1=0,"",SUM(F1099:H1099)*$I$1)

Sheet MATRICE ARTICLE
A1: Nr CRT. | B1: UM | C1: MATERIAUX | J1: MAIN D'ŒUVRE
C2: Componente | D2: Cant/Um | E2: Pierd | F2: UM | G2: Pret Euro | H2: Valoare Euro | I2: 1 | J2: etapa de fabricație | K2: Cant | L2: Pret Euro | M2: Valoare Euro | N2: 0.55 | O2: Suprafete | P2: Cant | Q2: Val
A3: Structure 50 mm | B3: m2 | C3: Lemn 50x45 mm | D3: =ROUND(5*0.05*0.045*1.21,4) -> 0.0136 | E3: 0.1 | F3: =IFERROR(VLOOKUP(C3,MATERIAUX!$C$3:$G$1002,3,FALSE),"") -> m3 | G3: =IFERROR(VLOOKUP(C3,MATERIAUX!$C$3:$G$1002,5,FALSE),"") -> 524.74227 | H3: =IFERROR(ROUND(G3*(1+E3)*D3,2),"") -> 7.85 | I3: =SUM(H3:H12) -> 8.777576 | J3: mur structure | K3: 1 | L3: =IFERROR(VLOOKUP(J3,'MAIN D OEUVRE'!$A$4:$B$99,2,FALSE)*$N$2,"") -> 2.75 | M3: =IFERROR(ROUND(L3*K3,2),"") -> 2.75 | N3: =SUM(M3:M12) -> 3.27 | O3: 0 | P3: =(D3+D3*E3)*O3 -> 0 | Q3: =IF(P3=0,0,P3*G3) -> 0
F4: =IFERROR(VLOOKUP(C4,MATERIAUX!$C$3:$G$1002,3,FALSE),"") | G4: =IFERROR(VLOOKUP(C4,MATERIAUX!$C$3:$G$1002,5,FALSE),"") | H4: =IFERROR(ROUND(G4*(1+E4)*D4,2),"") | J4: Bochemit | K4: =(D3+D4)*2 -> 0.0272 | L4: =IFERROR(VLOOKUP(J4,'MAIN D OEUVRE'!$A$4:$B$99,2,FALSE)*$N$2,"") -> 19.25 | M4: =IFERROR(ROUND(L4*K4,2),"") -> 0.52 | O4: =O3 -> 0 | P4: =(D4+D4*E4)*O4 -> 0 | Q4: =IF(P4=0,0,P4*G4) -> 0
C5: Cuie 90 / 120 | D5: 21 | E5: 0 | F5: =IFERROR(VLOOKUP(C5,MATERIAUX!$C$3:$G$1002,3,FALSE),"") -> u | G5: =IFERROR(VLOOKUP(C5,MATERIAUX!$C$3:$G$1002,5,FALSE),"") -> 0.039175258 | H5: =IFERROR(ROUND(G5*(1+E5)*D5,2),"") -> 0.82 | L5: =IFERROR(VLOOKUP(J5,'MAIN D OEUVRE'!$A$4:$B$99,2,FALSE)*$N$2,"") | M5: =IFERROR(ROUND(L5*K5,2),"") | O5: =O4 -> 0 | P5: =(D5+D5*E5)*O5 -> 0 | Q5: =IF(P5=0,0,P5*G5) -> 0
C6: BOCHEMIT | D6: 1.06 | E6: 0.02 | F6: =IFERROR(VLOOKUP(C6,MATERIAUX!$C$3:$G$1002,3,FALSE),"") -> m2 | G6: =IFERROR(VLOOKUP(C6,MATERIAUX!$C$3:$G$1002,5,FALSE),"") -> 7.3154639 | H6: =IFERROR(ROUND(G6*(1+E6)*D6,2)*(D3+D4),"") -> 0.107576 | L6: =IFERROR(VLOOKUP(J6,'MAIN D OEUVRE'!$A$4:$B$99,2,FALSE)*$N$2,"") | M6: =IFERROR(ROUND(L6*K6,2),"") | O6: =O5 -> 0 | P6: =O6*D6*(D3+D4)*1.02 -> 0 | Q6: =IF(P6=0,0,P6*G6) -> 0
F7: =IFERROR(VLOOKUP(C7,MATERIAUX!$C$3:$G$1002,3,FALSE),"") | G7: =IFERROR(VLOOKUP(C7,MATERIAUX!$C$3:$G$1002,5,FALSE),"") | H7: =IFERROR(ROUND(G7*(1+E7)*D7,2),"") | L7: =IFERROR(VLOOKUP(J7,'MAIN D OEUVRE'!$A$4:$B$99,2,FALSE)*$N$2,"") | M7: =IFERROR(ROUND(L7*K7,2),"") | O7: =O6 -> 0 | P7: =(D7+D7*E7)*O7 -> 0 | Q7: =IF(P7=0,0,P7*G7) -> 0
F8: =IFERROR(VLOOKUP(C8,MATERIAUX!$C$3:$G$1002,3,FALSE),"") | G8: =IFERROR(VLOOKUP(C8,MATERIAUX!$C$3:$G$1002,5,FALSE),"") | H8: =IFERROR(ROUND(G8*(1+E8)*D8,2),"") | L8: =IFERROR(VLOOKUP(J8,'MAIN D OEUVRE'!$A$4:$B$99,2,FALSE)*$N$2,"") | M8: =IFERROR(ROUND(L8*K8,2),"") | O8: =O7 -> 0 | P8: =(D8+D8*E8)*O8 -> 0 | Q8: =IF(P8=0,0,P8*G8) -> 0
F9: =IFERROR(VLOOKUP(C9,MATERIAUX!$C$3:$G$1002,3,FALSE),"") | G9: =IFERROR(VLOOKUP(C9,MATERIAUX!$C$3:$G$1002,5,FALSE),"") | H9: =IFERROR(ROUND(G9*(1+E9)*D9,2),"") | L9: =IFERROR(VLOOKUP(J9,'MAIN D OEUVRE'!$A$4:$B$99,2,FALSE)*$N$2,"") | M9: =IFERROR(ROUND(L9*K9,2),"") | O9: =O8 -> 0 | P9: =(D9+D9*E9)*O9 -> 0 | Q9: =IF(P9=0,0,P9*G9) -> 0
F10: =IFERROR(VLOOKUP(C10,MATERIAUX!$C$3:$G$1002,3,FALSE),"") | G10: =IFERROR(VLOOKUP(C10,MATERIAUX!$C$3:$G$1002,5,FALSE),"") | H10: =IFERROR(ROUND(G10*(1+E10)*D10,2),"") | L10: =IFERROR(VLOOKUP(J10,'MAIN D OEUVRE'!$A$4:$B$99,2,FALSE)*$N$2,"") | M10: =IFERROR(ROUND(L10*K10,2),"") | O10: =O9 -> 0 | P10: =(D10+D10*E10)*O10 -> 0 | Q10: =IF(P10=0,0,P10*G10) -> 0
F11: =IFERROR(VLOOKUP(C11,MATERIAUX!$C$3:$G$1002,3,FALSE),"") | G11: =IFERROR(VLOOKUP(C11,MATERIAUX!$C$3:$G$1002,5,FALSE),"") | H11: =IFERROR(ROUND(G11*(1+E11)*D11,2),"") | O11: =O10 -> 0 | P11: =(D11+D11*E11)*O11 -> 0 | Q11: =IF(P11=0,0,P11*G11) -> 0
F12: =IFERROR(VLOOKUP(C12,MATERIAUX!$C$3:$G$1002,3,FALSE),"") | G12: =IFERROR(VLOOKUP(C12,MATERIAUX!$C$3:$G$1002,5,FALSE),"") | H12: =IFERROR(ROUND(G12*(1+E12)*D12,2),"") | O12: =O11 -> 0 | P12: =(D12+D12*E12)*O12 -> 0 | Q12: =IF(P12=0,0,P12*G12) -> 0
A13: Structure 100 mm | B13: m2 | C13: Lemn 100x45 mm | D13: =ROUND(5*0.1*0.045*1.25,4) -> 0.0281 | E13: 0.1 | F13: =IFERROR(VLOOKUP(C13,MATERIAUX!$C$3:$G$1002,3,FALSE),"") -> m3 | G13: =IFERROR(VLOOKUP(C13,MATERIAUX!$C$3:$G$1002,5,FALSE),"") -> 575.25773 | H13: =IFERROR(ROUND(G13*(1+E13)*D13,2),"") -> 17.78 | I13: =SUM(H13:H22) -> 18.822271 | J13: mur structure | K13: 1 | L13: =IFERROR(VLOOKUP(J13,'MAIN D OEUVRE'!$A$4:$B$99,2,FALSE)*$N$2,"") -> 2.75 | M13: =IFERROR(ROUND(L13*K13,2),"") -> 2.75 | N13: =SUM(M13:M22) -> 3.83 | O13: 554 | P13: =(D13+D13*E13)*O13 -> 17.12414 | Q13: =IF(P13=0,0,P13*G13) -> 9850.7939
J14: Bochemit | K14: =(D13+D14)*2 -> 0.0562 | L14: =IFERROR(VLOOKUP(J14,'MAIN D OEUVRE'!$A$4:$B$99,2,FALSE)*$N$2,"") -> 19.25 | M14: =IFERROR(ROUND(L14*K14,2),"") -> 1.08 | O14: =O13 -> 554 | P14: =(D14+D14*E14)*O14 -> 0 | Q14: =IF(P14=0,0,P14*G14) -> 0
C15: Cuie 90 / 120 | D15: 21 | E15: 0 | F15: =IFERROR(VLOOKUP(C15,MATERIAUX!$C$3:$G$1002,3,FALSE),"") -> u | G15: =IFERROR(VLOOKUP(C15,MATERIAUX!$C$3:$G$1002,5,FALSE),"") -> 0.039175258 | H15: =IFERROR(ROUND(G15*(1+E15)*D15,2),"") -> 0.82 | L15: =IFERROR(VLOOKUP(J15,'MAIN D OEUVRE'!$A$4:$B$99,2,FALSE)*$N$2,"") | M15: =IFERROR(ROUND(L15*K15,2),"") | O15: =O14 -> 554 | P15: =(D15+D15*E15)*O15 -> 11634 | Q15: =IF(P15=0,0,P15*G15) -> 455.76495
C16: BOCHEMIT | D16: 1.06 | E16: 0.02 | F16: =IFERROR(VLOOKUP(C16,MATERIAUX!$C$3:$G$1002,3,FALSE),"") -> m2 | G16: =IFERROR(VLOOKUP(C16,MATERIAUX!$C$3:$G$1002,5,FALSE),"") -> 7.3154639 | H16: =IFERROR(ROUND(G16*(1+E16)*D16,2)*(D13+D14),"") -> 0.222271 | L16: =IFERROR(VLOOKUP(J16,'MAIN D OEUVRE'!$A$4:$B$99,2,FALSE)*$N$2,"") | M16: =IFERROR(ROUND(L16*K16,2),"") | O16: =O15 -> 554 | P16: =O16*D16*(D13+D14)*1.02 -> 16.831473 | Q16: =IF(P16=0,0,P16*G16) -> 123.13003
F17: =IFERROR(VLOOKUP(C17,MATERIAUX!$C$3:$G$1002,3,FALSE),"") | G17: =IFERROR(VLOOKUP(C17,MATERIAUX!$C$3:$G$1002,5,FALSE),"") | H17: =IFERROR(ROUND(G17*(1+E17)*D17,2),"") | L17: =IFERROR(VLOOKUP(J17,'MAIN D OEUVRE'!$A$4:$B$99,2,FALSE)*$N$2,"") | M17: =IFERROR(ROUND(L17*K17,2),"") | O17: =O16 -> 554 | P17: =(D17+D17*E17)*O17 -> 0 | Q17: =IF(P17=0,0,P17*G17) -> 0
F18: =IFERROR(VLOOKUP(C18,MATERIAUX!$C$3:$G$1002,3,FALSE),"") | G18: =IFERROR(VLOOKUP(C18,MATERIAUX!$C$3:$G$1002,5,FALSE),"") | H18: =IFERROR(ROUND(G18*(1+E18)*D18,2),"") | L18: =IFERROR(VLOOKUP(J18,'MAIN D OEUVRE'!$A$4:$B$99,2,FALSE)*$N$2,"") | M18: =IFERROR(ROUND(L18*K18,2),"") | O18: =O17 -> 554 | P18: =(D18+D18*E18)*O18 -> 0 | Q18: =IF(P18=0,0,P18*G18) -> 0
F19: =IFERROR(VLOOKUP(C19,MATERIAUX!$C$3:$G$1002,3,FALSE),"") | G19: =IFERROR(VLOOKUP(C19,MATERIAUX!$C$3:$G$1002,5,FALSE),"") | H19: =IFERROR(ROUND(G19*(1+E19)*D19,2),"") | L19: =IFERROR(VLOOKUP(J19,'MAIN D OEUVRE'!$A$4:$B$99,2,FALSE)*$N$2,"") | M19: =IFERROR(ROUND(L19*K19,2),"") | O19: =O18 -> 554 | P19: =(D19+D19*E19)*O19 -> 0 | Q19: =IF(P19=0,0,P19*G19) -> 0
F20: =IFERROR(VLOOKUP(C20,MATERIAUX!$C$3:$G$1002,3,FALSE),"") | G20: =IFERROR(VLOOKUP(C20,MATERIAUX!$C$3:$G$1002,5,FALSE),"") | H20: =IFERROR(ROUND(G20*(1+E20)*D20,2),"") | L20: =IFERROR(VLOOKUP(J20,'MAIN D OEUVRE'!$A$4:$B$99,2,FALSE)*$N$2,"") | M20: =IFERROR(ROUND(L20*K20,2),"") | O20: =O19 -> 554 | P20: =(D20+D20*E20)*O20 -> 0 | Q20: =IF(P20=0,0,P20*G20) -> 0
F21: =IFERROR(VLOOKUP(C21,MATERIAUX!$C$3:$G$1002,3,FALSE),"") | G21: =IFERROR(VLOOKUP(C21,MATERIAUX!$C$3:$G$1002,5,FALSE),"") | H21: =IFERROR(ROUND(G21*(1+E21)*D21,2),"") | O21: =O20 -> 554 | P21: =(D21+D21*E21)*O21 -> 0 | Q21: =IF(P21=0,0,P21*G21) -> 0
F22: =IFERROR(VLOOKUP(C22,MATERIAUX!$C$3:$G$1002,3,FALSE),"") | G22: =IFERROR(VLOOKUP(C22,MATERIAUX!$C$3:$G$1002,5,FALSE),"") | H22: =IFERROR(ROUND(G22*(1+E22)*D22,2),"") | O22: =O21 -> 554 | P22: =(D22+D22*E22)*O22 -> 0 | Q22: =IF(P22=0,0,P22*G22) -> 0
A23: Structure 145 mm | B23: m2 | C23: Lemn 150x45 mm | D23: =ROUND(5*0.15*0.045*1.1,4)+3.64/552 -> 0.043694203 | E23: 0.1 | F23: =IFERROR(VLOOKUP(C23,MATERIAUX!$C$3:$G$1002,3,FALSE),"") -> m3 | G23: =IFERROR(VLOOKUP(C23,MATERIAUX!$C$3:$G$1002,5,FALSE),"") -> 575.25773 | H23: =IFERROR(ROUND(G23*(1+E23)*D23,2),"") -> 27.65 | I23: =SUM(H23:H32) -> 29.445621 | J23: mur structure | K23: 1 | L23: =IFERROR(VLOOKUP(J23,'MAIN D OEUVRE'!$A$4:$B$99,2,FALSE)*$N$2,"") -> 2.75 | M23: =IFERROR(ROUND(L23*K23,2),"") -> 2.75 | N23: =SUM(M23:M32) -> 4.43 | O23: 548 | P23: =(D23+D23*E23)*O23 -> 26.338866 | Q23: =IF(P23=0,0,P23*G23) -> 15151.636
F24: =IFERROR(VLOOKUP(C24,MATERIAUX!$C$3:$G$1002,3,FALSE),"") | G24: =IFERROR(VLOOKUP(C24,MATERIAUX!$C$3:$G$1002,5,FALSE),"") | H24: =IFERROR(ROUND(G24*(1+E24)*D24,2),"") | J24: Bochemit | K24: =(D23+D24)*2 -> 0.087388406 | L24: =IFERROR(VLOOKUP(J24,'MAIN D OEUVRE'!$A$4:$B$99,2,FALSE)*$N$2,"") -> 19.25 | M24: =IFERROR(ROUND(L24*K24,2),"") -> 1.68 | O24: =O23 -> 548 | P24: =(D24+D24*E24)*O24 -> 0 | Q24: =IF(P24=0,0,P24*G24) -> 0
C25: Cuie 90 / 120 | D25: 37 | E25: 0 | F25: =IFERROR(VLOOKUP(C25,MATERIAUX!$C$3:$G$1002,3,FALSE),"") -> u | G25: =IFERROR(VLOOKUP(C25,MATERIAUX!$C$3:$G$1002,5,FALSE),"") -> 0.039175258 | H25: =IFERROR(ROUND(G25*(1+E25)*D25,2),"") -> 1.45 | L25: =IFERROR(VLOOKUP(J25,'MAIN D OEUVRE'!$A$4:$B$99,2,FALSE)*$N$2,"") | M25: =IFERROR(ROUND(L25*K25,2),"") | O25: =O24 -> 548 | P25: =(D25+D25*E25)*O25 -> 20276 | Q25: =IF(P25=0,0,P25*G25) -> 794.31753
C26: BOCHEMIT | D26: 1.06 | E26: 0.02 | F26: =IFERROR(VLOOKUP(C26,MATERIAUX!$C$3:$G$1002,3,FALSE),"") -> m2 | G26: =IFERROR(VLOOKUP(C26,MATERIAUX!$C$3:$G$1002,5,FALSE),"") -> 7.3154639 | H26: =IFERROR(ROUND(G26*(1+E26)*D26,2)*(D23+D24),"") -> 0.34562114 | L26: =IFERROR(VLOOKUP(J26,'MAIN D OEUVRE'!$A$4:$B$99,2,FALSE)*$N$2,"") | M26: =IFERROR(ROUND(L26*K26,2),"") | O26: =O25 -> 548 | P26: =O26*D26*(D23+D24)*1.02 -> 25.88871 | Q26: =IF(P26=0,0,P26*G26) -> 189.38793
F27: =IFERROR(VLOOKUP(C27,MATERIAUX!$C$3:$G$1002,3,FALSE),"") | G27: =IFERROR(VLOOKUP(C27,MATERIAUX!$C$3:$G$1002,5,FALSE),"") | H27: =IFERROR(ROUND(G27*(1+E27)*D27,2),"") | L27: =IFERROR(VLOOKUP(J27,'MAIN D OEUVRE'!$A$4:$B$99,2,FALSE)*$N$2,"") | M27: =IFERROR(ROUND(L27*K27,2),"") | O27: =O26 -> 548 | P27: =(D27+D27*E27)*O27 -> 0 | Q27: =IF(P27=0,0,P27*G27) -> 0
F28: =IFERROR(VLOOKUP(C28,MATERIAUX!$C$3:$G$1002,3,FALSE),"") | G28: =IFERROR(VLOOKUP(C28,MATERIAUX!$C$3:$G$1002,5,FALSE),"") | H28: =IFERROR(ROUND(G28*(1+E28)*D28,2),"") | L28: =IFERROR(VLOOKUP(J28,'MAIN D OEUVRE'!$A$4:$B$99,2,FALSE)*$N$2,"") | M28: =IFERROR(ROUND(L28*K28,2),"") | O28: =O27 -> 548 | P28: =(D28+D28*E28)*O28 -> 0 | Q28: =IF(P28=0,0,P28*G28) -> 0
F29: =IFERROR(VLOOKUP(C29,MATERIAUX!$C$3:$G$1002,3,FALSE),"") | G29: =IFERROR(VLOOKUP(C29,MATERIAUX!$C$3:$G$1002,5,FALSE),"") | H29: =IFERROR(ROUND(G29*(1+E29)*D29,2),"") | L29: =IFERROR(VLOOKUP(J29,'MAIN D OEUVRE'!$A$4:$B$99,2,FALSE)*$N$2,"") | M29: =IFERROR(ROUND(L29*K29,2),"") | O29: =O28 -> 548 | P29: =(D29+D29*E29)*O29 -> 0 | Q29: =IF(P29=0,0,P29*G29) -> 0
F30: =IFERROR(VLOOKUP(C30,MATERIAUX!$C$3:$G$1002,3,FALSE),"") | G30: =IFERROR(VLOOKUP(C30,MATERIAUX!$C$3:$G$1002,5,FALSE),"") | H30: =IFERROR(ROUND(G30*(1+E30)*D30,2),"") | L30: =IFERROR(VLOOKUP(J30,'MAIN D OEUVRE'!$A$4:$B$99,2,FALSE)*$N$2,"") | M30: =IFERROR(ROUND(L30*K30,2),"") | O30: =O29 -> 548 | P30: =(D30+D30*E30)*O30 -> 0 | Q30: =IF(P30=0,0,P30*G30) -> 0
F31: =IFERROR(VLOOKUP(C31,MATERIAUX!$C$3:$G$1002,3,FALSE),"") | G31: =IFERROR(VLOOKUP(C31,MATERIAUX!$C$3:$G$1002,5,FALSE),"") | H31: =IFERROR(ROUND(G31*(1+E31)*D31,2),"") | O31: =O30 -> 548 | P31: =(D31+D31*E31)*O31 -> 0 | Q31: =IF(P31=0,0,P31*G31) -> 0
F32: =IFERROR(VLOOKUP(C32,MATERIAUX!$C$3:$G$1002,3,FALSE),"") | G32: =IFERROR(VLOOKUP(C32,MATERIAUX!$C$3:$G$1002,5,FALSE),"") | H32: =IFERROR(ROUND(G32*(1+E32)*D32,2),"") | O32: =O31 -> 548 | P32: =(D32+D32*E32)*O32 -> 0 | Q32: =IF(P32=0,0,P32*G32) -> 0
A33: Structure PP 240-250 | B33: m2 | C33: Lemn 240x45 mm | D33: =ROUND(5*0.24*0.045,4) -> 0.054 | E33: 0.1 | F33: =IFERROR(VLOOKUP(C33,MATERIAUX!$C$3:$G$1002,3,FALSE),"") -> m3 | G33: =IFERROR(VLOOKUP(C33,MATERIAUX!$C$3:$G$1002,5,FALSE),"") -> 483.50515 | H33: =IFERROR(ROUND(G33*(1+E33)*D33,2),"") -> 28.72 | I33: =SUM(H33:H42) -> 29.96714 | J33: PP Structure | K33: =ROUNDUP(2-0.25/0.625,2) -> 1.6 | L33: =IFERROR(VLOOKUP(J33,'MAIN D OEUVRE'!$A$4:$B$99,2,FALSE)*$N$2,"") -> 4.4 | M33: =IFERROR(ROUND(L33*K33,2),"") -> 7.04 | N33: =SUM(M33:M42) -> 9.12 | O33: 0 | P33: =(D33+D33*E33)*O33 -> 0 | Q33: =IF(P33=0,0,P33*G33) -> 0
C34: Cuie 90 / 120 | D34: 21 | E34: 0 | F34: =IFERROR(VLOOKUP(C34,MATERIAUX!$C$3:$G$1002,3,FALSE),"") -> u | G34: =IFERROR(VLOOKUP(C34,MATERIAUX!$C$3:$G$1002,5,FALSE),"") -> 0.039175258 | H34: =IFERROR(ROUND(G34*(1+E34)*D34,2),"") -> 0.82 | J34: Bochemit | K34: =D33*2 -> 0.108 | L34: =IFERROR(VLOOKUP(J34,'MAIN D OEUVRE'!$A$4:$B$99,2,FALSE)*$N$2,"") -> 19.25 | M34: =IFERROR(ROUND(L34*K34,2),"") -> 2.08 | O34: =O33 -> 0 | P34: =(D34+D34*E34)*O34 -> 0 | Q34: =IF(P34=0,0,P34*G34) -> 0
C35: BOCHEMIT | D35: 1.06 | E35: 0.02 | F35: =IFERROR(VLOOKUP(C35,MATERIAUX!$C$3:$G$1002,3,FALSE),"") -> m2 | G35: =IFERROR(VLOOKUP(C35,MATERIAUX!$C$3:$G$1002,5,FALSE),"") -> 7.3154639 | H35: =IFERROR(ROUND(G35*(1+E35)*D35,2)*D33,"") -> 0.42714 | L35: =IFERROR(VLOOKUP(J35,'MAIN D OEUVRE'!$A$4:$B$99,2,FALSE)*$N$2,"") | M35: =IFERROR(ROUND(L35*K35,2),"") | O35: =O34 -> 0 | P35: =O35*D35*(D32+D33)*1.02 -> 0 | Q35: =IF(P35=0,0,P35*G35) -> 0
F36: =IFERROR(VLOOKUP(C36,MATERIAUX!$C$3:$G$1002,3,FALSE),"") | G36: =IFERROR(VLOOKUP(C36,MATERIAUX!$C$3:$G$1002,5,FALSE),"") | H36: =IFERROR(ROUND(G36*(1+E36)*D36,2),"") | L36: =IFERROR(VLOOKUP(J36,'MAIN D OEUVRE'!$A$4:$B$99,2,FALSE)*$N$2,"") | M36: =IFERROR(ROUND(L36*K36,2),"") | O36: =O35 -> 0 | P36: =(D36+D36*E36)*O36 -> 0 | Q36: =IF(P36=0,0,P36*G36) -> 0
F37: =IFERROR(VLOOKUP(C37,MATERIAUX!$C$3:$G$1002,3,FALSE),"") | G37: =IFERROR(VLOOKUP(C37,MATERIAUX!$C$3:$G$1002,5,FALSE),"") | H37: =IFERROR(ROUND(G37*(1+E37)*D37,2),"") | L37: =IFERROR(VLOOKUP(J37,'MAIN D OEUVRE'!$A$4:$B$99,2,FALSE)*$N$2,"") | M37: =IFERROR(ROUND(L37*K37,2),"") | O37: =O36 -> 0 | P37: =(D37+D37*E37)*O37 -> 0 | Q37: =IF(P37=0,0,P37*G37) -> 0
F38: =IFERROR(VLOOKUP(C38,MATERIAUX!$C$3:$G$1002,3,FALSE),"") | G38: =IFERROR(VLOOKUP(C38,MATERIAUX!$C$3:$G$1002,5,FALSE),"") | H38: =IFERROR(ROUND(G38*(1+E38)*D38,2),"") | L38: =IFERROR(VLOOKUP(J38,'MAIN D OEUVRE'!$A$4:$B$99,2,FALSE)*$N$2,"") | M38: =IFERROR(ROUND(L38*K38,2),"") | O38: =O37 -> 0 | P38: =(D38+D38*E38)*O38 -> 0 | Q38: =IF(P38=0,0,P38*G38) -> 0
F39: =IFERROR(VLOOKUP(C39,MATERIAUX!$C$3:$G$1002,3,FALSE),"") | G39: =IFERROR(VLOOKUP(C39,MATERIAUX!$C$3:$G$1002,5,FALSE),"") | H39: =IFERROR(ROUND(G39*(1+E39)*D39,2),"") | L39: =IFERROR(VLOOKUP(J39,'MAIN D OEUVRE'!$A$4:$B$99,2,FALSE)*$N$2,"") | M39: =IFERROR(ROUND(L39*K39,2),"") | O39: =O38 -> 0 | P39: =(D39+D39*E39)*O39 -> 0 | Q39: =IF(P39=0,0,P39*G39) -> 0
F40: =IFERROR(VLOOKUP(C40,MATERIAUX!$C$3:$G$1002,3,FALSE),"") | G40: =IFERROR(VLOOKUP(C40,MATERIAUX!$C$3:$G$1002,5,FALSE),"") | H40: =IFERROR(ROUND(G40*(1+E40)*D40,2),"") | L40: =IFERROR(VLOOKUP(J40,'MAIN D OEUVRE'!$A$4:$B$99,2,FALSE)*$N$2,"") | M40: =IFERROR(ROUND(L40*K40,2),"") | O40: =O39 -> 0 | P40: =(D40+D40*E40)*O40 -> 0 | Q40: =IF(P40=0,0,P40*G40) -> 0
F41: =IFERROR(VLOOKUP(C41,MATERIAUX!$C$3:$G$1002,3,FALSE),"") | G41: =IFERROR(VLOOKUP(C41,MATERIAUX!$C$3:$G$1002,5,FALSE),"") | H41: =IFERROR(ROUND(G41*(1+E41)*D41,2),"") | O41: =O40 -> 0 | P41: =(D41+D41*E41)*O41 -> 0 | Q41: =IF(P41=0,0,P41*G41) -> 0
F42: =IFERROR(VLOOKUP(C42,MATERIAUX!$C$3:$G$1002,3,FALSE),"") | G42: =IFERROR(VLOOKUP(C42,MATERIAUX!$C$3:$G$1002,5,FALSE),"") | H42: =IFERROR(ROUND(G42*(1+E42)*D42,2),"") | O42: =O41 -> 0 | P42: =(D42+D42*E42)*O42 -> 0 | Q42: =IF(P42=0,0,P42*G42) -> 0
A43: Structure PP 240-313 | B43: m2 | C43: Lemn 240x45 mm | D43: =ROUND(4.5*0.24*0.045,4) -> 0.0486 | E43: 0.1 | F43: =IFERROR(VLOOKUP(C43,MATERIAUX!$C$3:$G$1002,3,FALSE),"") -> m3 | G43: =IFERROR(VLOOKUP(C43,MATERIAUX!$C$3:$G$1002,5,FALSE),"") -> 483.50515 | H43: =IFERROR(ROUND(G43*(1+E43)*D43,2),"") -> 25.85 | I43: =SUM(H43:H52) -> 27.054426 | J43: PP Structure | K43: =ROUNDUP(2-0.313/0.625,2) -> 1.5 | L43: =IFERROR(VLOOKUP(J43,'MAIN D OEUVRE'!$A$4:$B$99,2,FALSE)*$N$2,"") -> 4.4 | M43: =IFERROR(ROUND(L43*K43,2),"") -> 6.6 | N43: =SUM(M43:M52) -> 8.47 | O43: 0 | P43: =(D43+D43*E43)*O43 -> 0 | Q43: =IF(P43=0,0,P43*G43) -> 0
C44: Cuie 90 / 120 | D44: 21 | E44: 0 | F44: =IFERROR(VLOOKUP(C44,MATERIAUX!$C$3:$G$1002,3,FALSE),"") -> u | G44: =IFERROR(VLOOKUP(C44,MATERIAUX!$C$3:$G$1002,5,FALSE),"") -> 0.039175258 | H44: =IFERROR(ROUND(G44*(1+E44)*D44,2),"") -> 0.82 | J44: Bochemit | K44: =D43*2 -> 0.0972 | L44: =IFERROR(VLOOKUP(J44,'MAIN D OEUVRE'!$A$4:$B$99,2,FALSE)*$N$2,"") -> 19.25 | M44: =IFERROR(ROUND(L44*K44,2),"") -> 1.87 | O44: =O43 -> 0 | P44: =(D44+D44*E44)*O44 -> 0 | Q44: =IF(P44=0,0,P44*G44) -> 0
C45: BOCHEMIT | D45: 1.06 | E45: 0.02 | F45: =IFERROR(VLOOKUP(C45,MATERIAUX!$C$3:$G$1002,3,FALSE),"") -> m2 | G45: =IFERROR(VLOOKUP(C45,MATERIAUX!$C$3:$G$1002,5,FALSE),"") -> 7.3154639 | H45: =IFERROR(ROUND(G45*(1+E45)*D45,2)*D43,"") -> 0.384426 | L45: =IFERROR(VLOOKUP(J45,'MAIN D OEUVRE'!$A$4:$B$99,2,FALSE)*$N$2,"") | M45: =IFERROR(ROUND(L45*K45,2),"") | O45: =O44 -> 0 | P45: =O45*D45*(D42+D43)*1.02 -> 0 | Q45: =IF(P45=0,0,P45*G45) -> 0
F46: =IFERROR(VLOOKUP(C46,MATERIAUX!$C$3:$G$1002,3,FALSE),"") | G46: =IFERROR(VLOOKUP(C46,MATERIAUX!$C$3:$G$1002,5,FALSE),"") | H46: =IFERROR(ROUND(G46*(1+E46)*D46,2),"") | L46: =IFERROR(VLOOKUP(J46,'MAIN D OEUVRE'!$A$4:$B$99,2,FALSE)*$N$2,"") | M46: =IFERROR(ROUND(L46*K46,2),"") | O46: =O45 -> 0 | P46: =(D46+D46*E46)*O46 -> 0 | Q46: =IF(P46=0,0,P46*G46) -> 0
F47: =IFERROR(VLOOKUP(C47,MATERIAUX!$C$3:$G$1002,3,FALSE),"") | G47: =IFERROR(VLOOKUP(C47,MATERIAUX!$C$3:$G$1002,5,FALSE),"") | H47: =IFERROR(ROUND(G47*(1+E47)*D47,2),"") | L47: =IFERROR(VLOOKUP(J47,'MAIN D OEUVRE'!$A$4:$B$99,2,FALSE)*$N$2,"") | M47: =IFERROR(ROUND(L47*K47,2),"") | O47: =O46 -> 0 | P47: =(D47+D47*E47)*O47 -> 0 | Q47: =IF(P47=0,0,P47*G47) -> 0
F48: =IFERROR(VLOOKUP(C48,MATERIAUX!$C$3:$G$1002,3,FALSE),"") | G48: =IFERROR(VLOOKUP(C48,MATERIAUX!$C$3:$G$1002,5,FALSE),"") | H48: =IFERROR(ROUND(G48*(1+E48)*D48,2),"") | L48: =IFERROR(VLOOKUP(J48,'MAIN D OEUVRE'!$A$4:$B$99,2,FALSE)*$N$2,"") | M48: =IFERROR(ROUND(L48*K48,2),"") | O48: =O47 -> 0 | P48: =(D48+D48*E48)*O48 -> 0 | Q48: =IF(P48=0,0,P48*G48) -> 0
F49: =IFERROR(VLOOKUP(C49,MATERIAUX!$C$3:$G$1002,3,FALSE),"") | G49: =IFERROR(VLOOKUP(C49,MATERIAUX!$C$3:$G$1002,5,FALSE),"") | H49: =IFERROR(ROUND(G49*(1+E49)*D49,2),"") | L49: =IFERROR(VLOOKUP(J49,'MAIN D OEUVRE'!$A$4:$B$99,2,FALSE)*$N$2,"") | M49: =IFERROR(ROUND(L49*K49,2),"") | O49: =O48 -> 0 | P49: =(D49+D49*E49)*O49 -> 0 | Q49: =IF(P49=0,0,P49*G49) -> 0
F50: =IFERROR(VLOOKUP(C50,MATERIAUX!$C$3:$G$1002,3,FALSE),"") | G50: =IFERROR(VLOOKUP(C50,MATERIAUX!$C$3:$G$1002,5,FALSE),"") | H50: =IFERROR(ROUND(G50*(1+E50)*D50,2),"") | L50: =IFERROR(VLOOKUP(J50,'MAIN D OEUVRE'!$A$4:$B$99,2,FALSE)*$N$2,"") | M50: =IFERROR(ROUND(L50*K50,2),"") | O50: =O49 -> 0 | P50: =(D50+D50*E50)*O50 -> 0 | Q50: =IF(P50=0,0,P50*G50) -> 0
F51: =IFERROR(VLOOKUP(C51,MATERIAUX!$C$3:$G$1002,3,FALSE),"") | G51: =IFERROR(VLOOKUP(C51,MATERIAUX!$C$3:$G$1002,5,FALSE),"") | H51: =IFERROR(ROUND(G51*(1+E51)*D51,2),"") | O51: =O50 -> 0 | P51: =(D51+D51*E51)*O51 -> 0 | Q51: =IF(P51=0,0,P51*G51) -> 0
F52: =IFERROR(VLOOKUP(C52,MATERIAUX!$C$3:$G$1002,3,FALSE),"") | G52: =IFERROR(VLOOKUP(C52,MATERIAUX!$C$3:$G$1002,5,FALSE),"") | H52: =IFERROR(ROUND(G52*(1+E52)*D52,2),"") | O52: =O51 -> 0 | P52: =(D52+D52*E52)*O52 -> 0 | Q52: =IF(P52=0,0,P52*G52) -> 0
A53: Structure PP 240-416 | B53: m2 | C53: Lemn 240x45 mm | D53: =ROUND(3.5*0.24*0.045,4) -> 0.0378 | E53: 0.1 | F53: =IFERROR(VLOOKUP(C53,MATERIAUX!$C$3:$G$1002,3,FALSE),"") -> m3 | G53: =IFERROR(VLOOKUP(C53,MATERIAUX!$C$3:$G$1002,5,FALSE),"") -> 483.50515 | H53: =IFERROR(ROUND(G53*(1+E53)*D53,2),"") -> 20.1 | I53: =SUM(H53:H62) -> 21.218998 | J53: PP Structure | K53: =ROUNDUP(2-0.416/0.625,2) -> 1.34 | L53: =IFERROR(VLOOKUP(J53,'MAIN D OEUVRE'!$A$4:$B$99,2,FALSE)*$N$2,"") -> 4.4 | M53: =IFERROR(ROUND(L53*K53,2),"") -> 5.9 | N53: =SUM(M53:M62) -> 7.36 | O53: 0 | P53: =(D53+D53*E53)*O53 -> 0 | Q53: =IF(P53=0,0,P53*G53) -> 0
C54: Cuie 90 / 120 | D54: 21 | E54: 0 | F54: =IFERROR(VLOOKUP(C54,MATERIAUX!$C$3:$G$1002,3,FALSE),"") -> u | G54: =IFERROR(VLOOKUP(C54,MATERIAUX!$C$3:$G$1002,5,FALSE),"") -> 0.039175258 | H54: =IFERROR(ROUND(G54*(1+E54)*D54,2),"") -> 0.82 | J54: Bochemit | K54: =D53*2 -> 0.0756 | L54: =IFERROR(VLOOKUP(J54,'MAIN D OEUVRE'!$A$4:$B$99,2,FALSE)*$N$2,"") -> 19.25 | M54: =IFERROR(ROUND(L54*K54,2),"") -> 1.46 | O54: =O53 -> 0 | P54: =(D54+D54*E54)*O54 -> 0 | Q54: =IF(P54=0,0,P54*G54) -> 0
C55: BOCHEMIT | D55: 1.06 | E55: 0.02 | F55: =IFERROR(VLOOKUP(C55,MATERIAUX!$C$3:$G$1002,3,FALSE),"") -> m2 | G55: =IFERROR(VLOOKUP(C55,MATERIAUX!$C$3:$G$1002,5,FALSE),"") -> 7.3154639 | H55: =IFERROR(ROUND(G55*(1+E55)*D55,2)*D53,"") -> 0.298998 | L55: =IFERROR(VLOOKUP(J55,'MAIN D OEUVRE'!$A$4:$B$99,2,FALSE)*$N$2,"") | M55: =IFERROR(ROUND(L55*K55,2),"") | O55: =O54 -> 0 | P55: =O55*D55*(D52+D53)*1.02 -> 0 | Q55: =IF(P55=0,0,P55*G55) -> 0
F56: =IFERROR(VLOOKUP(C56,MATERIAUX!$C$3:$G$1002,3,FALSE),"") | G56: =IFERROR(VLOOKUP(C56,MATERIAUX!$C$3:$G$1002,5,FALSE),"") | H56: =IFERROR(ROUND(G56*(1+E56)*D56,2),"") | L56: =IFERROR(VLOOKUP(J56,'MAIN D OEUVRE'!$A$4:$B$99,2,FALSE)*$N$2,"") | M56: =IFERROR(ROUND(L56*K56,2),"") | O56: =O55 -> 0 | P56: =(D56+D56*E56)*O56 -> 0 | Q56: =IF(P56=0,0,P56*G56) -> 0
F57: =IFERROR(VLOOKUP(C57,MATERIAUX!$C$3:$G$1002,3,FALSE),"") | G57: =IFERROR(VLOOKUP(C57,MATERIAUX!$C$3:$G$1002,5,FALSE),"") | H57: =IFERROR(ROUND(G57*(1+E57)*D57,2),"") | L57: =IFERROR(VLOOKUP(J57,'MAIN D OEUVRE'!$A$4:$B$99,2,FALSE)*$N$2,"") | M57: =IFERROR(ROUND(L57*K57,2),"") | O57: =O56 -> 0 | P57: =(D57+D57*E57)*O57 -> 0 | Q57: =IF(P57=0,0,P57*G57) -> 0
F58: =IFERROR(VLOOKUP(C58,MATERIAUX!$C$3:$G$1002,3,FALSE),"") | G58: =IFERROR(VLOOKUP(C58,MATERIAUX!$C$3:$G$1002,5,FALSE),"") | H58: =IFERROR(ROUND(G58*(1+E58)*D58,2),"") | L58: =IFERROR(VLOOKUP(J58,'MAIN D OEUVRE'!$A$4:$B$99,2,FALSE)*$N$2,"") | M58: =IFERROR(ROUND(L58*K58,2),"") | O58: =O57 -> 0 | P58: =(D58+D58*E58)*O58 -> 0 | Q58: =IF(P58=0,0,P58*G58) -> 0
F59: =IFERROR(VLOOKUP(C59,MATERIAUX!$C$3:$G$1002,3,FALSE),"") | G59: =IFERROR(VLOOKUP(C59,MATERIAUX!$C$3:$G$1002,5,FALSE),"") | H59: =IFERROR(ROUND(G59*(1+E59)*D59,2),"") | L59: =IFERROR(VLOOKUP(J59,'MAIN D OEUVRE'!$A$4:$B$99,2,FALSE)*$N$2,"") | M59: =IFERROR(ROUND(L59*K59,2),"") | O59: =O58 -> 0 | P59: =(D59+D59*E59)*O59 -> 0 | Q59: =IF(P59=0,0,P59*G59) -> 0
F60: =IFERROR(VLOOKUP(C60,MATERIAUX!$C$3:$G$1002,3,FALSE),"") | G60: =IFERROR(VLOOKUP(C60,MATERIAUX!$C$3:$G$1002,5,FALSE),"") | H60: =IFERROR(ROUND(G60*(1+E60)*D60,2),"") | L60: =IFERROR(VLOOKUP(J60,'MAIN D OEUVRE'!$A$4:$B$99,2,FALSE)*$N$2,"") | M60: =IFERROR(ROUND(L60*K60,2),"") | O60: =O59 -> 0 | P60: =(D60+D60*E60)*O60 -> 0 | Q60: =IF(P60=0,0,P60*G60) -> 0
F61: =IFERROR(VLOOKUP(C61,MATERIAUX!$C$3:$G$1002,3,FALSE),"") | G61: =IFERROR(VLOOKUP(C61,MATERIAUX!$C$3:$G$1002,5,FALSE),"") | H61: =IFERROR(ROUND(G61*(1+E61)*D61,2),"") | O61: =O60 -> 0 | P61: =(D61+D61*E61)*O61 -> 0 | Q61: =IF(P61=0,0,P61*G61) -> 0
F62: =IFERROR(VLOOKUP(C62,MATERIAUX!$C$3:$G$1002,3,FALSE),"") | G62: =IFERROR(VLOOKUP(C62,MATERIAUX!$C$3:$G$1002,5,FALSE),"") | H62: =IFERROR(ROUND(G62*(1+E62)*D62,2),"") | O62: =O61 -> 0 | P62: =(D62+D62*E62)*O62 -> 0 | Q62: =IF(P62=0,0,P62*G62) -> 0
A63: Structure PP 240-625 | B63: m2 | C63: Lemn 240x45 mm | D63: =ROUND(3*0.24*0.045,4) -> 0.0324 | E63: 0.1 | F63: =IFERROR(VLOOKUP(C63,MATERIAUX!$C$3:$G$1002,3,FALSE),"") -> m3 | G63: =IFERROR(VLOOKUP(C63,MATERIAUX!$C$3:$G$1002,5,FALSE),"") -> 483.50515 | H63: =IFERROR(ROUND(G63*(1+E63)*D63,2),"") -> 17.23 | I63: =SUM(H63:H72) -> 18.306284 | J63: PP Structure | K63: =ROUNDUP(2-0.625/0.625,2) -> 1 | L63: =IFERROR(VLOOKUP(J63,'MAIN D OEUVRE'!$A$4:$B$99,2,FALSE)*$N$2,"") -> 4.4 | M63: =IFERROR(ROUND(L63*K63,2),"") -> 4.4 | N63: =SUM(M63:M72) -> 5.65 | O63: 0 | P63: =(D63+D63*E63)*O63 -> 0 | Q63: =IF(P63=0,0,P63*G63) -> 0
C64: Cuie 90 / 120 | D64: 21 | E64: 0 | F64: =IFERROR(VLOOKUP(C64,MATERIAUX!$C$3:$G$1002,3,FALSE),"") -> u | G64: =IFERROR(VLOOKUP(C64,MATERIAUX!$C$3:$G$1002,5,FALSE),"") -> 0.039175258 | H64: =IFERROR(ROUND(G64*(1+E64)*D64,2),"") -> 0.82 | J64: Bochemit | K64: =D63*2 -> 0.0648 | L64: =IFERROR(VLOOKUP(J64,'MAIN D OEUVRE'!$A$4:$B$99,2,FALSE)*$N$2,"") -> 19.25 | M64: =IFERROR(ROUND(L64*K64,2),"") -> 1.25 | O64: =O63 -> 0 | P64: =(D64+D64*E64)*O64 -> 0 | Q64: =IF(P64=0,0,P64*G64) -> 0
C65: BOCHEMIT | D65: 1.06 | E65: 0.02 | F65: =IFERROR(VLOOKUP(C65,MATERIAUX!$C$3:$G$1002,3,FALSE),"") -> m2 | G65: =IFERROR(VLOOKUP(C65,MATERIAUX!$C$3:$G$1002,5,FALSE),"") -> 7.3154639 | H65: =IFERROR(ROUND(G65*(1+E65)*D65,2)*D63,"") -> 0.256284 | L65: =IFERROR(VLOOKUP(J65,'MAIN D OEUVRE'!$A$4:$B$99,2,FALSE)*$N$2,"") | M65: =IFERROR(ROUND(L65*K65,2),"") | O65: =O64 -> 0 | P65: =O65*D65*(D62+D63)*1.02 -> 0 | Q65: =IF(P65=0,0,P65*G65) -> 0
F66: =IFERROR(VLOOKUP(C66,MATERIAUX!$C$3:$G$1002,3,FALSE),"") | G66: =IFERROR(VLOOKUP(C66,MATERIAUX!$C$3:$G$1002,5,FALSE),"") | H66: =IFERROR(ROUND(G66*(1+E66)*D66,2),"") | L66: =IFERROR(VLOOKUP(J66,'MAIN D OEUVRE'!$A$4:$B$99,2,FALSE)*$N$2,"") | M66: =IFERROR(ROUND(L66*K66,2),"") | O66: =O65 -> 0 | P66: =(D66+D66*E66)*O66 -> 0 | Q66: =IF(P66=0,0,P66*G66) -> 0
F67: =IFERROR(VLOOKUP(C67,MATERIAUX!$C$3:$G$1002,3,FALSE),"") | G67: =IFERROR(VLOOKUP(C67,MATERIAUX!$C$3:$G$1002,5,FALSE),"") | H67: =IFERROR(ROUND(G67*(1+E67)*D67,2),"") | L67: =IFERROR(VLOOKUP(J67,'MAIN D OEUVRE'!$A$4:$B$99,2,FALSE)*$N$2,"") | M67: =IFERROR(ROUND(L67*K67,2),"") | O67: =O66 -> 0 | P67: =(D67+D67*E67)*O67 -> 0 | Q67: =IF(P67=0,0,P67*G67) -> 0
F68: =IFERROR(VLOOKUP(C68,MATERIAUX!$C$3:$G$1002,3,FALSE),"") | G68: =IFERROR(VLOOKUP(C68,MATERIAUX!$C$3:$G$1002,5,FALSE),"") | H68: =IFERROR(ROUND(G68*(1+E68)*D68,2),"") | L68: =IFERROR(VLOOKUP(J68,'MAIN D OEUVRE'!$A$4:$B$99,2,FALSE)*$N$2,"") | M68: =IFERROR(ROUND(L68*K68,2),"") | O68: =O67 -> 0 | P68: =(D68+D68*E68)*O68 -> 0 | Q68: =IF(P68=0,0,P68*G68) -> 0
F69: =IFERROR(VLOOKUP(C69,MATERIAUX!$C$3:$G$1002,3,FALSE),"") | G69: =IFERROR(VLOOKUP(C69,MATERIAUX!$C$3:$G$1002,5,FALSE),"") | H69: =IFERROR(ROUND(G69*(1+E69)*D69,2),"") | L69: =IFERROR(VLOOKUP(J69,'MAIN D OEUVRE'!$A$4:$B$99,2,FALSE)*$N$2,"") | M69: =IFERROR(ROUND(L69*K69,2),"") | O69: =O68 -> 0 | P69: =(D69+D69*E69)*O69 -> 0 | Q69: =IF(P69=0,0,P69*G69) -> 0
F70: =IFERROR(VLOOKUP(C70,MATERIAUX!$C$3:$G$1002,3,FALSE),"") | G70: =IFERROR(VLOOKUP(C70,MATERIAUX!$C$3:$G$1002,5,FALSE),"") | H70: =IFERROR(ROUND(G70*(1+E70)*D70,2),"") | L70: =IFERROR(VLOOKUP(J70,'MAIN D OEUVRE'!$A$4:$B$99,2,FALSE)*$N$2,"") | M70: =IFERROR(ROUND(L70*K70,2),"") | O70: =O69 -> 0 | P70: =(D70+D70*E70)*O70 -> 0 | Q70: =IF(P70=0,0,P70*G70) -> 0
F71: =IFERROR(VLOOKUP(C71,MATERIAUX!$C$3:$G$1002,3,FALSE),"") | G71: =IFERROR(VLOOKUP(C71,MATERIAUX!$C$3:$G$1002,5,FALSE),"") | H71: =IFERROR(ROUND(G71*(1+E71)*D71,2),"") | O71: =O70 -> 0 | P71: =(D71+D71*E71)*O71 -> 0 | Q71: =IF(P71=0,0,P71*G71) -> 0
F72: =IFERROR(VLOOKUP(C72,MATERIAUX!$C$3:$G$1002,3,FALSE),"") | G72: =IFERROR(VLOOKUP(C72,MATERIAUX!$C$3:$G$1002,5,FALSE),"") | H72: =IFERROR(ROUND(G72*(1+E72)*D72,2),"") | O72: =O71 -> 0 | P72: =(D72+D72*E72)*O72 -> 0 | Q72: =IF(P72=0,0,P72*G72) -> 0
A73: Structure PP 260-250 | B73: m2 | C73: Lemn 260x45 mm | D73: =ROUND(5*0.26*0.045,4) -> 0.0585 | E73: 0.1 | F73: =IFERROR(VLOOKUP(C73,MATERIAUX!$C$3:$G$1002,3,FALSE),"") -> m3 | G73: =IFERROR(VLOOKUP(C73,MATERIAUX!$C$3:$G$1002,5,FALSE),"") -> 483.50515 | H73: =IFERROR(ROUND(G73*(1+E73)*D73,2),"") -> 31.11 | I73: =SUM(H73:H82) -> 32.392735 | J73: PP Structure | K73: =ROUNDUP(2-0.25/0.625,2) -> 1.6 | L73: =IFERROR(VLOOKUP(J73,'MAIN D OEUVRE'!$A$4:$B$99,2,FALSE)*$N$2,"") -> 4.4 | M73: =IFERROR(ROUND(L73*K73,2),"") -> 7.04 | N73: =SUM(M73:M82) -> 9.29 | O73: 0 | P73: =(D73+D73*E73)*O73 -> 0 | Q73: =IF(P73=0,0,P73*G73) -> 0
C74: Cuie 90 / 120 | D74: 21 | E74: 0 | F74: =IFERROR(VLOOKUP(C74,MATERIAUX!$C$3:$G$1002,3,FALSE),"") -> u | G74: =IFERROR(VLOOKUP(C74,MATERIAUX!$C$3:$G$1002,5,FALSE),"") -> 0.039175258 | H74: =IFERROR(ROUND(G74*(1+E74)*D74,2),"") -> 0.82 | J74: Bochemit | K74: =D73*2 -> 0.117 | L74: =IFERROR(VLOOKUP(J74,'MAIN D OEUVRE'!$A$4:$B$99,2,FALSE)*$N$2,"") -> 19.25 | M74: =IFERROR(ROUND(L74*K74,2),"") -> 2.25 | O74: =O73 -> 0 | P74: =(D74+D74*E74)*O74 -> 0 | Q74: =IF(P74=0,0,P74*G74) -> 0
C75: BOCHEMIT | D75: 1.06 | E75: 0.02 | F75: =IFERROR(VLOOKUP(C75,MATERIAUX!$C$3:$G$1002,3,FALSE),"") -> m2 | G75: =IFERROR(VLOOKUP(C75,MATERIAUX!$C$3:$G$1002,5,FALSE),"") -> 7.3154639 | H75: =IFERROR(ROUND(G75*(1+E75)*D75,2)*D73,"") -> 0.462735 | L75: =IFERROR(VLOOKUP(J75,'MAIN D OEUVRE'!$A$4:$B$99,2,FALSE)*$N$2,"") | M75: =IFERROR(ROUND(L75*K75,2),"") | O75: =O74 -> 0 | P75: =O75*D75*(D72+D73)*1.02 -> 0 | Q75: =IF(P75=0,0,P75*G75) -> 0
F76: =IFERROR(VLOOKUP(C76,MATERIAUX!$C$3:$G$1002,3,FALSE),"") | G76: =IFERROR(VLOOKUP(C76,MATERIAUX!$C$3:$G$1002,5,FALSE),"") | H76: =IFERROR(ROUND(G76*(1+E76)*D76,2),"") | L76: =IFERROR(VLOOKUP(J76,'MAIN D OEUVRE'!$A$4:$B$99,2,FALSE)*$N$2,"") | M76: =IFERROR(ROUND(L76*K76,2),"") | O76: =O75 -> 0 | P76: =(D76+D76*E76)*O76 -> 0 | Q76: =IF(P76=0,0,P76*G76) -> 0
F77: =IFERROR(VLOOKUP(C77,MATERIAUX!$C$3:$G$1002,3,FALSE),"") | G77: =IFERROR(VLOOKUP(C77,MATERIAUX!$C$3:$G$1002,5,FALSE),"") | H77: =IFERROR(ROUND(G77*(1+E77)*D77,2),"") | L77: =IFERROR(VLOOKUP(J77,'MAIN D OEUVRE'!$A$4:$B$99,2,FALSE)*$N$2,"") | M77: =IFERROR(ROUND(L77*K77,2),"") | O77: =O76 -> 0 | P77: =(D77+D77*E77)*O77 -> 0 | Q77: =IF(P77=0,0,P77*G77) -> 0
F78: =IFERROR(VLOOKUP(C78,MATERIAUX!$C$3:$G$1002,3,FALSE),"") | G78: =IFERROR(VLOOKUP(C78,MATERIAUX!$C$3:$G$1002,5,FALSE),"") | H78: =IFERROR(ROUND(G78*(1+E78)*D78,2),"") | L78: =IFERROR(VLOOKUP(J78,'MAIN D OEUVRE'!$A$4:$B$99,2,FALSE)*$N$2,"") | M78: =IFERROR(ROUND(L78*K78,2),"") | O78: =O77 -> 0 | P78: =(D78+D78*E78)*O78 -> 0 | Q78: =IF(P78=0,0,P78*G78) -> 0
F79: =IFERROR(VLOOKUP(C79,MATERIAUX!$C$3:$G$1002,3,FALSE),"") | G79: =IFERROR(VLOOKUP(C79,MATERIAUX!$C$3:$G$1002,5,FALSE),"") | H79: =IFERROR(ROUND(G79*(1+E79)*D79,2),"") | L79: =IFERROR(VLOOKUP(J79,'MAIN D OEUVRE'!$A$4:$B$99,2,FALSE)*$N$2,"") | M79: =IFERROR(ROUND(L79*K79,2),"") | O79: =O78 -> 0 | P79: =(D79+D79*E79)*O79 -> 0 | Q79: =IF(P79=0,0,P79*G79) -> 0
F80: =IFERROR(VLOOKUP(C80,MATERIAUX!$C$3:$G$1002,3,FALSE),"") | G80: =IFERROR(VLOOKUP(C80,MATERIAUX!$C$3:$G$1002,5,FALSE),"") | H80: =IFERROR(ROUND(G80*(1+E80)*D80,2),"") | L80: =IFERROR(VLOOKUP(J80,'MAIN D OEUVRE'!$A$4:$B$99,2,FALSE)*$N$2,"") | M80: =IFERROR(ROUND(L80*K80,2),"") | O80: =O79 -> 0 | P80: =(D80+D80*E80)*O80 -> 0 | Q80: =IF(P80=0,0,P80*G80) -> 0
F81: =IFERROR(VLOOKUP(C81,MATERIAUX!$C$3:$G$1002,3,FALSE),"") | G81: =IFERROR(VLOOKUP(C81,MATERIAUX!$C$3:$G$1002,5,FALSE),"") | H81: =IFERROR(ROUND(G81*(1+E81)*D81,2),"") | O81: =O80 -> 0 | P81: =(D81+D81*E81)*O81 -> 0 | Q81: =IF(P81=0,0,P81*G81) -> 0
F82: =IFERROR(VLOOKUP(C82,MATERIAUX!$C$3:$G$1002,3,FALSE),"") | G82: =IFERROR(VLOOKUP(C82,MATERIAUX!$C$3:$G$1002,5,FALSE),"") | H82: =IFERROR(ROUND(G82*(1+E82)*D82,2),"") | O82: =O81 -> 0 | P82: =(D82+D82*E82)*O82 -> 0 | Q82: =IF(P82=0,0,P82*G82) -> 0
A83: Structure PP 260-313 | B83: m2 | C83: Lemn 260x45 mm | D83: =ROUND(5.8*0.26*0.045,4) -> 0.0679 | E83: 0.1 | F83: =IFERROR(VLOOKUP(C83,MATERIAUX!$C$3:$G$1002,3,FALSE),"") -> m3 | G83: =IFERROR(VLOOKUP(C83,MATERIAUX!$C$3:$G$1002,5,FALSE),"") -> 483.50515 | H83: =IFERROR(ROUND(G83*(1+E83)*D83,2),"") -> 36.11 | I83: =SUM(H83:H92) -> 37.467089 | J83: PP Structure | K83: =ROUNDUP(2-0.313/0.625,2) -> 1.5 | L83: =IFERROR(VLOOKUP(J83,'MAIN D OEUVRE'!$A$4:$B$99,2,FALSE)*$N$2,"") -> 4.4 | M83: =IFERROR(ROUND(L83*K83,2),"") -> 6.6 | N83: =SUM(M83:M92) -> 9.21 | O83: 0 | P83: =(D83+D83*E83)*O83 -> 0 | Q83: =IF(P83=0,0,P83*G83) -> 0
C84: Cuie 90 / 120 | D84: 21 | E84: 0 | F84: =IFERROR(VLOOKUP(C84,MATERIAUX!$C$3:$G$1002,3,FALSE),"") -> u | G84: =IFERROR(VLOOKUP(C84,MATERIAUX!$C$3:$G$1002,5,FALSE),"") -> 0.039175258 | H84: =IFERROR(ROUND(G84*(1+E84)*D84,2),"") -> 0.82 | J84: Bochemit | K84: =D83*2 -> 0.1358 | L84: =IFERROR(VLOOKUP(J84,'MAIN D OEUVRE'!$A$4:$B$99,2,FALSE)*$N$2,"") -> 19.25 | M84: =IFERROR(ROUND(L84*K84,2),"") -> 2.61 | O84: =O83 -> 0 | P84: =(D84+D84*E84)*O84 -> 0 | Q84: =IF(P84=0,0,P84*G84) -> 0
C85: BOCHEMIT | D85: 1.06 | E85: 0.02 | F85: =IFERROR(VLOOKUP(C85,MATERIAUX!$C$3:$G$1002,3,FALSE),"") -> m2 | G85: =IFERROR(VLOOKUP(C85,MATERIAUX!$C$3:$G$1002,5,FALSE),"") -> 7.3154639 | H85: =IFERROR(ROUND(G85*(1+E85)*D85,2)*D83,"") -> 0.537089 | L85: =IFERROR(VLOOKUP(J85,'MAIN D OEUVRE'!$A$4:$B$99,2,FALSE)*$N$2,"") | M85: =IFERROR(ROUND(L85*K85,2),"") | O85: =O84 -> 0 | P85: =O85*D85*(D82+D83)*1.02 -> 0 | Q85: =IF(P85=0,0,P85*G85) -> 0
F86: =IFERROR(VLOOKUP(C86,MATERIAUX!$C$3:$G$1002,3,FALSE),"") | G86: =IFERROR(VLOOKUP(C86,MATERIAUX!$C$3:$G$1002,5,FALSE),"") | H86: =IFERROR(ROUND(G86*(1+E86)*D86,2),"") | L86: =IFERROR(VLOOKUP(J86,'MAIN D OEUVRE'!$A$4:$B$99,2,FALSE)*$N$2,"") | M86: =IFERROR(ROUND(L86*K86,2),"") | O86: =O85 -> 0 | P86: =(D86+D86*E86)*O86 -> 0 | Q86: =IF(P86=0,0,P86*G86) -> 0
F87: =IFERROR(VLOOKUP(C87,MATERIAUX!$C$3:$G$1002,3,FALSE),"") | G87: =IFERROR(VLOOKUP(C87,MATERIAUX!$C$3:$G$1002,5,FALSE),"") | H87: =IFERROR(ROUND(G87*(1+E87)*D87,2),"") | L87: =IFERROR(VLOOKUP(J87,'MAIN D OEUVRE'!$A$4:$B$99,2,FALSE)*$N$2,"") | M87: =IFERROR(ROUND(L87*K87,2),"") | O87: =O86 -> 0 | P87: =(D87+D87*E87)*O87 -> 0 | Q87: =IF(P87=0,0,P87*G87) -> 0
F88: =IFERROR(VLOOKUP(C88,MATERIAUX!$C$3:$G$1002,3,FALSE),"") | G88: =IFERROR(VLOOKUP(C88,MATERIAUX!$C$3:$G$1002,5,FALSE),"") | H88: =IFERROR(ROUND(G88*(1+E88)*D88,2),"") | L88: =IFERROR(VLOOKUP(J88,'MAIN D OEUVRE'!$A$4:$B$99,2,FALSE)*$N$2,"") | M88: =IFERROR(ROUND(L88*K88,2),"") | O88: =O87 -> 0 | P88: =(D88+D88*E88)*O88 -> 0 | Q88: =IF(P88=0,0,P88*G88) -> 0
F89: =IFERROR(VLOOKUP(C89,MATERIAUX!$C$3:$G$1002,3,FALSE),"") | G89: =IFERROR(VLOOKUP(C89,MATERIAUX!$C$3:$G$1002,5,FALSE),"") | H89: =IFERROR(ROUND(G89*(1+E89)*D89,2),"") | L89: =IFERROR(VLOOKUP(J89,'MAIN D OEUVRE'!$A$4:$B$99,2,FALSE)*$N$2,"") | M89: =IFERROR(ROUND(L89*K89,2),"") | O89: =O88 -> 0 | P89: =(D89+D89*E89)*O89 -> 0 | Q89: =IF(P89=0,0,P89*G89) -> 0
F90: =IFERROR(VLOOKUP(C90,MATERIAUX!$C$3:$G$1002,3,FALSE),"") | G90: =IFERROR(VLOOKUP(C90,MATERIAUX!$C$3:$G$1002,5,FALSE),"") | H90: =IFERROR(ROUND(G90*(1+E90)*D90,2),"") | L90: =IFERROR(VLOOKUP(J90,'MAIN D OEUVRE'!$A$4:$B$99,2,FALSE)*$N$2,"") | M90: =IFERROR(ROUND(L90*K90,2),"") | O90: =O89 -> 0 | P90: =(D90+D90*E90)*O90 -> 0 | Q90: =IF(P90=0,0,P90*G90) -> 0
F91: =IFERROR(VLOOKUP(C91,MATERIAUX!$C$3:$G$1002,3,FALSE),"") | G91: =IFERROR(VLOOKUP(C91,MATERIAUX!$C$3:$G$1002,5,FALSE),"") | H91: =IFERROR(ROUND(G91*(1+E91)*D91,2),"") | O91: =O90 -> 0 | P91: =(D91+D91*E91)*O91 -> 0 | Q91: =IF(P91=0,0,P91*G91) -> 0
F92: =IFERROR(VLOOKUP(C92,MATERIAUX!$C$3:$G$1002,3,FALSE),"") | G92: =IFERROR(VLOOKUP(C92,MATERIAUX!$C$3:$G$1002,5,FALSE),"") | H92: =IFERROR(ROUND(G92*(1+E92)*D92,2),"") | O92: =O91 -> 0 | P92: =(D92+D92*E92)*O92 -> 0 | Q92: =IF(P92=0,0,P92*G92) -> 0
A93: Structure PP 260-416 | B93: m2 | C93: Lemn 260x45 mm | D93: =ROUND(4.9*0.26*0.045,4) -> 0.0573 | E93: 0.1 | F93: =IFERROR(VLOOKUP(C93,MATERIAUX!$C$3:$G$1002,3,FALSE),"") -> m3 | G93: =IFERROR(VLOOKUP(C93,MATERIAUX!$C$3:$G$1002,5,FALSE),"") -> 483.50515 | H93: =IFERROR(ROUND(G93*(1+E93)*D93,2),"") -> 30.48 | I93: =SUM(H93:H102) -> 31.753243 | J93: PP Structure | K93: =ROUNDUP(2-0.416/0.625,2) -> 1.34 | L93: =IFERROR(VLOOKUP(J93,'MAIN D OEUVRE'!$A$4:$B$99,2,FALSE)*$N$2,"") -> 4.4 | M93: =IFERROR(ROUND(L93*K93,2),"") -> 5.9 | N93: =SUM(M93:M102) -> 8.11 | O93: 0 | P93: =(D93+D93*E93)*O93 -> 0 | Q93: =IF(P93=0,0,P93*G93) -> 0
C94: Cuie 90 / 120 | D94: 21 | E94: 0 | F94: =IFERROR(VLOOKUP(C94,MATERIAUX!$C$3:$G$1002,3,FALSE),"") -> u | G94: =IFERROR(VLOOKUP(C94,MATERIAUX!$C$3:$G$1002,5,FALSE),"") -> 0.039175258 | H94: =IFERROR(ROUND(G94*(1+E94)*D94,2),"") -> 0.82 | J94: Bochemit | K94: =D93*2 -> 0.1146 | L94: =IFERROR(VLOOKUP(J94,'MAIN D OEUVRE'!$A$4:$B$99,2,FALSE)*$N$2,"") -> 19.25 | M94: =IFERROR(ROUND(L94*K94,2),"") -> 2.21 | O94: =O93 -> 0 | P94: =(D94+D94*E94)*O94 -> 0 | Q94: =IF(P94=0,0,P94*G94) -> 0
C95: BOCHEMIT | D95: 1.06 | E95: 0.02 | F95: =IFERROR(VLOOKUP(C95,MATERIAUX!$C$3:$G$1002,3,FALSE),"") -> m2 | G95: =IFERROR(VLOOKUP(C95,MATERIAUX!$C$3:$G$1002,5,FALSE),"") -> 7.3154639 | H95: =IFERROR(ROUND(G95*(1+E95)*D95,2)*D93,"") -> 0.453243 | L95: =IFERROR(VLOOKUP(J95,'MAIN D OEUVRE'!$A$4:$B$99,2,FALSE)*$N$2,"") | M95: =IFERROR(ROUND(L95*K95,2),"") | O95: =O94 -> 0 | P95: =O95*D95*(D92+D93)*1.02 -> 0 | Q95: =IF(P95=0,0,P95*G95) -> 0
F96: =IFERROR(VLOOKUP(C96,MATERIAUX!$C$3:$G$1002,3,FALSE),"") | G96: =IFERROR(VLOOKUP(C96,MATERIAUX!$C$3:$G$1002,5,FALSE),"") | H96: =IFERROR(ROUND(G96*(1+E96)*D96,2),"") | L96: =IFERROR(VLOOKUP(J96,'MAIN D OEUVRE'!$A$4:$B$99,2,FALSE)*$N$2,"") | M96: =IFERROR(ROUND(L96*K96,2),"") | O96: =O95 -> 0 | P96: =(D96+D96*E96)*O96 -> 0 | Q96: =IF(P96=0,0,P96*G96) -> 0
F97: =IFERROR(VLOOKUP(C97,MATERIAUX!$C$3:$G$1002,3,FALSE),"") | G97: =IFERROR(VLOOKUP(C97,MATERIAUX!$C$3:$G$1002,5,FALSE),"") | H97: =IFERROR(ROUND(G97*(1+E97)*D97,2),"") | L97: =IFERROR(VLOOKUP(J97,'MAIN D OEUVRE'!$A$4:$B$99,2,FALSE)*$N$2,"") | M97: =IFERROR(ROUND(L97*K97,2),"") | O97: =O96 -> 0 | P97: =(D97+D97*E97)*O97 -> 0 | Q97: =IF(P97=0,0,P97*G97) -> 0
F98: =IFERROR(VLOOKUP(C98,MATERIAUX!$C$3:$G$1002,3,FALSE),"") | G98: =IFERROR(VLOOKUP(C98,MATERIAUX!$C$3:$G$1002,5,FALSE),"") | H98: =IFERROR(ROUND(G98*(1+E98)*D98,2),"") | L98: =IFERROR(VLOOKUP(J98,'MAIN D OEUVRE'!$A$4:$B$99,2,FALSE)*$N$2,"") | M98: =IFERROR(ROUND(L98*K98,2),"") | O98: =O97 -> 0 | P98: =(D98+D98*E98)*O98 -> 0 | Q98: =IF(P98=0,0,P98*G98) -> 0
F99: =IFERROR(VLOOKUP(C99,MATERIAUX!$C$3:$G$1002,3,FALSE),"") | G99: =IFERROR(VLOOKUP(C99,MATERIAUX!$C$3:$G$1002,5,FALSE),"") | H99: =IFERROR(ROUND(G99*(1+E99)*D99,2),"") | L99: =IFERROR(VLOOKUP(J99,'MAIN D OEUVRE'!$A$4:$B$99,2,FALSE)*$N$2,"") | M99: =IFERROR(ROUND(L99*K99,2),"") | O99: =O98 -> 0 | P99: =(D99+D99*E99)*O99 -> 0 | Q99: =IF(P99=0,0,P99*G99) -> 0
F100: =IFERROR(VLOOKUP(C100,MATERIAUX!$C$3:$G$1002,3,FALSE),"") | G100: =IFERROR(VLOOKUP(C100,MATERIAUX!$C$3:$G$1002,5,FALSE),"") | H100: =IFERROR(ROUND(G100*(1+E100)*D100,2),"") | L100: =IFERROR(VLOOKUP(J100,'MAIN D OEUVRE'!$A$4:$B$99,2,FALSE)*$N$2,"") | M100: =IFERROR(ROUND(L100*K100,2),"") | O100: =O99 -> 0 | P100: =(D100+D100*E100)*O100 -> 0 | Q100: =IF(P100=0,0,P100*G100) -> 0
...

Sheet MATERIAUX
C1: =TODAY() -> 45993 | D1: ID | H1: 44851 | O1: 44719 | P1: ID | U1: 44690 | V1: ID | AA1: 44641 | AB1: ID | AG1: 44484 | AL1: 44363 | AN1: ="001" -> 001 | AQ1: 44354
A2: Liste déroulante | B2: DESCIPTION | C2: MATERIAUX | E2: U | F2: =GESTION!B5 -> 0.2 | G2: =GESTION!$B$7 -> 4.85 | H2: → Lei | I2: Transf in mp | J2: U | K2: =GESTION!$B$8 -> 0.20618557 | L2: Lei | N2: Variations | O2: MATERIAUX | Q2: U | R2: =GESTION!N5 -> 0 | S2: =GESTION!$B$7 -> 4.85 | T2: → Lei | U2: MATERIAUX | W2: U | X2: 4.91 | Y2: → Lei | Z2: Variations | AA2: MATERIAUX | AC2: U | AD2: 4.9444081 | AE2: → Lei | AF2: Variations | AG2: MATERIAUX | AH2: U | AI2: 4.9273348 | AJ2: → Lei | AK2: Variations | AL2: MATERIAUX | AM2: U | AN2: 4.95 | AO2: → Lei | AP2: Variations | AQ2: MATERIAUX | AR2: U | AS2: 4.95 | AT2: → Lei
A3: {=_xlfn.UNIQUE(_xlfn._xlws.FILTER(C3:C1100,NOT(ISBLANK(C3:C1100))))} -> adeziv | B3: Colle | C3: adeziv | E3: kg | F3: =IF(E3="","",ROUND(G3*(1+$F$2),2)) -> 0.25 | G3: =H3/$G$2 -> 0.20618557 | H3: 1 | I3: =1/25 -> 0.04 | J3: kg | K3: =L3*K2 -> 14.226804 | L3: =23*3 -> 69 | N3: =(H3-T3)/Y3 -> 0.13636364 | O3: adeziv | Q3: kg | R3: =IF(Q3="","",ROUND(S3*(1+$F$2),2)) -> 0.22 | S3: =T3/$G$2 -> 0.1814433 | T3: 0.88 | U3: adeziv | W3: kg | X3: 0.17922607 | Y3: 0.88 | Z3: =(Y3-AE3)/AE3 -> -0.68115942 | AA3: adeziv | AC3: kg | AD3: 0.55820635 | AE3: 2.76 | AF3: =(AE3-AJ3)/AJ3 -> 0 | AG3: adeziv | AH3: kg | AI3: 0.56014054 | AJ3: 2.76 | AK3: =(AJ3-AO3)/AO3 -> 0.0036363636 | AL3: adeziv | AM3: kg | AN3: 0.55555556 | AO3: 2.75 | AP3: =(AO3-AT3)/AT3 -> 0 | AQ3: adeziv | AR3: kg | AS3: 0.55555556 | AT3: 2.75
A4: Adeziv imbinare | B4: Platre | C4: Adeziv imbinare | E4: l | F4: =IF(E4="","",ROUND(G4*(1+$F$2),2)) -> 10.58 | G4: =H4/$G$2 -> 8.8206186 | H4: 42.78 | I4: 1 | J4: l | K4: =L4*K2 -> 8.8206186 | L4: 42.78 | N4: =(H4-T4)/T4 -> 0 | O4: Adeziv imbinare | Q4: l | R4: =IF(Q4="","",ROUND(S4*(1+$F$2),2)) -> 10.58 | S4: =T4/$G$2 -> 8.8206186 | T4: 42.78 | U4: Adeziv imbinare | W4: l | X4: 8.712831 | Y4: 42.78 | Z4: =(Y4-AE4)/AE4 -> 0 | AA4: Adeziv imbinare | AC4: l | AD4: 8.6521984 | AE4: 42.78 | AF4: =(AE4-AJ4)/AJ4 -> 0 | AG4: Adeziv imbinare | AH4: l | AI4: 8.6821784 | AJ4: 42.78 | AK4: =(AJ4-AO4)/AO4 -> -0.060606061 | AL4: Adeziv imbinare | AM4: l | AN4: 9.2 | AO4: 45.54 | AP4: =(AO4-AT4)/AT4 -> 0 | AQ4: Adeziv imbinare | AR4: l | AS4: 9.2 | AT4: 45.54
A5: Amorsa | B5: Sous enduit Maité | C5: Amorsa | E5: l | F5: =IF(E5="","",ROUND(G5*(1+$F$2),2)) -> 0.08 | G5: =H5/$G$2 -> 0.068041237 | H5: 0.33 | N5: =(H5-T5)/T5 -> 0 | O5: Amorsa | Q5: l | R5: =IF(Q5="","",ROUND(S5*(1+$F$2),2)) -> 0.08 | S5: =T5/$G$2 -> 0.068041237 | T5: 0.33 | U5: Amorsa | W5: l | X5: 0.67209776 | Y5: 3.3 | Z5: =(Y5-AE5)/AE5 -> -0.484375 | AA5: Amorsa | AC5: l | AD5: 1.2943915 | AE5: 6.4 | AF5: =(AE5-AJ5)/AJ5 -> 0 | AG5: Amorsa | AH5: l | AI5: 1.2988766 | AJ5: 6.4 | AK5: =(AJ5-AO5)/AO5 -> -1.3877788e-16 | AL5: Amorsa | AM5: l | AN5: 1.2929293 | AO5: 6.4 | AP5: =(AO5-AT5)/AT5 -> 0 | AQ5: Amorsa | AR5: l | AS5: 1.2929293 | AT5: 6.4
A6: Banda imbinare | B6: Bande de joint | C6: Banda imbinare | E6: ml | F6: =IF(E6="","",ROUND(G6*(1+$F$2),2)) -> 1.94 | G6: =H6/$G$2 -> 1.6199258 | H6: 7.85664 | N6: =(H6-T6)/T6 -> 0 | O6: Banda imbinare | Q6: ml | R6: =IF(Q6="","",ROUND(S6*(1+$F$2),2)) -> 1.94 | S6: =T6/$G$2 -> 1.6199258 | T6: 7.85664 | U6: Banda imbinare | W6: ml | X6: 1.6001303 | Y6: 7.85664 | Z6: =(Y6-AE6)/AE6 -> 0 | AA6: Banda imbinare | AC6: ml | AD6: 1.5889951 | AE6: 7.85664 | AF6: =(AE6-AJ6)/AJ6 -> 0 | AG6: Banda imbinare | AH6: ml | AI6: 1.5945009 | AJ6: 7.85664 | AK6: =(AJ6-AO6)/AO6 -> -0.00042748092 | AL6: Banda imbinare | AM6: ml | AN6: 1.5872 | AO6: 7.86 | AP6: =(AO6-AT6)/AT6 -> 0 | AQ6: Banda imbinare | AR6: ml | AS6: 1.5872 | AT6: 7.86
A7: Capse folie 10 mm | B7: Agrafe 10 mm | C7: Capse folie 10 mm | E7: u | F7: =IF(E7="","",ROUND(G7*(1+$F$2),2)) -> 0.02 | G7: =H7/$G$2 -> 0.01443299 | H7: 0.07 | L7: 0.04 | N7: =(H7-T7)/T7 -> 16.5 | O7: Capse folie 10 mm | Q7: u | R7: =IF(Q7="","",ROUND(S7*(1+$F$2),2)) -> 0 | S7: =T7/$G$2 -> 0.00082474227 | T7: 0.004 | U7: Capse folie 10 mm | W7: u | X7: 0.00081466395 | Y7: 0.004 | Z7: =(Y7-AE7)/AE7 -> -0.9 | AA7: Capse folie 10 mm | AC7: u | AD7: 0.0080899471 | AE7: 0.04 | AF7: =(AE7-AJ7)/AJ7 -> 0 | AG7: Capse folie 10 mm | AH7: u | AI7: 0.0081179789 | AJ7: 0.04 | AK7: =(AJ7-AO7)/AO7 -> 3 | AL7: Capse folie 10 mm | AM7: buc | AN7: 0.00080808081 | AO7: 0.01 | AP7: =(AO7-AT7)/AT7 -> 0 | AQ7: Capse folie 10 mm | AR7: buc | AS7: 0.00080808081 | AT7: 0.01
A8: Capse OSB 50 mm | B8: Agrafe 50 mm | C8: Capse OSB 50 mm | E8: u | F8: =IF(E8="","",ROUND(G8*(1+$F$2),2)) -> 0.18 | G8: =H8/$G$2 -> 0.15257732 | H8: 0.74 | N8: =(H8-T8)/T8 -> 9.5714286 | O8: Capse OSB 50 mm | Q8: u | R8: =IF(Q8="","",ROUND(S8*(1+$F$2),2)) -> 0.02 | S8: =T8/$G$2 -> 0.01443299 | T8: 0.07 | U8: Capse OSB 50 mm | W8: u | X8: 0.014256619 | Y8: 0.07 | Z8: =(Y8-AE8)/AE8 -> 2.5 | AA8: Capse OSB 50 mm | AC8: u | AD8: 0.0040449736 | AE8: 0.02 | AF8: =(AE8-AJ8)/AJ8 -> 0 | AG8: Capse OSB 50 mm | AH8: u | AI8: 0.0040589895 | AJ8: 0.02 | AK8: =(AJ8-AO8)/AO8 -> 1 | AL8: Capse OSB 50 mm | AM8: buc | AN8: 0.00088888889 | AO8: 0.01 | AP8: =(AO8-AT8)/AT8 -> 0 | AQ8: Capse OSB 50 mm | AR8: buc | AS8: 0.00088888889 | AT8: 0.01
A9: Capse THD 70 mm | B9: Agrafe 70 mm | C9: Capse THD 70 mm | E9: u | F9: =IF(E9="","",ROUND(G9*(1+$F$2),2)) -> 0.03 | G9: =H9/$G$2 -> 0.024742268 | H9: 0.12 | N9: =(H9-T9)/T9 -> 0 | O9: Capse THD 70 mm | Q9: u | R9: =IF(Q9="","",ROUND(S9*(1+$F$2),2)) -> 0.03 | S9: =T9/$G$2 -> 0.024742268 | T9: 0.12 | U9: Capse THD 70 mm | W9: u | X9: 0.024439919 | Y9: 0.12 | Z9: =(Y9-AE9)/AE9 -> 0 | AA9: Capse THD 70 mm | AC9: u | AD9: 0.024269841 | AE9: 0.12 | AF9: =(AE9-AJ9)/AJ9 -> 0 | AG9: Capse THD 70 mm | AH9: u | AI9: 0.024353937 | AJ9: 0.12 | AK9: =(AJ9-AO9)/AO9 -> 0 | AL9: Capse THD 70 mm | AM9: buc | AN9: 0.023030303 | AO9: 0.12 | AP9: =(AO9-AT9)/AT9 -> 0 | AQ9: Capse THD 70 mm | AR9: buc | AS9: 0.023030303 | AT9: 0.12
A10: Cuie 90 / 120 | B10: Clou 90 / 120 | C10: Cuie 90 / 120 | E10: u | F10: =IF(E10="","",ROUND(G10*(1+$F$2),2)) -> 0.05 | G10: =H10/$G$2 -> 0.039175258 | H10: 0.19 | N10: =(H10-T10)/T10 -> 1.4675325 | O10: Cuie 90 / 120 | Q10: u | R10: =IF(Q10="","",ROUND(S10*(1+$F$2),2)) -> 0.02 | S10: =T10/$G$2 -> 0.015876289 | T10: 0.077 | U10: Cuie 90 / 120 | W10: u | X10: 0.015682281 | Y10: 0.077 | Z10: =(Y10-AE10)/AE10 -> -0.3 | AA10: Cuie 90 / 120 | AC10: u | AD10: 0.022247355 | AE10: 0.11 | AF10: =(AE10-AJ10)/AJ10 -> 0 | AG10: Cuie 90 / 120 | AH10: u | AI10: 0.022324442 | AJ10: 0.11 | AK10: =(AJ10-AO10)/AO10 -> 0 | AL10: Cuie 90 / 120 | AM10: buc | AN10: 0.022222222 | AO10: 0.11 | AP10: =(AO10-AT10)/AT10 -> 0 | AQ10: Cuie 90 / 120 | AR10: buc | AS10: 0.022222222 | AT10: 0.11
A11: Domisole | B11: Isolant phonique sol | C11: Domisole | E11: m2 | F11: =IF(E11="","",ROUND(G11*(1+$F$2),2)) -> 4.51 | G11: =H11/$G$2 -> 3.7587629 | H11: 18.23 | N11: =(H11-T11)/T11 -> 0 | O11: Domisole | Q11: m2 | R11: =IF(Q11="","",ROUND(S11*(1+$F$2),2)) -> 4.51 | S11: =T11/$G$2 -> 3.7587629 | T11: 18.23 | U11: Domisole | W11: m2 | X11: 3.712831 | Y11: 18.23 | Z11: =(Y11-AE11)/AE11 -> 0 | AA11: Domisole | AC11: m2 | AD11: 3.6869934 | AE11: 18.23 | AF11: =(AE11-AJ11)/AJ11 -> 0 | AG11: Domisole | AH11: m2 | AI11: 3.6997689 | AJ11: 18.23 | AK11: =(AJ11-AO11)/AO11 -> 0 | AL11: Domisole | AM11: mp | AN11: 3.6828283 | AO11: 18.23 | AP11: =(AO11-AT11)/AT11 -> 0 | AQ11: Domisole | AR11: mp | AS11: 3.6828283 | AT11: 18.23
A12: DWD 16 mm | B12: Panneau medium | C12: DWD 16 mm | E12: m2 | F12: =IF(E12="","",ROUND(G12*(1+$F$2),2)) -> 9.64 | G12: =H12/$G$2 -> 8.0309278 | H12: 38.95 | N12: =(H12-T12)/T12 -> 0 | O12: DWD 16 mm | Q12: m2 | R12: =IF(Q12="","",ROUND(S12*(1+$F$2),2)) -> 9.64 | S12: =T12/$G$2 -> 8.0309278 | T12: 38.95 | U12: DWD 16 mm | W12: m2 | X12: 7.6496945 | Y12: 37.56 | Z12: =(Y12-AE12)/AE12 -> -0.035686778 | AA12: DWD 16 mm | AC12: m2 | AD12: 7.877586 | AE12: 38.95 | AF12: =(AE12-AJ12)/AJ12 -> 0.3661873 | AG12: DWD 16 mm | AH12: m2 | AI12: 5.7860895 | AJ12: 28.51 | AK12: =(AJ12-AO12)/AO12 -> 0 | AL12: DWD 16 mm | AM12: mp | AN12: 5.759596 | AO12: 28.51 | AP12: =(AO12-AT12)/AT12 -> 0 | AQ12: DWD 16 mm | AR12: mp | AS12: 5.759596 | AT12: 28.51
A13: EASY BAND 50MMX25M | B13: Scotch étanche | C13: EASY BAND 50MMX25M | E13: ml | F13: =IF(E13="","",ROUND(G13*(1+$F$2),2)) -> 0.57 | G13: =H13/$G$2 -> 0.4742268 | H13: 2.3 | I13: =1/25 -> 0.04 | J13: ml | K13: 7.6666667 | L13: 37.95 | N13: =(H13-T13)/T13 -> 0.17346939 | O13: EASY BAND 50MMX25M | Q13: ml | R13: =IF(Q13="","",ROUND(S13*(1+$F$2),2)) -> 0.48 | S13: =T13/$G$2 -> 0.40412371 | T13: 1.96 | U13: EASY BAND 50MMX25M | W13: ml | X13: 0.39918534 | Y13: 1.96 | Z13: =(Y13-AE13)/AE13 -> 0.2911726 | AA13: EASY BAND 50MMX25M | AC13: ml | AD13: 0.30701349 | AE13: 1.518 | AF13: =(AE13-AJ13)/AJ13 -> 0 | AG13: EASY BAND 50MMX25M | AH13: ml | AI13: 0.30666667 | AJ13: 1.518 | AK13: =(AJ13-AO13)/AO13 -> 0.025675676 | AL13: EASY BAND 50MMX25M | AM13: ml | AN13: 0.2989899 | AO13: 1.48 | AP13: =(AO13-AT13)/AT13 -> 0 | AQ13: EASY BAND 50MMX25M | AR13: ml | AS13: 0.2989899 | AT13: 1.48
A14: Etrier 360L | B14: Rothoblaast | C14: Etrier 360L | E14: u | F14: =IF(E14="","",ROUND(G14*(1+$F$2),2)) -> 23.01 | G14: =H14/$G$2 -> 19.175258 | H14: 93 | N14: =(H14-T14)/T14 -> 0 | O14: Etrier 360L | Q14: u | R14: =IF(Q14="","",ROUND(S14*(1+$F$2),2)) -> 23.01 | S14: =T14/$G$2 -> 19.175258 | T14: 93 | U14: Etrier 360L | W14: u | X14: 18.940937 | Y14: 93 | Z14: =(Y14-AE14)/AE14 -> 0 | AA14: Etrier 360L | AC14: u | AD14: 18.809127 | AE14: 93 | AF14: =(AE14-AJ14)/AJ14 -> 0 | AG14: Etrier 360L | AH14: u | AI14: 18.874301 | AJ14: 93 | AK14: =(AJ14-AO14)/AO14 -> 1.5280489e-16 | AL14: Etrier 360L | AM14: u | AN14: 18.787879 | AO14: 93 | AP14: =(AO14-AT14)/AT14 -> 0 | AQ14: Etrier 360L | AR14: u | AS14: 18.787879 | AT14: 93
A15: Etude BE France | B15: Etude bureau d'étude France | C15: Etude BE France | E15: j | F15: =IF(E15="","",ROUND(G15*(1+$F$2),2)) -> 734.85 | G15: =H15/$G$2 -> 612.37113 | H15: 2970 | N15: =(H15-T15)/T15 -> 0 | O15: Etude BE France | Q15: j | R15: =IF(Q15="","",ROUND(S15*(1+$F$2),2)) -> 734.85 | S15: =T15/$G$2 -> 612.37113 | T15: 2970 | U15: Etude BE France | W15: j | X15: 604.88798 | Y15: 2970 | Z15: =(Y15-AE15)/AE15 -> 0 | AA15: Etude BE France | AC15: j | AD15: 600.67857 | AE15: 2970 | AF15: =(AE15-AJ15)/AJ15 -> 0 | AG15: Etude BE France | AH15: j | AI15: 602.75993 | AJ15: 2970 | AK15: =(AJ15-AO15)/AO15 -> 0 | AL15: Etude BE France | AM15: j | AN15: 600 | AO15: 2970 | AP15: =(AO15-AT15)/AT15 -> 0 | AQ15: Etude BE France | AR15: j | AS15: 600 | AT15: 2970
A16: Fermacell HD | B16: Fermacell HDl | C16: Fermacell HD | E16: m2 | F16: =IF(E16="","",ROUND(G16*(1+$F$2),2)) -> 24.55 | G16: =H16/$G$2 -> 20.459794 | H16: 99.23 | N16: =(H16-T16)/T16 -> 0.26568878 | O16: Fermacell HD | Q16: m2 | R16: =IF(Q16="","",ROUND(S16*(1+$F$2),2)) -> 19.4 | S16: =T16/$G$2 -> 16.164948 | T16: 78.4 | U16: Fermacell HD 2600*1200*15 | W16: m2 | X16: 18.93279 | Y16: 92.96 | Z16: =(Y16-AE16)/AE16 -> 0.18571429 | AA16: Fermacell HD | AC16: m2 | AD16: 15.856296 | AE16: 78.4 | AF16: =(AE16-AJ16)/AJ16 -> 0 | AG16: Fermacell HD | AH16: m2 | AI16: 15.911239 | AJ16: 78.4 | AK16: =(AJ16-AO16)/AO16 -> -0.060627846 | AL16: Fermacell HD | AM16: mp | AN16: 16.86 | AO16: 83.46 | AP16: =(AO16-AT16)/AT16 -> 0 | AQ16: Fermacell HD | AR16: mp | AS16: 16.86 | AT16: 83.46
A17: Firestop basic sealant | B17: Mastic RF | C17: Firestop basic sealant | E17: boite | F17: =IF(E17="","",ROUND(G17*(1+$F$2),2)) -> 7.92 | G17: =H17/$G$2 -> 6.6020619 | H17: 32.02 | N17: =(H17-T17)/T17 -> 0 | O17: Firestop basic sealant | Q17: boite | R17: =IF(Q17="","",ROUND(S17*(1+$F$2),2)) -> 7.92 | S17: =T17/$G$2 -> 6.6020619 | T17: 32.02 | U17: Firestop basic sealant | W17: boite | X17: 6.5213849 | Y17: 32.02 | Z17: =(Y17-AE17)/AE17 -> 0.035240866 | AA17: Firestop basic sealant | AC17: boite | AD17: 6.2555516 | AE17: 30.93 | AF17: =(AE17-AJ17)/AJ17 -> 0 | AG17: Firestop basic sealant | AH17: boite | AI17: 6.2772272 | AJ17: 30.93 | AK17: =(AJ17-AO17)/AO17 -> -0.037348273 | AL17: Firestop basic sealant | AM17: buc | AN17: 6.49 | AO17: 32.13 | AP17: =(AO17-AT17)/AT17 -> 0 | AQ17: Firestop basic sealant | AR17: buc | AS17: 6.49 | AT17: 32.13
A18: Firestop tape 100x0,06 | B18: Scotch RF | C18: Firestop tape 100x0,06 | E18: boite | F18: =IF(E18="","",ROUND(G18*(1+$F$2),2)) -> 9.8 | G18: =H18/$G$2 -> 8.1690722 | H18: 39.62 | N18: =(H18-T18)/T18 -> 0 | O18: Firestop tape 100x0,06 | Q18: boite | R18: =IF(Q18="","",ROUND(S18*(1+$F$2),2)) -> 9.8 | S18: =T18/$G$2 -> 8.1690722 | T18: 39.62 | U18: Firestop tape 100x0,06 | W18: boite | X18: 8.0692464 | Y18: 39.62 | Z18: =(Y18-AE18)/AE18 -> 0 | AA18: Firestop tape 100x0,06 | AC18: boite | AD18: 8.0130926 | AE18: 39.62 | AF18: =(AE18-AJ18)/AJ18 -> 0 | AG18: Firestop tape 100x0,06 | AH18: boite | AI18: 8.0408581 | AJ18: 39.62 | AK18: =(AJ18-AO18)/AO18 -> 0 | AL18: Firestop tape 100x0,06 | AM18: buc | AN18: 8.0040404 | AO18: 39.62 | AP18: =(AO18-AT18)/AT18 -> 0 | AQ18: Firestop tape 100x0,06 | AR18: buc | AS18: 8.0040404 | AT18: 39.62
A19: Folie antiploaie | B19: Écran pare-pluie | C19: Folie antiploaie | E19: m2 | F19: =IF(E19="","",ROUND(G19*(1+$F$2),2)) -> 0.71 | G19: =H19/$G$2 -> 0.58969072 | H19: 2.86 | N19: =(H19-T19)/T19 -> 0.28395062 | O19: Folie antiploaie | Q19: m2 | R19: =IF(Q19="","",ROUND(S19*(1+$F$2),2)) -> 0.55 | S19: =T19/$G$2 -> 0.45927835 | T19: 2.2275 | U19: Folie antiploaie | W19: m2 | X19: 0.45366599 | Y19: 2.2275 | Z19: =(Y19-AE19)/AE19 -> 0 | AA19: Folie antiploaie | AC19: m2 | AD19: 0.45050893 | AE19: 2.2275 | AF19: =(AE19-AJ19)/AJ19 -> 0 | AG19: Folie antiploaie | AH19: m2 | AI19: 0.45206995 | AJ19: 2.2275
A20: Folie antivapori Sd>28 | B20: Pare vapeur | C20: Folie antivapori Sd>28 | E20: m2 | F20: =IF(E20="","",ROUND(G20*(1+$F$2),2)) -> 1.73 | G20: =H20/$G$2 -> 1.4391753 | H20: 6.98 | N20: =(H20-T20)/T20 -> 0.10094637 | O20: Folie antivapori | Q20: m2 | R20: =IF(Q20="","",ROUND(S20*(1+$F$2),2)) -> 1.57 | S20: =T20/$G$2 -> 1.3072165 | T20: 6.34 | U20: Folie antivapori | W20: m2 | X20: 1.2912424 | Y20: 6.34 | Z20: =(Y20-AE20)/AE20 -> 1.8462402 | AA20: Folie antivapori | AC20: m2 | AD20: 0.45050893 | AE20: 2.2275 | AF20: =(AE20-AJ20)/AJ20 -> 0 | AG20: Folie antivapori | AH20: m2 | AI20: 0.45206995 | AJ20: 2.2275 | AK20: =(AJ20-AO20)/AO20 -> -0.0011210762 | AL20: Folie antivapori | AM20: mp | AN20: 0.45 | AO20: 2.23 | AP20: =(AO20-AT20)/AT20 -> 0 | AQ20: Folie antivapori | AR20: mp | AS20: 0.45 | AT20: 2.23
A21: Lemn 100x45 mm | B21: Bois classe 2 | C21: Lemn 100x45 mm | D21: ST | E21: m3 | F21: =IF(E21="","",ROUND(G21*(1+$F$2),2)) -> 690.31 | G21: =H21/$G$2 -> 575.25773 | H21: 2790 | I21: =0.045*0.1 -> 0.0045 | J21: ml | K21: =L21*$K$2 -> 2.5886598 | L21: =H21*I21 -> 12.555 | N21: =(H21-T21)/T21 -> 0.37777778 | O21: Lemn 100x45 mm | P21: ST | Q21: m3 | R21: =IF(Q21="","",ROUND(S21*(1+$F$2),2)) -> 501.03 | S21: =T21/$G$2 -> 417.52577 | T21: 2025 | U21: Lemn 100x45 mm | V21: ST | W21: m3 | X21: 412.42363 | Y21: 2025 | Z21: =(Y21-AE21)/AE21 -> 0.265625 | AA21: Lemn 100x45 mm | AB21: ST | AC21: m3 | AD21: 323.59788 | AE21: 1600 | AF21: =(AE21-AJ21)/AJ21 -> 0 | AG21: Lemn 100x45 mm | AH21: m3 | AI21: 323.23232 | AJ21: 1600 | AK21: =(AJ21-AO21)/AO21 -> 0.14283265 | AL21: Lemn 100x45 mm | AM21: mc | AN21: 282.83434 | AO21: 1400.03 | AP21: =(AO21-AT21)/AT21 -> 0 | AQ21: Lemn 100x45 mm | AR21: mc | AS21: 282.83434 | AT21: 1400.03
A22: Lemn 100x45 mm talpa | B22: Bois classe 4 | C22: Lemn 100x45 mm talpa | D22: ST | E22: m3 | F22: =IF(E22="","",ROUND(G22*(1+$F$2),2)) -> 690.31 | G22: =H22/$G$2 -> 575.25773 | H22: 2790 | I22: =0.045*0.1 -> 0.0045 | J22: ml | K22: =L22*$K$2 -> 2.5886598 | L22: =H22*I22 -> 12.555 | N22: =(H22-T22)/T22 -> 0.15355991 | O22: Lemn 100x45 mm talpa | P22: ST | Q22: m3 | R22: =IF(Q22="","",ROUND(S22*(1+$F$2),2)) -> 598.42 | S22: =T22/$G$2 -> 498.68041 | T22: 2418.6 | U22: Lemn 100x45 mm talpa | V22: ST | W22: m3 | X22: 492.58656 | Y22: 2418.6 | Z22: =(Y22-AE22)/AE22 -> 0.2093 | AA22: Lemn 100x45 mm talpa | AB22: ST | AC22: m3 | AD22: 404.49736 | AE22: 2000 | AF22: =(AE22-AJ22)/AJ22 -> 0 | AG22: Lemn 100x45 mm talpa | AH22: m3 | AI22: 404.0404 | AJ22: 2000 | AK22: =(AJ22-AO22)/AO22 -> 0.097688816 | AL22: Lemn 100x45 mm talpa | AM22: mc | AN22: 368.08283 | AO22: 1822.01 | AP22: =(AO22-AT22)/AT22 -> 0 | AQ22: Lemn 100x45 mm talpa | AR22: mc | AS22: 368.08283 | AT22: 1822.01
A23: Lemn 150x45 mm | B23: Bois classe 2 | C23: Lemn 150x45 mm | D23: ST | E23: m3 | F23: =IF(E23="","",ROUND(G23*(1+$F$2),2)) -> 690.31 | G23: =H23/$G$2 -> 575.25773 | H23: 2790 | I23: =0.045*0.15 -> 0.00675 | J23: ml | K23: =L23*$K$2 -> 3.8829897 | L23: =H23*I23 -> 18.8325 | N23: =(H23-T23)/T23 -> 0.37777778 | O23: Lemn 150x45 mm | P23: ST | Q23: m3 | R23: =IF(Q23="","",ROUND(S23*(1+$F$2),2)) -> 501.03 | S23: =T23/$G$2 -> 417.52577 | T23: 2025 | U23: Lemn 150x45 mm | V23: ST | W23: m3 | X23: 412.42363 | Y23: 2025 | Z23: =(Y23-AE23)/AE23 -> 0.265625 | AA23: Lemn 150x45 mm | AB23: ST | AC23: m3 | AD23: 323.59788 | AE23: 1600 | AF23: =(AE23-AJ23)/AJ23 -> 0 | AG23: Lemn 150x45 mm | AH23: m3 | AI23: 323.23232 | AJ23: 1600 | AK23: =(AJ23-AO23)/AO23 -> 0.14283265 | AL23: Lemn 150x45 mm | AM23: mc | AN23: 282.83434 | AO23: 1400.03 | AP23: =(AO23-AT23)/AT23 -> 0 | AQ23: Lemn 150x45 mm | AR23: mc | AS23: 282.83434 | AT23: 1400.03
A24: Lemn 150x45 mm talpa | B24: Bois classe 4 | C24: Lemn 150x45 mm talpa | D24: ST | E24: m3 | F24: =IF(E24="","",ROUND(G24*(1+$F$2),2)) -> 690.31 | G24: =H24/$G$2 -> 575.25773 | H24: 2790 | I24: =0.045*0.15 -> 0.00675 | J24: ml | K24: =L24*$K$2 -> 3.8829897 | L24: =H24*I24 -> 18.8325 | N24: =(H24-T24)/T24 -> 0.15384615 | O24: Lemn 150x45 mm talpa | P24: ST | Q24: m3 | R24: =IF(Q24="","",ROUND(S24*(1+$F$2),2)) -> 598.27 | S24: =T24/$G$2 -> 498.5567 | T24: 2418 | U24: Lemn 150x45 mm talpa | V24: ST | W24: m3 | X24: 492.46436 | Y24: 2418 | Z24: =(Y24-AE24)/AE24 -> 0.209 | AA24: Lemn 150x45 mm talpa | AB24: ST | AC24: m3 | AD24: 404.49736 | AE24: 2000 | AF24: =(AE24-AJ24)/AJ24 -> 0 | AG24: Lemn 150x45 mm talpa | AH24: m3 | AI24: 404.0404 | AJ24: 2000 | AK24: =(AJ24-AO24)/AO24 -> 0.12864906 | AL24: Lemn 150x45 mm talpa | AM24: mc | AN24: 357.98586 | AO24: 1772.03 | AP24: =(AO24-AT24)/AT24 -> 0 | AQ24: Lemn 150x45 mm talpa | AR24: mc | AS24: 357.98586 | AT24: 1772.03
A25: Lemn 240x45 mm | B25: Bois classe 2 | C25: Lemn 240x45 mm | D25: ST | E25: m3 | F25: =IF(E25="","",ROUND(G25*(1+$F$2),2)) -> 580.21 | G25: =H25/$G$2 -> 483.50515 | H25: =2300+45 -> 2345 | I25: =0.045*0.24 -> 0.0108 | J25: ml | K25: =L25*$K$2 -> 5.2218557 | L25: =H25*I25 -> 25.326 | N25: =(H25-T25)/T25 -> 0.15802469 | O25: Lemn 240x45 mm | P25: ST | Q25: m3 | R25: =IF(Q25="","",ROUND(S25*(1+$F$2),2)) -> 501.03 | S25: =T25/$G$2 -> 417.52577 | T25: 2025 | U25: Lemn 240x45 mm | V25: ST | W25: m3 | X25: 412.42363 | Y25: 2025 | Z25: =(Y25-AE25)/AE25 -> 0.265625 | AA25: Lemn 240x45 mm | AB25: ST | AC25: m3 | AD25: 323.59788 | AE25: 1600 | AF25: =(AE25-AJ25)/AJ25 -> 0 | AG25: Lemn 240x45 mm | AH25: m3 | AI25: 323.23232 | AJ25: 1600 | AK25: =(AJ25-AO25)/AO25 -> 0.066666667 | AL25: Lemn 240x45 mm | AM25: mc | AN25: 303.0303 | AO25: 1500 | AP25: =(AO25-AT25)/AT25 -> 0 | AQ25: Lemn 240x45 mm | AR25: mc | AS25: 303.0303 | AT25: 1500
A26: Lemn 240x80 mm | B26: KVH | C26: Lemn 240x80 mm | D26: ST | E26: m3 | F26: =IF(E26="","",ROUND(G26*(1+$F$2),2)) -> 629.69 | G26: =H26/$G$2 -> 524.74227 | H26: =2500+45 -> 2545 | I26: =0.08*0.24 -> 0.0192 | J26: ml | K26: =L26*$K$2 -> 10.075052 | L26: =H26*I26 -> 48.864 | N26: =(H26-T26)/T26 -> 0.25679012 | O26: Lemn 240x80 mm | P26: ST | Q26: m3 | R26: =IF(Q26="","",ROUND(S26*(1+$F$2),2)) -> 501.03 | S26: =T26/$G$2 -> 417.52577 | T26: 2025 | U26: Lemn 240x80 mm | V26: ST | W26: m3 | X26: 412.42363 | Y26: 2025 | Z26: =(Y26-AE26)/AE26 -> 0.14601019 | AA26: Lemn 240x80 mm | AB26: ST | AC26: m3 | AD26: 357.37341 | AE26: 1767 | AF26: =(AE26-AJ26)/AJ26 -> 0 | AG26: Lemn 240x80 mm | AH26: m3 | AI26: 356.9697 | AJ26: 1767 | AK26: =(AJ26-AO26)/AO26 -> 0 | AL26: Lemn 240x80 mm | AM26: mc | AN26: 356.9697 | AO26: 1767 | AP26: =(AO26-AT26)/AT26 -> 0 | AQ26: Lemn 240x80 mm | AR26: mc | AS26: 356.9697 | AT26: 1767
A27: Lemn 260x45 mm | B27: Bois classe 2 | C27: Lemn 260x45 mm | D27: ST | E27: m3 | F27: =IF(E27="","",ROUND(G27*(1+$F$2),2)) -> 580.21 | G27: =H27/$G$2 -> 483.50515 | H27: =2300+45 -> 2345 | I27: =0.045*0.26 -> 0.0117 | J27: ml | K27: =L27*$K$2 -> 5.6570103 | L27: =H27*I27 -> 27.4365 | N27: =(H27-T27)/T27 -> 0.15802469 | O27: Lemn 260x45 mm | P27: ST | Q27: m3 | R27: =IF(Q27="","",ROUND(S27*(1+$F$2),2)) -> 501.03 | S27: =T27/$G$2 -> 417.52577 | T27: 2025 | U27: Lemn 260x45 mm | V27: ST | W27: m3 | X27: 412.42363 | Y27: 2025 | Z27: =(Y27-AE27)/AE27 -> 0.265625 | AA27: Lemn 260x45 mm | AB27: ST | AC27: m3 | AD27: 323.59788 | AE27: 1600 | AF27: =(AE27-AJ27)/AJ27 -> 0 | AG27: Lemn 260x45 mm | AH27: m3 | AI27: 323.23232 | AJ27: 1600 | AK27: =(AJ27-AO27)/AO27 -> 0.066666667 | AL27: Lemn 260x45 mm | AM27: mc | AN27: 303.0303 | AO27: 1500 | AP27: =(AO27-AT27)/AT27 -> 0 | AQ27: Lemn 260x45 mm | AR27: mc | AS27: 303.0303 | AT27: 1500
A28: Lemn 260x80 mm | B28: KVH | C28: Lemn 260x80 mm | D28: ST | E28: m3 | F28: =IF(E28="","",ROUND(G28*(1+$F$2),2)) -> 629.69 | G28: =H28/$G$2 -> 524.74227 | H28: =2500+45 -> 2545 | I28: =0.08*0.26 -> 0.0208 | J28: ml | K28: =L28*$K$2 -> 10.914639 | L28: =H28*I28 -> 52.936 | N28: =(H28-T28)/T28 -> 0.25679012 | O28: Lemn 260x80 mm | P28: ST | Q28: m3 | R28: =IF(Q28="","",ROUND(S28*(1+$F$2),2)) -> 501.03 | S28: =T28/$G$2 -> 417.52577 | T28: 2025 | U28: Lemn 260x80 mm | V28: ST | W28: m3 | X28: 412.42363 | Y28: 2025 | Z28: =(Y28-AE28)/AE28 -> 0.14601019 | AA28: Lemn 260x80 mm | AB28: ST | AC28: m3 | AD28: 357.37341 | AE28: 1767 | AF28: =(AE28-AJ28)/AJ28 -> 0 | AG28: Lemn 260x80 mm | AH28: m3 | AI28: 356.9697 | AJ28: 1767 | AK28: =(AJ28-AO28)/AO28 -> 0 | AL28: Lemn 260x80 mm | AM28: mc | AN28: 356.9697 | AO28: 1767 | AP28: =(AO28-AT28)/AT28 -> 0 | AQ28: Lemn 260x80 mm | AR28: mc | AS28: 356.9697 | AT28: 1767
A29: Lemn 50x45 mm | B29: Bois classe 2 | C29: Lemn 50x45 mm | D29: ST | E29: m3 | F29: =IF(E29="","",ROUND(G29*(1+$F$2),2)) -> 629.69 | G29: =H29/$G$2 -> 524.74227 | H29: =2500+45 -> 2545 | I29: =0.045*0.05 -> 0.00225 | J29: ml | K29: =L29*$K$2 -> 1.1806701 | L29: =H29*I29 -> 5.72625 | N29: =(H29-T29)/T29 -> 0.13111111 | O29: Lemn 50x45 mm | P29: ST | Q29: m3 | R29: =IF(Q29="","",ROUND(S29*(1+$F$2),2)) -> 556.7 | S29: =T29/$G$2 -> 463.91753 | T29: 2250 | U29: Lemn 50x45 mm | V29: ST | W29: m3 | X29: 458.24847 | Y29: 2250 | Z29: =(Y29-AE29)/AE29 -> 0.40625 | AA29: Lemn 50x45 mm | AB29: ST | AC29: m3 | AD29: 323.59788 | AE29: 1600 | AF29: =(AE29-AJ29)/AJ29 -> 0 | AG29: Lemn 50x45 mm | AH29: m3 | AI29: 323.23232 | AJ29: 1600 | AK29: =(AJ29-AO29)/AO29 -> 0.14283265 | AL29: Lemn 50x45 mm | AM29: mc | AN29: 282.83434 | AO29: 1400.03 | AP29: =(AO29-AT29)/AT29 -> 0 | AQ29: Lemn 50x45 mm | AR29: mc | AS29: 282.83434 | AT29: 1400.03
A30: Lemn 50x45 mm talpa | B30: Bois classe 4 | C30: Lemn 50x45 mm talpa | D30: ST | E30: m3 | F30: =IF(E30="","",ROUND(G30*(1+$F$2),2)) -> 727.08 | G30: =H30/$G$2 -> 605.89691 | H30: =2545+80*4.92 -> 2938.6 | I30: =0.045*0.05 -> 0.00225 | J30: ml | K30: =L30*$K$2 -> 1.363268 | L30: =H30*I30 -> 6.61185 | N30: =(H30-T30)/T30 -> 0.13301974 | O30: Lemn 50x45 mm talpa | P30: ST | Q30: m3 | R30: =IF(Q30="","",ROUND(S30*(1+$F$2),2)) -> 641.72 | S30: =T30/$G$2 -> 534.76289 | T30: =2200+80*4.92 -> 2593.6 | U30: Lemn 50x45 mm talpa | V30: ST | W30: m3 | X30: 528.22811 | Y30: 2593.6 | Z30: =(Y30-AE30)/AE30 -> 0.2968 | AA30: Lemn 50x45 mm talpa | AB30: ST | AC30: m3 | AD30: 404.49736 | AE30: 2000 | AF30: =(AE30-AJ30)/AJ30 -> 0 | AG30: Lemn 50x45 mm talpa | AH30: m3 | AI30: 404.0404 | AJ30: 2000 | AK30: =(AJ30-AO30)/AO30 -> 0.12864906 | AL30: Lemn 50x45 mm talpa | AM30: mc | AN30: 357.98586 | AO30: 1772.03 | AP30: =(AO30-AT30)/AT30 -> 0 | AQ30: Lemn 50x45 mm talpa | AR30: mc | AS30: 357.98586 | AT30: 1772.03
A31: Lemn Stratificat | B31: Lamellé collé | C31: Lemn Stratificat | E31: m3 | F31: =IF(E31="","",ROUND(G31*(1+$F$2),2)) -> 1039.18 | G31: =H31/$G$2 -> 865.97938 | H31: 4200 | N31: =(H31-T31)/T31 -> 0.004784689 | O31: Lemn Stratificat | Q31: m3 | R31: =IF(Q31="","",ROUND(S31*(1+$F$2),2)) -> 1034.23 | S31: =T31/$G$2 -> 861.85567 | T31: 4180 | U31: Lemn Stratificat | W31: m3 | X31: 851.32383 | Y31: 4180 | Z31: =(Y31-AE31)/AE31 -> 0.045 | AA31: Lemn Stratificat | AC31: m3 | AD31: 808.99471 | AE31: 4000 | AF31: =(AE31-AJ31)/AJ31 -> 0 | AG31: Lemn Stratificat | AH31: m3 | AI31: 811.79789 | AJ31: 4000 | AK31: =(AJ31-AO31)/AO31 -> -0.0023693727 | AL31: Lemn Stratificat | AM31: mp | AN31: 810 | AO31: 4009.5 | AP31: =(AO31-AT31)/AT31 -> 0 | AQ31: Lemn Stratificat | AR31: mp | AS31: 810 | AT31: 4009.5
A32: OSB 8 mm 2,5x1,25 m | B32: OSB 3 | C32: OSB 8 mm 2,5x1,25 m | E32: m2 | F32: =IF(E32="","",ROUND(G32*(1+$F$2),2)) -> 3.09 | G32: =H32/$G$2 -> 2.5731959 | H32: 12.48 | N32: =(H32-T32)/T32 -> -0.50574257 | O32: OSB 12 mm 2,5x1,25 m | Q32: m2 | R32: =IF(Q32="","",ROUND(S32*(1+$F$2),2)) -> 6.25 | S32: =T32/$G$2 -> 5.2061856 | T32: 25.25 | U32: OSB 12 mm 2,5x1,25 m | W32: m2 | X32: 4.5784114 | Y32: 22.48 | Z32: =(Y32-AE32)/AE32 -> -0.036433776 | AA32: OSB 12 mm 2,5x1,25 m | AC32: m2 | AD32: 4.7184616 | AE32: 23.33 | AF32: =(AE32-AJ32)/AJ32 -> 0.0032233873 | AG32: OSB 12 mm 2,5x1,25 m | AH32: m2 | AI32: 4.7195981 | AJ32: 23.25504 | AK32: =(AJ32-AO32)/AO32 -> 0.32281229 | AL32: OSB 12 mm 2,5x1,25 m | AM32: mp | AN32: 3.5515152 | AO32: 17.58 | AP32: =(AO32-AT32)/AT32 -> 0 | AQ32: OSB 12 mm 2,5x1,25 m | AR32: mp | AS32: 3.5515152 | AT32: 17.58
A33: OSB 9 mm 2,5x1,25 m | B33: OSB 3 | C33: OSB 9 mm 2,5x1,25 m | E33: m2 | F33: =IF(E33="","",ROUND(G33*(1+$F$2),2)) -> 3.21 | G33: =H33/$G$2 -> 2.6721649 | H33: 12.96 | N33: =(H33-T33)/T33 -> -0.59052133 | O33: OSB 15 mm 2,5x1,25 m | Q33: m2 | R33: =IF(Q33="","",ROUND(S33*(1+$F$2),2)) -> 7.83 | S33: =T33/$G$2 -> 6.5257732 | T33: 31.65 | U33: OSB 15 mm 2,5x1,25 m | W33: m2 | X33: 5.8615071 | Y33: 28.78 | Z33: =(Y33-AE33)/AE33 -> -0.0099350506 | AA33: OSB 15 mm 2,5x1,25 m | AC33: m2 | AD33: 5.8791264 | AE33: 29.0688 | AF33: =(AE33-AJ33)/AJ33 -> 0 | AG33: OSB 15 mm 2,5x1,25 m | AH33: m2 | AI33: 5.8994976 | AJ33: 29.0688 | AK33: =(AJ33-AO33)/AO33 -> -0.44609756 | AL33: OSB 15 mm 2,5x1,25 m | AM33: mp | AN33: 10.60202 | AO33: 52.48 | AP33: =(AO33-AT33)/AT33 -> 0 | AQ33: OSB 15 mm 2,5x1,25 m | AR33: mp | AS33: 10.60202 | AT33: 52.48
A34: OSB 12 mm 2,5x1,25 m | B34: OSB 3 résistant au feu | C34: OSB 12 mm 2,5x1,25 m | E34: m2 | F34: =IF(E34="","",ROUND(G34*(1+$F$2),2)) -> 5.24 | G34: =H34/$G$2 -> 4.3690722 | H34: 21.19 | N34: =(H34-T34)/T34 -> -0.72417474 | O34: OSB 16 mm RF | Q34: m2 | R34: =IF(Q34="","",ROUND(S34*(1+$F$2),2)) -> 19.01 | S34: =T34/$G$2 -> 15.84 | T34: 76.824 | U34: OSB 16 mm RF | W34: m2 | X34: 13.92668 | Y34: 68.38 | Z34: =(Y34-AE34)/AE34 -> -0.10991357 | AA34: OSB 16 mm RF | AC34: m2 | AD34: 15.537552 | AE34: 76.824 | AF34: =(AE34-AJ34)/AJ34 -> 0 | AG34: OSB 16 mm RF | AH34: m2 | AI34: 15.59139 | AJ34: 76.824 | AK34: =(AJ34-AO34)/AO34 -> -7.8094494e-05 | AL34: OSB 16 mm RF | AM34: mp | AN34: 15.52 | AO34: 76.83 | AP34: =(AO34-AT34)/AT34 -> 0 | AQ34: OSB 16 mm RF | AR34: mp | AS34: 15.52 | AT34: 76.83
A35: OSB 15 mm 2,5x1,25 m | B35: OSB 3 | C35: OSB 15 mm 2,5x1,25 m | E35: m2 | F35: =IF(E35="","",ROUND(G35*(1+$F$2),2)) -> 5.12 | G35: =H35/$G$2 -> 4.2680412 | H35: 20.7 | N35: =(H35-T35)/T35 -> -0.47937626 | O35: OSB 18 mm 2,5x1,25 m | Q35: m2 | R35: =IF(Q35="","",ROUND(S35*(1+$F$2),2)) -> 9.84 | S35: =T35/$G$2 -> 8.1979381 | T35: 39.76 | U35: OSB 18 mm 2,5x1,25 m | W35: m2 | X35: 5.9979633 | Y35: 29.45 | Z35: =(Y35-AE35)/AE35 -> -0.15573857 | AA35: OSB 18 mm 2,5x1,25 m | AC35: m2 | AD35: 7.0549516 | AE35: 34.88256 | AF35: =(AE35-AJ35)/AJ35 -> 0 | AG35: OSB 18 mm 2,5x1,25 m | AH35: m2 | AI35: 7.0793972 | AJ35: 34.88256 | AK35: =(AJ35-AO35)/AO35 -> -0.47466024 | AL35: OSB 18 mm 2,5x1,25 m | AM35: mp | AN35: 13.414141 | AO35: 66.4 | AP35: =(AO35-AT35)/AT35 -> 0 | AQ35: OSB 18 mm 2,5x1,25 m | AR35: mp | AS35: 13.414141 | AT35: 66.4
A36: OSB 16 mm RF | B36: OSB 3 | C36: OSB 16 mm RF | E36: m2 | F36: =IF(E36="","",ROUND(G36*(1+$F$2),2)) -> 19.01 | G36: =H36/$G$2 -> 15.84 | H36: 76.824 | N36: =(H36-T36)/T36 -> 0.66465872 | O36: OSB 22 mm 2,5x1,25 m | Q36: m2 | R36: =IF(Q36="","",ROUND(S36*(1+$F$2),2)) -> 11.42 | S36: =T36/$G$2 -> 9.5154639 | T36: 46.15 | U36: OSB 22 mm 2,5x1,25 m | W36: m2 | X36: 8.5437882 | Y36: 41.95 | Z36: =(Y36-AE36)/AE36 -> -0.016403436 | AA36: OSB 22 mm 2,5x1,25 m | AC36: m2 | AD36: 8.6258252 | AE36: 42.6496 | AF36: =(AE36-AJ36)/AJ36 -> 0 | AG36: OSB 22 mm 2,5x1,25 m | AH36: m2 | AI36: 8.6557138 | AJ36: 42.6496 | AK36: =(AJ36-AO36)/AO36 -> -0.44466667 | AL36: OSB 22 mm 2,5x1,25 m | AM36: mp | AN36: 15.515152 | AO36: 76.8 | AP36: =(AO36-AT36)/AT36 -> 0 | AQ36: OSB 22 mm 2,5x1,25 m | AR36: mp | AS36: 15.515152 | AT36: 76.8
A37: OSB 18 mm 2,5x1,25 m | B37: OSB 3 | C37: OSB 18 mm 2,5x1,25 m | E37: m2 | F37: =IF(E37="","",ROUND(G37*(1+$F$2),2)) -> 9.84 | G37: =H37/$G$2 -> 8.1979381 | H37: 39.76 | N37: =(H37-T37)/T37 -> 1.1115242 | O37: OSB 8 mm 2,5x1,25 m | Q37: m2 | R37: =IF(Q37="","",ROUND(S37*(1+$F$2),2)) -> 4.66 | S37: =T37/$G$2 -> 3.8824742 | T37: 18.83 | U37: OSB 8 mm 2,5x1,25 m | W37: m2 | X37: 3.3421589 | Y37: 16.41 | Z37: =(Y37-AE37)/AE37 -> 0.016728625 | AA37: OSB 8 mm 2,5x1,25 m | AC37: m2 | AD37: 3.2642937 | AE37: 16.14 | AF37: =(AE37-AJ37)/AJ37 -> 0.041064647 | AG37: OSB 8 mm 2,5x1,25 m | AH37: m2 | AI37: 3.1463987 | AJ37: 15.50336 | AK37: =(AJ37-AO37)/AO37 -> -0.16513947 | AL37: OSB 8 mm 2,5x1,25 m | AM37: mp | AN37: 3.75 | AO37: 18.57 | AP37: =(AO37-AT37)/AT37 -> 0 | AQ37: OSB 8 mm 2,5x1,25 m | AR37: mp | AS37: 3.75 | AT37: 18.57
A38: OSB 22 mm 2,5x1,25 m | B38: OSB 3 | C38: OSB 22 mm 2,5x1,25 m | E38: m2 | F38: =IF(E38="","",ROUND(G38*(1+$F$2),2)) -> 7.59 | G38: =H38/$G$2 -> 6.3257732 | H38: 30.68 | N38: =(H38-T38)/T38 -> 0.39454545 | O38: OSB 9 mm 2,5x1,25 m | Q38: m2 | R38: =IF(Q38="","",ROUND(S38*(1+$F$2),2)) -> 5.44 | S38: =T38/$G$2 -> 4.5360825 | T38: 22 | U38: OSB 9 mm 2,5x1,25 m | W38: m2 | X38: 4.4806517 | Y38: 22 | Z38: =(Y38-AE38)/AE38 -> 0.26137531 | AA38: OSB 9 mm 2,5x1,25 m | AC38: m2 | AD38: 3.5274758 | AE38: 17.44128 | AF38: =(AE38-AJ38)/AJ38 -> 0 | AG38: OSB 9 mm 2,5x1,25 m | AH38: m2 | AI38: 3.5396986 | AJ38: 17.44128 | AK38: =(AJ38-AO38)/AO38 -> -0.53114839 | AL38: OSB 9 mm 2,5x1,25 m | AM38: mp | AN38: 7.5151515 | AO38: 37.2 | AP38: =(AO38-AT38)/AT38 -> 0 | AQ38: OSB 9 mm 2,5x1,25 m | AR38: mp | AS38: 7.5151515 | AT38: 37.2
A39: OSB3 22 mm RL | B39: Contreplaqué blanc mélaminé | C39: OSB3 22 mm RL | E39: m2 | F39: =IF(E39="","",ROUND(G39*(1+$F$2),2)) -> 8.35 | G39: =H39/$G$2 -> 6.9587629 | H39: 33.75 | N39: =(H39-T39)/T39 -> -0.6625 | O39: Panneau contreplaqué 19 mm | Q39: m2 | R39: =IF(Q39="","",ROUND(S39*(1+$F$2),2)) -> 24.74 | S39: =T39/$G$2 -> 20.618557 | T39: 100 | U39: Panneau contreplaqué 19 mm | W39: m2 | X39: 20.366599 | Y39: 100 | Z39: =(Y39-AE39)/AE39 -> 0 | AA39: Panneau contreplaqué 19 mm | AC39: m2 | AD39: 20.224868 | AE39: 100 | AF39: =(AE39-AJ39)/AJ39 -> 0 | AG39: Panneau contreplaqué 19 mm | AH39: m2 | AI39: 20.294947 | AJ39: 100 | AK39: =(AJ39-AO39)/AO39 -> 0.075268817 | AL39: panou de placaj 19 mm | AM39: mp | AN39: 18.787879 | AO39: 93 | AP39: =(AO39-AT39)/AT39 -> 0 | AQ39: panou de placaj 19 mm | AR39: mp | AS39: 18.787879 | AT39: 93
A40: Panneau contreplaqué 19 mm | B40: FDB 40 mm | C40: Panneau contreplaqué 19 mm | E40: m2 | F40: =IF(E40="","",ROUND(G40*(1+$F$2),2)) -> 24.74 | G40: =H40/$G$2 -> 20.618557 | H40: 100 | N40: =(H40-T40)/T40 -> 0.92012289 | O40: PAVAWALL | Q40: m2 | R40: =IF(Q40="","",ROUND(S40*(1+$F$2),2)) -> 12.89 | S40: =T40/$G$2 -> 10.738144 | T40: 52.08 | U40: PAVAWALL | W40: m2 | X40: 10.606925 | Y40: 52.08 | Z40: =(Y40-AE40)/AE40 -> 0 | AA40: PAVAWALL | AC40: m2 | AD40: 10.533111 | AE40: 52.08 | AF40: =(AE40-AJ40)/AJ40 -> 0 | AG40: PAVAWALL | AH40: m2 | AI40: 10.569609 | AJ40: 52.08 | AK40: =(AJ40-AO40)/AO40 -> -0.060606061 | AL40: PAVAWALL | AM40: mp | AN40: 11.2 | AO40: 55.44 | AP40: =(AO40-AT40)/AT40 -> 0 | AQ40: PAVAWALL | AR40: mp | AS40: 11.2 | AT40: 55.44
A41: PAVAWALL | B41: Trame | C41: PAVAWALL | E41: m2 | F41: =IF(E41="","",ROUND(G41*(1+$F$2),2)) -> 12.89 | G41: =H41/$G$2 -> 10.738144 | H41: 52.08 | N41: =(H41-T41)/T41 -> 21.942731 | O41: Plasa fibra 50 mp | Q41: m2 | R41: =IF(Q41="","",ROUND(S41*(1+$F$2),2)) -> 0.56 | S41: =T41/$G$2 -> 0.46804124 | T41: 2.27 | U41: Plasa fibra 50 mp | W41: m2 | X41: 0.46232179 | Y41: 2.27 | Z41: =(Y41-AE41)/AE41 -> 0.42767296 | AA41: Plasa fibra 50 mp | AC41: m2 | AD41: 0.3215754 | AE41: 1.59 | AF41: =(AE41-AJ41)/AJ41 -> 0 | AG41: Plasa fibra 50 mp | AH41: m2 | AI41: 0.32268966 | AJ41: 1.59 | AK41: =(AJ41-AO41)/AO41 -> 0 | AL41: Plasa fibra 50 mp | AM41: mp | AN41: 0.32121212 | AO41: 1.59 | AP41: =(AO41-AT41)/AT41 -> 0 | AQ41: Plasa fibra 50 mp | AR41: mp | AS41: 0.32121212 | AT41: 1.59
A42: Plasa fibra 50 mp | B42: Rothoblaast | C42: Plasa fibra 50 mp | E42: m2 | F42: =IF(E42="","",ROUND(G42*(1+$F$2),2)) -> 1.19 | G42: =H42/$G$2 -> 0.98969072 | H42: =240/50 -> 4.8 | N42: =(H42-T42)/T42 -> -0.952 | O42: PPIN | Q42: u | R42: =IF(Q42="","",ROUND(S42*(1+$F$2),2)) -> 24.74 | S42: =T42/$G$2 -> 20.618557 | T42: 100 | U42: PPIN | W42: u | X42: 20.366599 | Y42: 100 | Z42: =(Y42-AE42)/AE42 -> 0 | AA42: PPIN | AC42: u | AD42: 20.224868 | AE42: 100 | AF42: =(AE42-AJ42)/AJ42 -> 0 | AG42: PPIN | AH42: u | AI42: 20.294947 | AJ42: 100 | AK42: =(AJ42-AO42)/AO42 -> 0.075268817 | AL42: PPIN | AM42: u | AN42: 18.787879 | AO42: 93 | AP42: =(AO42-AT42)/AT42 -> 0 | AQ42: PPIN | AR42: u | AS42: 18.787879 | AT42: 93
A43: PPIN | B43: Rothoblaast | C43: PPIN | E43: u | F43: =IF(E43="","",ROUND(G43*(1+$F$2),2)) -> 24.74 | G43: =H43/$G$2 -> 20.618557 | H43: 100 | N43: =(H43-T43)/T43 -> 0 | O43: PPINE | Q43: u | R43: =IF(Q43="","",ROUND(S43*(1+$F$2),2)) -> 24.74 | S43: =T43/$G$2 -> 20.618557 | T43: 100 | U43: PPINE | W43: u | X43: 20.366599 | Y43: 100 | Z43: =(Y43-AE43)/AE43 -> 0 | AA43: PPINE | AC43: u | AD43: 20.224868 | AE43: 100 | AF43: =(AE43-AJ43)/AJ43 -> 0 | AG43: PPINE | AH43: u | AI43: 20.294947 | AJ43: 100 | AK43: =(AJ43-AO43)/AO43 -> 0.075268817 | AL43: PPINE | AM43: u | AN43: 18.787879 | AO43: 93 | AP43: =(AO43-AT43)/AT43 -> 0 | AQ43: PPINE | AR43: u | AS43: 18.787879 | AT43: 93
A44: PPINE | B44: Profile départ FDB | C44: PPINE | E44: u | F44: =IF(E44="","",ROUND(G44*(1+$F$2),2)) -> 24.74 | G44: =H44/$G$2 -> 20.618557 | H44: 100 | N44: =(H44-T44)/T44 -> 5.3131313 | O44: Profil U THD | Q44: ml | R44: =IF(Q44="","",ROUND(S44*(1+$F$2),2)) -> 3.92 | S44: =T44/$G$2 -> 3.2659794 | T44: 15.84 | U44: Profil U THD | W44: ml | X44: 3.2260692 | Y44: 15.84 | Z44: =(Y44-AE44)/AE44 -> 0 | AA44: Profil U THD | AC44: ml | AD44: 3.2036191 | AE44: 15.84 | AF44: =(AE44-AJ44)/AJ44 -> 0 | AG44: Profil U THD | AH44: ml | AI44: 3.2147196 | AJ44: 15.84 | AK44: =(AJ44-AO44)/AO44 -> 1.1214374e-16 | AL44: Profil U THD | AM44: ml | AN44: 3.2 | AO44: 15.84 | AP44: =(AO44-AT44)/AT44 -> 0 | AQ44: Profil U THD | AR44: ml | AS44: 3.2 | AT44: 15.84
A45: Profil U THD | B45: Polystyrène 50 mm | C45: Profil U THD | E45: ml | F45: =IF(E45="","",ROUND(G45*(1+$F$2),2)) -> 3.92 | G45: =H45/$G$2 -> 3.2659794 | H45: 15.84 | N45: =(H45-T45)/T45 -> -0.22536876 | O45: PSE | Q45: m2 | R45: =IF(Q45="","",ROUND(S45*(1+$F$2),2)) -> 5.06 | S45: =T45/$G$2 -> 4.2161731 | T45: 20.448439 | U45: PSE | W45: m2 | X45: 4.1646516 | Y45: 20.448439 | Z45: =(Y45-AE45)/AE45 -> 0 | AA45: PSE | AC45: m2 | AD45: 4.1356698 | AE45: 20.448439 | AF45: =(AE45-AJ45)/AJ45 -> -0.17 | AG45: PSE | AH45: m2 | AI45: 5 | AJ45: 24.636674 | AK45: =(AJ45-AO45)/AO45 -> -0.29367334 | AL45: PSE | AM45: mp | AN45: 7.0464646 | AO45: 34.88 | AP45: =(AO45-AT45)/AT45 -> 0 | AQ45: PSE | AR45: mp | AS45: 7.0464646 | AT45: 34.88
A46: PSE | B46: Traitement | C46: PSE | E46: m2 | F46: =IF(E46="","",ROUND(G46*(1+$F$2),2)) -> 5.06 | G46: =H46/$G$2 -> 4.2161731 | H46: 20.448439 | N46: =(H46-T46)/T46 -> -0.94503108 | O46: Talpa | Q46: m3 | R46: =IF(Q46="","",ROUND(S46*(1+$F$2),2)) -> 92.04 | S46: =T46/$G$2 -> 76.701031 | T46: 372 | U46: Talpa | W46: m3 | X46: 75.763747 | Y46: 372 | Z46: =(Y46-AE46)/AE46 -> 0 | AA46: Talpa | AC46: m3 | AD46: 75.236508 | AE46: 372 | AF46: =(AE46-AJ46)/AJ46 -> 0 | AG46: Talpa | AH46: m3 | AI46: 75.497204 | AJ46: 372 | AK46: =(AJ46-AO46)/AO46 -> 1.5280489e-16 | AL46: Talpa | AM46: mc | AN46: 75.151515 | AO46: 372 | AP46: =(AO46-AT46)/AT46 -> 0 | AQ46: Talpa | AR46: mc | AS46: 75.151515 | AT46: 372
A47: Talpa | B47: Enduit | C47: Talpa | E47: m3 | F47: =IF(E47="","",ROUND(G47*(1+$F$2),2)) -> 92.04 | G47: =H47/$G$2 -> 76.701031 | H47: 372 | I47: =1/25 -> 0.04 | J47: buc | K47: =L47*$K$2 -> 4.742268 | L47: 23 | N47: =(H47-T47)/T47 -> 403.34783 | O47: Tencuiala 25 Kg | Q47: kg | R47: =IF(Q47="","",ROUND(S47*(1+$F$2),2)) -> 0.23 | S47: =T47/$G$2 -> 0.18969072 | T47: 0.92 | U47: Tencuiala 25 Kg | W47: kg | X47: 0.18737271 | Y47: 0.92 | Z47: =(Y47-AE47)/AE47 -> 0 | AA47: Tencuiala 25 Kg | AC47: kg | AD47: 0.18606878 | AE47: 0.92 | AF47: =(AE47-AJ47)/AJ47 -> 0 | AG47: Tencuiala 25 Kg | AH47: kg | AI47: 0.18671351 | AJ47: 0.92 | AK47: =(AJ47-AO47)/AO47 -> -0.66666667 | AL47: Tencuiala 25 Kg | AM47: kg | AN47: 0.55757576 | AO47: 2.76 | AP47: =(AO47-AT47)/AT47 -> 0 | AQ47: Tencuiala 25 Kg | AR47: kg | AS47: 0.55757576 | AT47: 2.76
A48: Tencuiala 25 Kg | B48: FDB 40 mm | C48: Tencuiala 25 Kg | E48: kg | F48: =IF(E48="","",ROUND(G48*(1+$F$2),2)) -> 0.23 | G48: =H48/$G$2 -> 0.18969072 | H48: 0.92 | N48: =(H48-T48)/T48 -> -0.98771203 | O48: THD | Q48: m2 | R48: =IF(Q48="","",ROUND(S48*(1+$F$2),2)) -> 18.52 | S48: =T48/$G$2 -> 15.437113 | T48: 74.87 | U48: THD | W48: m2 | X48: 12.720978 | Y48: 62.46 | Z48: =(Y48-AE48)/AE48 -> 0.5278865 | AA48: THD | AC48: m2 | AD48: 8.2679259 | AE48: 40.88 | AF48: =(AE48-AJ48)/AJ48 -> 0 | AG48: THD | AH48: m2 | AI48: 8.2965744 | AJ48: 40.88 | AK48: =(AJ48-AO48)/AO48 -> -0.14691152 | AL48: THD | AM48: mp | AN48: 9.68 | AO48: 47.92 | AP48: =(AO48-AT48)/AT48 -> 0 | AQ48: THD | AR48: mp | AS48: 9.68 | AT48: 47.92
A49: THD | C49: THD | E49: m2 | F49: =IF(E49="","",ROUND(G49*(1+$F$2),2)) -> 18.52 | G49: =H49/$G$2 -> 15.437113 | H49: 74.87 | N49: =(H49-T49)/T49 -> -0.99382643 | O49: Transport Ro/Fr | Q49: ft | R49: =IF(Q49="","",ROUND(S49*(1+$F$2),2)) -> 3000.62 | S49: =T49/$G$2 -> 2500.5155 | T49: 12127.5 | U49: Transport Ro/Fr | W49: ft | X49: 2469.9593 | Y49: 12127.5 | Z49: =(Y49-AE49)/AE49 -> 0 | AA49: Transport Ro/Fr | AC49: ft | AD49: 2452.7708 | AE49: 12127.5 | AF49: =(AE49-AJ49)/AJ49 -> 0 | AG49: Transport Ro/Fr | AH49: ft | AI49: 2461.2697 | AJ49: 12127.5 | AK49: =(AJ49-AO49)/AO49 -> 0 | AL49: Transport Ro/Fr | AM49: ft | AN49: 2450 | AO49: 12127.5 | AP49: =(AO49-AT49)/AT49 -> 0 | AQ49: Transport Ro/Fr | AR49: ft | AS49: 2450 | AT49: 12127.5
A50: Transport Ro/Fr | B50: Transport | C50: Transport Ro/Fr | E50: ft | F50: =IF(E50="","",ROUND(G50*(1+$F$2),2)) -> 4032.99 | G50: =H50/$G$2 -> 3360.8247 | H50: 16300 | N50: =(H50-T50)/T50 -> 469.1471 | O50: Vata bazaltica 100 mm | Q50: m2 | R50: =IF(Q50="","",ROUND(S50*(1+$F$2),2)) -> 8.58 | S50: =T50/$G$2 -> 7.1484536 | T50: 34.67 | U50: Vata bazaltica 100 mm | W50: m2 | X50: 7.0610998 | Y50: 34.67 | Z50: =(Y50-AE50)/AE50 -> 0.55960414 | AA50: Vata bazaltica 100 mm | AC50: m2 | AD50: 4.4959881 | AE50: 22.23 | AF50: =(AE50-AJ50)/AJ50 -> 0 | AG50: Vata bazaltica 100 mm | AH50: m2 | AI50: 4.5115668 | AJ50: 22.23 | AK50: =(AJ50-AO50)/AO50 -> 0 | AL50: Vata bazaltica 100 mm | AM50: mp | AN50: 4.4909091 | AO50: 22.23 | AP50: =(AO50-AT50)/AT50 -> 0 | AQ50: Vata bazaltica 100 mm | AR50: mp | AS50: 4.4909091 | AT50: 22.23
A51: Vata bazaltica 100 mm | B51: Laine minérale 100 mm | C51: Vata bazaltica 100 mm | E51: m2 | F51: =IF(E51="","",ROUND(G51*(1+$F$2),2)) -> 8.22 | G51: =H51/$G$2 -> 6.8515464 | H51: 33.23 | N51: =(H51-T51)/T51 -> 0.91637832 | O51: Vata bazaltica 50 mm | Q51: m2 | R51: =IF(Q51="","",ROUND(S51*(1+$F$2),2)) -> 4.29 | S51: =T51/$G$2 -> 3.5752577 | T51: 17.34 | U51: Vata bazaltica 50 mm | W51: m2 | X51: 3.5315682 | Y51: 17.34 | Z51: =(Y51-AE51)/AE51 -> 0.55935252 | AA51: Vata bazaltica 50 mm | AC51: m2 | AD51: 2.2490053 | AE51: 11.12 | AF51: =(AE51-AJ51)/AJ51 -> 0 | AG51: Vata bazaltica 50 mm | AH51: m2 | AI51: 2.2567981 | AJ51: 11.12 | AK51: =(AJ51-AO51)/AO51 -> 0 | AL51: Vata bazaltica 50 mm | AM51: mp | AN51: 2.2464646 | AO51: 11.12 | AP51: =(AO51-AT51)/AT51 -> 0 | AQ51: Vata bazaltica 50 mm | AR51: mp | AS51: 2.2464646 | AT51: 11.12
A52: Vata bazaltica 50 mm | B52: Laine minérale 50 mm | C52: Vata bazaltica 50 mm | E52: m2 | F52: =IF(E52="","",ROUND(G52*(1+$F$2),2)) -> 4.1 | G52: =H52/$G$2 -> 3.4206186 | H52: 16.59 | N52: =(H52-T52)/T52 -> -0.68704018 | O52: Vata lemn 100 mm | Q52: m2 | R52: =IF(Q52="","",ROUND(S52*(1+$F$2),2)) -> 13.12 | S52: =T52/$G$2 -> 10.929897 | T52: 53.01 | U52: Vata lemn 100 mm | W52: m2 | X52: 10.040733 | Y52: 49.3 | Z52: =(Y52-AE52)/AE52 -> -0.069986795 | AA52: Vata lemn 100 mm | AC52: m2 | AD52: 10.721202 | AE52: 53.01 | AF52: =(AE52-AJ52)/AJ52 -> 0 | AG52: Vata lemn 100 mm | AH52: m2 | AI52: 10.758352 | AJ52: 53.01 | AK52: =(AJ52-AO52)/AO52 -> -0.060606061 | AL52: Vata lemn 100 mm | AM52: mp | AN52: 11.4 | AO52: 56.43 | AP52: =(AO52-AT52)/AT52 -> 0 | AQ52: Vata lemn 100 mm | AR52: mp | AS52: 11.4 | AT52: 56.43
A53: Vata bazaltica 100 mm 70kg/m3 | C53: Vata bazaltica 100 mm 70kg/m3 | E53: m2 | F53: =IF(E53="","",ROUND(G53*(1+$F$2),2)) -> 11.93 | G53: =H53/$G$2 -> 9.9381443 | H53: 48.2
A54: Vata bazaltica 150 mm 70 kg/m3 | C54: Vata bazaltica 150 mm 70 kg/m3 | E54: m2 | F54: =IF(E54="","",ROUND(G54*(1+$F$2),2)) -> 17.88 | G54: =H54/$G$2 -> 14.901031 | H54: 72.27
A55: Vata lemn 100 mm | C55: Vata lemn 100 mm | E55: m2 | F55: =IF(E55="","",ROUND(G55*(1+$F$2),2)) -> 13.12 | G55: =H55/$G$2 -> 10.929897 | H55: 53.01 | N55: =(H55-T55)/T55 -> 0.98242334 | O55: Vata lemn 50 mm | Q55: m2 | R55: =IF(Q55="","",ROUND(S55*(1+$F$2),2)) -> 6.62 | S55: =T55/$G$2 -> 5.5134021 | T55: 26.74 | U55: Vata lemn 50 mm | W55: m2 | X55: 5.3604888 | Y55: 26.32 | Z55: =(Y55-AE55)/AE55 -> -0.015706806 | AA55: Vata lemn 50 mm | AC55: m2 | AD55: 5.4081296 | AE55: 26.74 | AF55: =(AE55-AJ55)/AJ55 -> 0 | AG55: Vata lemn 50 mm | AH55: m2 | AI55: 5.4268689 | AJ55: 26.74 | AK55: =(AJ55-AO55)/AO55 -> -0.060765718 | AL55: Vata lemn 50 mm | AM55: mp | AN55: 5.75 | AO55: 28.47 | AP55: =(AO55-AT55)/AT55 -> 0 | AQ55: Vata lemn 50 mm | AR55: mp | AS55: 5.75 | AT55: 28.47
A56: Vata lemn 50 mm | B56: Laine de bois 50 mm | C56: Vata lemn 50 mm | E56: m2 | F56: =IF(E56="","",ROUND(G56*(1+$F$2),2)) -> 6.62 | G56: =H56/$G$2 -> 5.5134021 | H56: 26.74 | I56: =0.02*0.04 -> 0.0008 | J56: mc | K56: =L56*$K$2 -> 329.89691 | L56: 1600 | N56: =(H56-T56)/T56 -> 14.193182 | O56: Latori 20x40 mm | Q56: ml | R56: =IF(Q56="","",ROUND(S56*(1+$F$2),2)) -> 0.44 | S56: =T56/$G$2 -> 0.3628866 | T56: =1*0.04*0.02*2200 -> 1.76 | U56: Latori 20x40 mm | W56: ml | X56: 0.35845214 | Y56: 1.76 | Z56: =(Y56-AE56)/AE56 -> 0.375 | AA56: Latori 20x40 mm | AC56: ml | AD56: 0.25887831 | AE56: 1.28 | AF56: =(AE56-AJ56)/AJ56 -> 0 | AG56: Latori 20x40 mm | AH56: ml | AI56: 0.25977533 | AJ56: 1.28
A57: Latori 20x40 mm | B57: Contelatte bois 20x40 mm | C57: Latori 20x40 mm | E57: ml | F57: =IF(E57="","",ROUND(G57*(1+$F$2),2)) -> 0.46 | G57: =H57/$G$2 -> 0.37938144 | H57: =1*0.04*0.02*2300 -> 1.84 | N57: =(H57-T57)/T57 -> -0.99438456 | O57: Etrier 240 L | Q57: u | R57: =IF(Q57="","",ROUND(S57*(1+$F$2),2)) -> 81.07 | S57: =T57/$G$2 -> 67.560364 | T57: 327.66776 | U57: Etrier 240 L | W57: u | X57: 66.734779 | Y57: 327.66776 | Z57: =(Y57-AE57)/AE57 -> 0 | AA57: Etrier 240 L | AC57: u | AD57: 66.270372 | AE57: 327.66776 | AF57: =(AE57-AJ57)/AJ57 -> 0 | AG57: Etrier 240 L | AH57: u | AI57: 66.5 | AJ57: 327.66776
A58: Etrier 240 L | C58: Etrier 240 L | E58: u | F58: =IF(E58="","",ROUND(G58*(1+$F$2),2)) -> 81.07 | G58: =H58/$G$2 -> 67.560364 | H58: 327.66776 | N58: =(H58-T58)/T58 -> -0.11627907 | O58: Etrier 360 L-G | Q58: u | R58: =IF(Q58="","",ROUND(S58*(1+$F$2),2)) -> 91.74 | S58: =T58/$G$2 -> 76.449885 | T58: 370.78194 | U58: Etrier 360 L-G | W58: u | X58: 75.515671 | Y58: 370.78194 | Z58: =(Y58-AE58)/AE58 -> 0 | AA58: Etrier 360 L-G | AC58: u | AD58: 74.990158 | AE58: 370.78194 | AF58: =(AE58-AJ58)/AJ58 -> 0 | AG58: Etrier 360 L-G | AH58: u | AI58: 75.25 | AJ58: 370.78194
A59: Etrier 360 L-G | C59: Etrier 360 L-G | E59: u | F59: =IF(E59="","",ROUND(G59*(1+$F$2),2)) -> 91.74 | G59: =H59/$G$2 -> 76.449885 | H59: 370.78194 | N59: =(H59-T59)/T59 -> 0 | O59: Etrier 360 L-D | Q59: u | R59: =IF(Q59="","",ROUND(S59*(1+$F$2),2)) -> 91.74 | S59: =T59/$G$2 -> 76.449885 | T59: 370.78194 | U59: Etrier 360 L-D | W59: u | X59: 75.515671 | Y59: 370.78194 | Z59: =(Y59-AE59)/AE59 -> 0 | AA59: Etrier 360 L-D | AC59: u | AD59: 74.990158 | AE59: 370.78194 | AF59: =(AE59-AJ59)/AJ59 -> 0 | AG59: Etrier 360 L-D | AH59: u | AI59: 75.25 | AJ59: 370.78194
A60: Etrier 360 L-D | C60: Etrier 360 L-D | E60: u | F60: =IF(E60="","",ROUND(G60*(1+$F$2),2)) -> 91.74 | G60: =H60/$G$2 -> 76.449885 | H60: 370.78194 | N60: =(H60-T60)/T60 -> -0.28333333 | O60: PP1 | Q60: u | R60: =IF(Q60="","",ROUND(S60*(1+$F$2),2)) -> 128.01 | S60: =T60/$G$2 -> 106.67426 | T60: 517.37015 | U60: PP1 | W60: u | X60: 105.3707 | Y60: 517.37015 | Z60: =(Y60-AE60)/AE60 -> 0 | AA60: PP1 | AC60: u | AD60: 104.63743 | AE60: 517.37015 | AF60: =(AE60-AJ60)/AJ60 -> 0 | AG60: PP1 | AH60: u | AI60: 105 | AJ60: 517.37015
A61: PP1 | C61: PP1 | E61: u | F61: =IF(E61="","",ROUND(G61*(1+$F$2),2)) -> 128.01 | G61: =H61/$G$2 -> 106.67426 | H61: 517.37015 | N61: =(H61-T61)/T61 -> -0.3814433 | O61: Platine C-a | Q61: u | R61: =IF(Q61="","",ROUND(S61*(1+$F$2),2)) -> 206.95 | S61: =T61/$G$2 -> 172.45672 | T61: 836.41508 | U61: Platine C-a | W61: u | X61: 170.3493 | Y61: 836.41508 | Z61: =(Y61-AE61)/AE61 -> 0 | AA61: Platine C-a | AC61: u | AD61: 169.16384 | AE61: 836.41508 | AF61: =(AE61-AJ61)/AJ61 -> 0 | AG61: Platine C-a | AH61: u | AI61: 169.75 | AJ61: 836.41508
A62: Platine C-a | C62: Platine C-a | E62: u | F62: =IF(E62="","",ROUND(G62*(1+$F$2),2)) -> 206.95 | G62: =H62/$G$2 -> 172.45672 | H62: 836.41508 | N62: =(H62-T62)/T62 -> 1.3658537 | O62: Platine C-b | Q62: u | R62: =IF(Q62="","",ROUND(S62*(1+$F$2),2)) -> 87.47 | S62: =T62/$G$2 -> 72.894077 | T62: 353.53627 | U62: Platine C-b | W62: u | X62: 72.003314 | Y62: 353.53627 | Z62: =(Y62-AE62)/AE62 -> 0 | AA62: Platine C-b | AC62: u | AD62: 71.502243 | AE62: 353.53627 | AF62: =(AE62-AJ62)/AJ62 -> 0 | AG62: Platine C-b | AH62: u | AI62: 71.75 | AJ62: 353.53627
A63: Platine C-b | C63: Platine C-b | E63: u | F63: =IF(E63="","",ROUND(G63*(1+$F$2),2)) -> 87.47 | G63: =H63/$G$2 -> 72.894077 | H63: 353.53627 | N63: =(H63-T63)/T63 -> 3.1 | O63: Platine C-c | Q63: u | R63: =IF(Q63="","",ROUND(S63*(1+$F$2),2)) -> 21.33 | S63: =T63/$G$2 -> 17.779043 | T63: 86.228359 | U63: Platine C-c | W63: u | X63: 17.561784 | Y63: 86.228359 | Z63: =(Y63-AE63)/AE63 -> 0 | AA63: Platine C-c | AC63: u | AD63: 17.439572 | AE63: 86.228359 | AF63: =(AE63-AJ63)/AJ63 -> 0 | AG63: Platine C-c | AH63: u | AI63: 17.5 | AJ63: 86.228359
A64: Platine C-c | C64: Platine C-c | E64: u | F64: =IF(E64="","",ROUND(G64*(1+$F$2),2)) -> 21.33 | G64: =H64/$G$2 -> 17.779043 | H64: 86.228359 | N64: =(H64-T64)/T64 -> -0.9609375 | O64: Platine A | Q64: u | R64: =IF(Q64="","",ROUND(S64*(1+$F$2),2)) -> 546.17 | S64: =T64/$G$2 -> 455.1435 | T64: 2207.446 | U64: Platine A | W64: u | X64: 449.58167 | Y64: 2207.446 | Z64: =(Y64-AE64)/AE64 -> 0 | AA64: Platine A | AC64: u | AD64: 446.45303 | AE64: 2207.446 | AF64: =(AE64-AJ64)/AJ64 -> 0 | AG64: Platine A | AH64: u | AI64: 448 | AJ64: 2207.446
A65: Platine A | C65: Platine A | E65: u | F65: =IF(E65="","",ROUND(G65*(1+$F$2),2)) -> 546.17 | G65: =H65/$G$2 -> 455.1435 | H65: 2207.446 | N65: =(H65-T65)/T65 -> 1.6947368 | O65: Platine B | Q65: u | R65: =IF(Q65="","",ROUND(S65*(1+$F$2),2)) -> 202.68 | S65: =T65/$G$2 -> 168.90091 | T65: 819.16941 | U65: Platine B | W65: u | X65: 166.83695 | Y65: 819.16941 | Z65: =(Y65-AE65)/AE65 -> 0 | AA65: Platine B | AC65: u | AD65: 165.67593 | AE65: 819.16941 | AF65: =(AE65-AJ65)/AJ65 -> 0 | AG65: Platine B | AH65: u | AI65: 166.25 | AJ65: 819.16941
A66: Platine B | C66: Platine B | E66: u | F66: =IF(E66="","",ROUND(G66*(1+$F$2),2)) -> 202.68 | G66: =H66/$G$2 -> 168.90091 | H66: 819.16941 | N66: =(H66-T66)/T66 -> -0.34482759 | O66: Console | Q66: u | R66: =IF(Q66="","",ROUND(S66*(1+$F$2),2)) -> 309.36 | S66: =T66/$G$2 -> 257.79612 | T66: 1250.3112 | U66: Console | W66: u | X66: 254.64587 | Y66: 1250.3112 | Z66: =(Y66-AE66)/AE66 -> 0 | AA66: Console | AC66: u | AD66: 252.87379 | AE66: 1250.3112 | AF66: =(AE66-AJ66)/AJ66 -> 0 | AG66: Console | AH66: u | AI66: 253.75 | AJ66: 1250.3112
A67: Console | C67: Console | E67: u | F67: =IF(E67="","",ROUND(G67*(1+$F$2),2)) -> 309.36 | G67: =H67/$G$2 -> 257.79612 | H67: 1250.3112 | N67: =(H67-T67)/T67 -> 0.36424731 | O67: Poteaux | Q67: u | R67: =IF(Q67="","",ROUND(S67*(1+$F$2),2)) -> 226.76 | S67: =T67/$G$2 -> 188.96583 | T67: 916.48427 | U67: Poteaux | W67: u | X67: 186.65667 | Y67: 916.48427 | Z67: =(Y67-AE67)/AE67 -> 0 | AA67: Poteaux | AC67: u | AD67: 185.35773 | AE67: 916.48427 | AF67: =(AE67-AJ67)/AJ67 -> 0 | AG67: Poteaux | AH67: u | AI67: 186 | AJ67: 916.48427
A68: Poteaux | C68: Poteaux | E68: u | F68: =IF(E68="","",ROUND(G68*(1+$F$2),2)) -> 226.76 | G68: =H68/$G$2 -> 188.96583 | H68: 916.48427 | N68: =(H68-T68)/T68 -> 0.047887324 | O68: Garde-corps | Q68: ml | R68: =IF(Q68="","",ROUND(S68*(1+$F$2),2)) -> 216.4 | S68: =T68/$G$2 -> 180.33029 | T68: 874.60193 | U68: Garde-corps | W68: ml | X68: 178.12667 | Y68: 874.60193 | Z68: =(Y68-AE68)/AE68 -> 0 | AA68: Garde-corps | AC68: ml | AD68: 176.88708 | AE68: 874.60193 | AF68: =(AE68-AJ68)/AJ68 -> 0 | AG68: Garde-corps | AH68: ml | AI68: 177.5 | AJ68: 874.60193
A69: Garde-corps | C69: Garde-corps | E69: ml | F69: =IF(E69="","",ROUND(G69*(1+$F$2),2)) -> 216.4 | G69: =H69/$G$2 -> 180.33029 | H69: 874.60193 | N69: =(H69-T69)/T69 -> 4.0028185 | O69: Bardage | Q69: m2 | R69: =IF(Q69="","",ROUND(S69*(1+$F$2),2)) -> 43.25 | S69: =T69/$G$2 -> 36.04574 | T69: 174.82184 | U69: Bardage | W69: m2 | X69: 35.605262 | Y69: 174.82184 | Z69: =(Y69-AE69)/AE69 -> 0 | AA69: Bardage | AC69: m2 | AD69: 35.357486 | AE69: 174.82184 | AF69: =(AE69-AJ69)/AJ69 -> 0 | AG69: Bardage | AH69: mp | AI69: 35.48 | AJ69: 174.82184
